Workbook

Sheet README
A1: ملف تتبّع إكمال الفرونت — Academia
A3: الإصدار | B3: v1.7
A4: آخر تحديث | B4: 2026-10-01
A5: الكاتب الوحيد للملف | B5: المنسّق (جلسة التتبع). الجلسات المتوازية لا تعدّل هذا الملف — ترسل تقريرًا بالصيغة أدناه.
A7: الهدف | B7: إكمال الـ19 متطلبًا (13 غير جاهز + 6 جزئي) من تقرير جاهزية الفرونت بالاعتماد على Swagger الحالي وSRS، مع 7 FRs داعمة لازمة لاكتمال المسارات، بدون تعارض بين عدة جلسات تعمل بالتوازي. هذا الملف خطة وتتبّع فقط — لم تُكتب أي أسطر كود بعد.
A8: المصادر المعتمدة | B8: Swagger_UI.pdf (تاريخ 2026-09-22) · SRS_1__updated_.docx · Frontend_Readiness_Audit_Report.pdf · Frontend.zip (الكود). ملفات md/docs القديمة بالمشروع غير معتمدة.
A9: خريطة الأوراق | B9: Dashboard: ملخص محسوب · BackendChecklist: كل ما نحتاجه من الباك اند + هل وصل · Availability: حجم كل WP + ما يمكن بدؤه الآن + JSON · ParallelPlan: التوازي والدمج · WorkPackages: 20 حزمة (WP-00 + WP-J + 17 + QA) · Tasks: المصدر الوحيد للحالة · FR_Matrix: تتبّع كل FR · UAT: معايير القبول · FileOwnership: مالك كل ملف + كشف التعارض · Contracts: واجهات المكونات + مفاتيح الكاش · API_Map: كل endpoint ↔ الكود · Discrepancies: فروقات Swagger/الكود · OpenQuestions: أسئلة وافتراضات افتراضية · Assumptions_Risks · ChangeRequests · SessionLog · Conventions · Lists
A10: ألوان الخلايا | B10: أصفر فاتح = إدخال يدوي · أزرق فاتح = صيغة (لا تعدّلها) · أبيض = خطة ثابتة (لا تغيّر إلا بقرار المنسّق)
A11: حالات المهام | B11: لم يبدأ · قيد التنفيذ · قيد المراجعة · متوقف · مكتمل · مؤجل. «مكتمل» لا تُعتمد إلا بعد تشغيل npm run validate محليًا (البيئة هنا بلا شبكة).
A12: بروتوكول التحديث | B12: 1) الجلسة تنفّذ WP واحدًا فقط. 2) تنتهي بتقرير نهاية الجلسة (أدناه). 3) المنسّق يلصق التقارير ويطلب «حدّث التتبع» ← يُحدَّث الملف دفعة واحدة، تُرفع النسخة، ويُضاف صف بـ SessionLog.
A13: قالب بداية جلسة | B13: قالب بداية جلسة: «نفّذ WP-xx فقط من ملف التتبع (النسخة vN). اقرأ: WorkPackages + Tasks (مهام WP-xx) + FileOwnership + Contracts + Conventions. لا تعدّل أي ملف ليس مملوكًا لـ WP-xx. المصادر المعتمدة: Swagger + SRS + تقرير الجاهزية. لا تعتمد على ملفات docs القديمة. عند الانتهاء أعطني تقرير الجلسة بصيغة SessionLog.»
A14: قالب نهاية جلسة | B14: قالب تقرير نهاية جلسة (يُنسخ كما هو): WP: ... | الجلسة: ... | التاريخ: ... المهام: [ID: الحالة] ... (مكتمل/قيد التنفيذ/متوقف + سبب) الملفات المعدّلة: ... نتيجة npm run validate: ... افتراضات جديدة / أسئلة مفتوحة: ... طلبات تغيير (CR): ... الخطوة التالية: ...
A15: قبل أي كود | B15: WP-00 أولًا. وقبله: الإجابة على الأسئلة الحاجبة (OpenQuestions) ولصق عينات JSON (API_Map: عمود «عينة مطلوبة»).

Sheet Dashboard
A1: لوحة المتابعة (Dashboard)
A2: كل الأرقام محسوبة تلقائيًا من الأوراق الأخرى. لا تحرّرها يدويًا.
A3: نسخة التتبع | B3: =README!B3
A4: آخر تحديث | B4: =README!B4
A6: 1) تقدّم المهام
A7: إجمالي المهام | B7: =COUNTA(Tasks!$A$5:$A$300)
A8: مكتمل | B8: =COUNTIF(Tasks!$M$5:$M$300,"مكتمل")
A9: قيد التنفيذ | B9: =COUNTIF(Tasks!$M$5:$M$300,"قيد التنفيذ")
A10: قيد المراجعة | B10: =COUNTIF(Tasks!$M$5:$M$300,"قيد المراجعة")
A11: متوقف | B11: =COUNTIF(Tasks!$M$5:$M$300,"متوقف")
A12: لم يبدأ | B12: =COUNTIF(Tasks!$M$5:$M$300,"لم يبدأ")
A13: مؤجل | B13: =COUNTIF(Tasks!$M$5:$M$300,"مؤجل")
A14: نسبة الإنجاز الكلية | B14: =IF(B7=0,0,B8/B7)
A15: إنجاز Wave 0 | B15: =IF(COUNTIF(Tasks!$C$5:$C$300,"Wave 0")=0,0,COUNTIFS(Tasks!$C$5:$C$300,"Wave 0",Tasks!$M$5:$M$300,"مكتمل")/COUNTIF(Tasks!$C$5:$C$300,"Wave 0"))
A16: إنجاز Wave 1 | B16: =IF(COUNTIF(Tasks!$C$5:$C$300,"Wave 1")=0,0,COUNTIFS(Tasks!$C$5:$C$300,"Wave 1",Tasks!$M$5:$M$300,"مكتمل")/COUNTIF(Tasks!$C$5:$C$300,"Wave 1"))
A17: إنجاز Wave 2 | B17: =IF(COUNTIF(Tasks!$C$5:$C$300,"Wave 2")=0,0,COUNTIFS(Tasks!$C$5:$C$300,"Wave 2",Tasks!$M$5:$M$300,"مكتمل")/COUNTIF(Tasks!$C$5:$C$300,"Wave 2"))
A19: 2) جاهزية الفرونت مقابل الـ30 FR في التقرير
A20: إجمالي FRs ضمن التقرير | B20: =COUNTIF(FR_Matrix!$I$5:$I$60,"نعم")
A21: الأساس: جاهز بالتقرير | B21: =COUNTIFS(FR_Matrix!$I$5:$I$60,"نعم",FR_Matrix!$G$5:$G$60,"جاهز")
A22: الأساس: جزئي | B22: =COUNTIFS(FR_Matrix!$I$5:$I$60,"نعم",FR_Matrix!$G$5:$G$60,"جزئي")
A23: الأساس: غير جاهز | B23: =COUNTIFS(FR_Matrix!$I$5:$I$60,"نعم",FR_Matrix!$G$5:$G$60,"غير جاهز")
A24: نسبة الجاهزية الأساسية | B24: =IF(B20=0,0,B21/B20)
A25: الآن: جاهز (أصلي + أُنجز وتم قبوله) | B25: =COUNTIFS(FR_Matrix!$I$5:$I$60,"نعم",FR_Matrix!$Q$5:$Q$60,"جاهز (أصلي)")+COUNTIFS(FR_Matrix!$I$5:$I$60,"نعم",FR_Matrix!$Q$5:$Q$60,"جاهز")
A26: الآن: مكتمل – بانتظار UAT | B26: =COUNTIFS(FR_Matrix!$I$5:$I$60,"نعم",FR_Matrix!$Q$5:$Q$60,"مكتمل – بانتظار UAT")
A27: الآن: قيد التنفيذ | B27: =COUNTIFS(FR_Matrix!$I$5:$I$60,"نعم",FR_Matrix!$Q$5:$Q$60,"قيد التنفيذ")
A28: الآن: لم يبدأ | B28: =COUNTIFS(FR_Matrix!$I$5:$I$60,"نعم",FR_Matrix!$Q$5:$Q$60,"لم يبدأ")
A29: نسبة الجاهزية الحالية | B29: =IF(B20=0,0,B25/B20)
A30: الهدف | B30: 1
A32: 3) اختبارات القبول (UAT)
A33: إجمالي بنود UAT | B33: =COUNTA(UAT!$A$5:$A$300)
A34: نجح | B34: =COUNTIF(UAT!$H$5:$H$300,"نجح")
A35: فشل | B35: =COUNTIF(UAT!$H$5:$H$300,"فشل")
A36: لم يُختبر | B36: =COUNTIF(UAT!$H$5:$H$300,"لم يُختبر")
A37: نسبة النجاح | B37: =IF(B33=0,0,B34/B33)
A39: 4) مخاطر التوازي والعوائق
A40: أسئلة حاجبة مفتوحة | B40: =COUNTIFS(OpenQuestions!$E$5:$E$60,"حاجب",OpenQuestions!$H$5:$H$60,"مفتوح")
A41: كل الأسئلة المفتوحة | B41: =COUNTIF(OpenQuestions!$H$5:$H$60,"مفتوح")
A42: فروقات Swagger مفتوحة | B42: =COUNTIF(Discrepancies!$G$5:$G$60,"مفتوح")
A43: مهام متوقفة | B43: =COUNTIF(Tasks!$M$5:$M$300,"متوقف")
A44: طلبات تغيير (CR) مفتوحة | B44: =COUNTIF(ChangeRequests!$G$6:$G$40,"مفتوح")
A45: ملفات بمالكين مكرّرين (يجب 0) | B45: =COUNTIF(FileOwnership!$G$5:$G$300,"⚠ مكرر")
A46: عينات JSON مطلوبة ولم تصل | B46: =COUNTIFS(API_Map!$K$5:$K$80,"نعم",API_Map!$L$5:$L$80,"لا")
A47: عناصر الباك اند الجاهزة (من BackendChecklist) | B47: =COUNTIF(BackendChecklist!$H$5:$H$30,"نعم")&" / "&COUNTIF(BackendChecklist!$A$5:$A$30,"NE-*")
A49: 5) حالة كل WP
A50: WP | B50: الاسم | C50: Wave | D50: % الإنجاز | E50: الحالة | F50: المسؤول
A51: =WorkPackages!A5 | B51: =WorkPackages!B5 | C51: =WorkPackages!C5 | D51: =WorkPackages!O5 | E51: =WorkPackages!P5 | F51: =WorkPackages!I5
A52: =WorkPackages!A6 | B52: =WorkPackages!B6 | C52: =WorkPackages!C6 | D52: =WorkPackages!O6 | E52: =WorkPackages!P6 | F52: =WorkPackages!I6
A53: =WorkPackages!A7 | B53: =WorkPackages!B7 | C53: =WorkPackages!C7 | D53: =WorkPackages!O7 | E53: =WorkPackages!P7 | F53: =WorkPackages!I7
A54: =WorkPackages!A8 | B54: =WorkPackages!B8 | C54: =WorkPackages!C8 | D54: =WorkPackages!O8 | E54: =WorkPackages!P8 | F54: =WorkPackages!I8
A55: =WorkPackages!A9 | B55: =WorkPackages!B9 | C55: =WorkPackages!C9 | D55: =WorkPackages!O9 | E55: =WorkPackages!P9 | F55: =WorkPackages!I9
A56: =WorkPackages!A10 | B56: =WorkPackages!B10 | C56: =WorkPackages!C10 | D56: =WorkPackages!O10 | E56: =WorkPackages!P10 | F56: =WorkPackages!I10
A57: =WorkPackages!A11 | B57: =WorkPackages!B11 | C57: =WorkPackages!C11 | D57: =WorkPackages!O11 | E57: =WorkPackages!P11 | F57: =WorkPackages!I11
A58: =WorkPackages!A12 | B58: =WorkPackages!B12 | C58: =WorkPackages!C12 | D58: =WorkPackages!O12 | E58: =WorkPackages!P12 | F58: =WorkPackages!I12
A59: =WorkPackages!A13 | B59: =WorkPackages!B13 | C59: =WorkPackages!C13 | D59: =WorkPackages!O13 | E59: =WorkPackages!P13 | F59: =WorkPackages!I13
A60: =WorkPackages!A14 | B60: =WorkPackages!B14 | C60: =WorkPackages!C14 | D60: =WorkPackages!O14 | E60: =WorkPackages!P14 | F60: =WorkPackages!I14
A61: =WorkPackages!A15 | B61: =WorkPackages!B15 | C61: =WorkPackages!C15 | D61: =WorkPackages!O15 | E61: =WorkPackages!P15 | F61: =WorkPackages!I15
A62: =WorkPackages!A16 | B62: =WorkPackages!B16 | C62: =WorkPackages!C16 | D62: =WorkPackages!O16 | E62: =WorkPackages!P16 | F62: =WorkPackages!I16
... A70: =WorkPackages!A24 | B70: =WorkPackages!B24 | C70: =WorkPackages!C24 | D70: =WorkPackages!O24 | E70: =WorkPackages!P24 | F70: =WorkPackages!I24

Sheet BackendChecklist
A1: المطلوب من فريق الباك اند (عينات JSON + قرارات) — هل أصبح جاهزًا؟
A2: غيّر عمود «جاهز؟» إلى نعم/جزئي/لا عند الاستلام. عمود «مهام تنتظر» يحسب كم مهمة ما زالت معلّقة عليه. تُحسب «حالة الاعتماد» لكل مهمة بورقة Tasks تلقائيًا.
A4: NE | B4: الوصف | C4: النوع | D4: Endpoint(s) | E4: أسئلة مرتبطة (OpenQuestions) | F4: المطلوب بالضبط | G4: تفتح المهام | H4: جاهز؟ | I4: تاريخ الاستلام | J4: مهام تنتظر الآن | K4: ملاحظات
A5: NE-01 | B5: طلبات الحجز وإعادة الجدولة (جهة المعلم) | C5: عينة JSON | D5: GET Booking/TeacherBookings?status= · GET Booking/TeacherRescheduleRequests?status= | E5: Q-14 | F5: رد حقيقي لكل endpoint (حجز واحد على الأقل بكل حالة موجودة)، وأسماء حالات إعادة الجدولة 1..4 | G5: T5-01، T5-02، T5-03، T5-04، T5-06 | H5: لا | J5: =COUNTIFS(Tasks!$W$5:$W$300,A5,Tasks!$M$5:$M$300,"<>مكتمل")
A6: NE-02 | B6: تفاصيل حجز الطالب | C6: عينة JSON + قرارات | D6: GET Student/GetBooking?id= | E6: Q-08, Q-09, Q-10 | F6: رد حجز مؤكد وآخر مكتمل؛ هل فيه isRated/تقييم؟ وهل يرجع سياسة الإلغاء/المهلة؟ وقواعد أهلية إعادة الجدولة | G6: S2-01، S2-02، S2-05، S4-02، S4-03 | H6: لا | J6: =COUNTIFS(Tasks!$W$5:$W$300,A6,Tasks!$M$5:$M$300,"<>مكتمل")
A7: NE-03 | B7: حالة دفع الحجز | C7: عينة JSON + قرار | D7: GET Student/BookingPayment?bookingId= | E7: Q-06 | F7: رد لحجز مؤكد وآخر رصيده غير كافٍ؛ ومتى يُخصم المبلغ فعليًا | G7: W1-01، W1-05 | H7: لا | J7: =COUNTIFS(Tasks!$W$5:$W$300,A7,Tasks!$M$5:$M$300,"<>مكتمل")
A8: NE-04 | B8: طلبات إعادة جدولة الطالب | C8: عينة JSON | D8: GET Student/MyRescheduleRequests | E8: — | F8: رد بطلب معلّق وآخر مرفوض/موافق عليه + أسماء الحالات | G8: S3-02 | H8: لا | J8: =COUNTIFS(Tasks!$W$5:$W$300,A8,Tasks!$M$5:$M$300,"<>مكتمل")
A9: NE-05 | B9: تفاصيل الدرس (طالب) | C9: عينة JSON | D9: GET Student/GetLesson?id= | E9: — | F9: درس حضوري (فيه القاعة) وآخر أونلاين (فيه المنصة والرابط وcanJoin) | G9: S5-01، S5-02، S5-03 | H9: لا | J9: =COUNTIFS(Tasks!$W$5:$W$300,A9,Tasks!$M$5:$M$300,"<>مكتمل")
A10: NE-06 | B10: تفاصيل الكورس المسجَّل | C10: عينة JSON | D10: GET Student/GetCourse?id= | E10: — | F10: كورس فيه مجموعة ودروس + كورس بلا دروس | G10: S6-01، S6-03، S6-04 | H10: لا | J10: =COUNTIFS(Tasks!$W$5:$W$300,A10,Tasks!$M$5:$M$300,"<>مكتمل")
A11: NE-07 | B11: سجل حضور الطالب | C11: عينة JSON | D11: GET Student/Attendance?from&to&courseId | E11: — | F11: رد بسجلات بالحالات الأربع وهل يرجع نسبة؟ | G11: S7-01، S7-03، S7-04، S7-05 | H11: لا | J11: =COUNTIFS(Tasks!$W$5:$W$300,A11,Tasks!$M$5:$M$300,"<>مكتمل")
A12: NE-08 | B12: نتائج امتحانات الطالب | C12: عينة JSON | D12: GET Student/ExamResults?courseId | E12: — | F12: رد بعدة نتائج (العنوان/التاريخ/الدرجة/المجموع/الملاحظات) | G12: S8-01، S8-02، S8-03 | H12: لا | J12: =COUNTIFS(Tasks!$W$5:$W$300,A12,Tasks!$M$5:$M$300,"<>مكتمل")
A13: NE-09 | B13: كورس المعلم + المجموعة | C13: عينة JSON + قرارات | D13: GET Course/GetMineById?id= | E13: Q-02, Q-03 | F13: شكل الرد (هل فيه groupId/المجموعات؟ هل لكورس أكثر من مجموعة؟)، وهل CreateEdit يأخذ teacherId من الجلسة؟ | G13: T1-07، T2-01، T2-02، T2-04، T2-05، T2-06 | H13: لا | J13: =COUNTIFS(Tasks!$W$5:$W$300,A13,Tasks!$M$5:$M$300,"<>مكتمل")
A14: NE-10 | B14: قائمة كورسات المعلم | C14: عينة JSON + قرار | D14: POST Course/GetAll (بحساب معلم) | E14: Q-01 | F14: هل يرجع كورسات المعلم الحالي فقط أم الكل؟ | G14: T1-01 | H14: لا | J14: =COUNTIFS(Tasks!$W$5:$W$300,A14,Tasks!$M$5:$M$300,"<>مكتمل")
A15: NE-11 | B15: طلاب المجموعة | C15: عينة JSON | D15: GET Course/GetGroupStudents?groupId&keyword | E15: Q-02 | F15: رد بطلاب (الحقول المرجعة) | G15: T3-01، T3-02، T3-03، T3-04 | H15: لا | J15: =COUNTIFS(Tasks!$W$5:$W$300,A15,Tasks!$M$5:$M$300,"<>مكتمل")
A16: NE-12 | B16: جدول دروس الكورس (معلم) | C16: عينة JSON | D16: GET Lesson/GetSchedule?courseId&groupId | E16: Q-02 | F16: رد بدروس حضورية وأونلاين | G16: T4-01، T4-05 | H16: لا | J16: =COUNTIFS(Tasks!$W$5:$W$300,A16,Tasks!$M$5:$M$300,"<>مكتمل")
A17: NE-13 | B17: مصدر المادة/التصنيف/الصف (IDs) | C17: عينة JSON + قرار | D17: GET Teacher/CreateEditModal · POST Constant/GetAll | E17: Q-04 | F17: من أين نجلب subjectId/categoryId/gradeId؟ مع الرد الفعلي (وأي parentId لـConstant) | G17: T1-03، T1-04، T1-05، T1-06، S1-03، S1-05 | H17: لا | J17: =COUNTIFS(Tasks!$W$5:$W$300,A17,Tasks!$M$5:$M$300,"<>مكتمل")
A18: NE-14 | B18: تحقق اختياري: أنواع موجودة بالكود قد تكون قديمة بعد تحديث الباك اند (لا تحجب أي مهمة) | C18: تحقق اختياري | D18: GET Student/Dashboard · Student/Schedule · Student/Progress · Parent/MyChildren · Parent/ChildAttendance · Parent/ChildExamResults · Wallet/MyWallet · POST Wallet/GetTransactionHistory · Teacher/PublicProfile · Teacher/Availability | E18: — | F18: هذه الردود غير موثّقة بالـSwagger أيضًا، لكن أنواعها منسوخة بالكود من DTOs الباك اند. إن تغيّر الباك اند قد تكون قديمة؛ عيّنة واحدة لكل endpoint تكفي للتأكد | H18: لا | J18: =COUNTIFS(Tasks!$W$5:$W$300,A18,Tasks!$M$5:$M$300,"<>مكتمل")
A20: قرارات/أسئلة لا تحجب بدء مهمة لكنها تغيّر السلوك أو النصوص (تفاصيلها بورقة OpenQuestions): Q-06 · Q-07 · Q-11 · Q-12 · Q-14 · Q-15 · Q-18 · Q-19 · Q-20 · Q-21. وQ-17 (حسابات اختبار) تحجب QA فقط.

Sheet Availability
A1: التوفّر والتوازي وحجم كل حزمة
A2: محسوب من Tasks. نقاط الجهد = S×1 + M×3 + L×5 (تقدير نسبي للمقارنة فقط، وليس ساعات). الأصفر = قابل للتعديل.
A3: وزن S | B3: 1 | C3: وزن M | D3: 3 | E3: وزن L | F3: 5
A5: WP | B5: الاسم | C5: Wave | D5: عدد المهام | E5: S | F5: M | G5: L | H5: نقاط الجهد | I5: JSON: نعم | J5: JSON: جزئي | K5: JSON: لا | L5: بوابة البدء (WP) | M5: يمكن توازيه مع | N5: ملاحظة
A6: WP-00 | B6: الأساس المشترك (Foundation) | C6: Wave 0 | D6: =COUNTIF(Tasks!$B$5:$B$300,A6) | E6: =COUNTIFS(Tasks!$B$5:$B$300,A6,Tasks!$L$5:$L$300,"S") | F6: =COUNTIFS(Tasks!$B$5:$B$300,A6,Tasks!$L$5:$L$300,"M") | G6: =COUNTIFS(Tasks!$B$5:$B$300,A6,Tasks!$L$5:$L$300,"L") | H6: =E6*$B$3+F6*$D$3+G6*$F$3 | I6: =COUNTIFS(Tasks!$B$5:$B$300,A6,Tasks!$U$5:$U$300,"نعم") | J6: =COUNTIFS(Tasks!$B$5:$B$300,A6,Tasks!$U$5:$U$300,"جزئي") | K6: =COUNTIFS(Tasks!$B$5:$B$300,A6,Tasks!$U$5:$U$300,"لا") | L6: سُلِّم — بانتظار validate (00-17) | M6: WP-P1، WP-W2 (الآن) | N6: لا يعتمد على JSON. يُغلق بتشغيلك validate محليًا.
A7: WP-J | B7: أنواع الردود الفعلية (بانتظار عينات JSON) | C7: Wave J | D7: =COUNTIF(Tasks!$B$5:$B$300,A7) | E7: =COUNTIFS(Tasks!$B$5:$B$300,A7,Tasks!$L$5:$L$300,"S") | F7: =COUNTIFS(Tasks!$B$5:$B$300,A7,Tasks!$L$5:$L$300,"M") | G7: =COUNTIFS(Tasks!$B$5:$B$300,A7,Tasks!$L$5:$L$300,"L") | H7: =E7*$B$3+F7*$D$3+G7*$F$3 | I7: =COUNTIFS(Tasks!$B$5:$B$300,A7,Tasks!$U$5:$U$300,"نعم") | J7: =COUNTIFS(Tasks!$B$5:$B$300,A7,Tasks!$U$5:$U$300,"جزئي") | K7: =COUNTIFS(Tasks!$B$5:$B$300,A7,Tasks!$U$5:$U$300,"لا") | L7: عند وصول عينات JSON | M7: — | N7: يفتح المهام المعلّمة JSON=نعم.
A8: WP-T1 | B8: المعلم: قائمة الكورسات + شاشة الكورس + نموذج التفاصيل | C8: Wave 1 | D8: =COUNTIF(Tasks!$B$5:$B$300,A8) | E8: =COUNTIFS(Tasks!$B$5:$B$300,A8,Tasks!$L$5:$L$300,"S") | F8: =COUNTIFS(Tasks!$B$5:$B$300,A8,Tasks!$L$5:$L$300,"M") | G8: =COUNTIFS(Tasks!$B$5:$B$300,A8,Tasks!$L$5:$L$300,"L") | H8: =E8*$B$3+F8*$D$3+G8*$F$3 | I8: =COUNTIFS(Tasks!$B$5:$B$300,A8,Tasks!$U$5:$U$300,"نعم") | J8: =COUNTIFS(Tasks!$B$5:$B$300,A8,Tasks!$U$5:$U$300,"جزئي") | K8: =COUNTIFS(Tasks!$B$5:$B$300,A8,Tasks!$U$5:$U$300,"لا") | L8: حسب المهمة: «الآن» / «الآن (seam)» / «بعد JSON» | M8: كل WPs Wave 1 الأخرى (ملفات منفصلة) | N8: شغّل المهام الخالية من JSON الآن؛ المعلّمة JSON=نعم تنتظر WP-J.
A9: WP-T2 | B9: المعلم: إعداد المجموعة والجدول المتكرر | C9: Wave 1 | D9: =COUNTIF(Tasks!$B$5:$B$300,A9) | E9: =COUNTIFS(Tasks!$B$5:$B$300,A9,Tasks!$L$5:$L$300,"S") | F9: =COUNTIFS(Tasks!$B$5:$B$300,A9,Tasks!$L$5:$L$300,"M") | G9: =COUNTIFS(Tasks!$B$5:$B$300,A9,Tasks!$L$5:$L$300,"L") | H9: =E9*$B$3+F9*$D$3+G9*$F$3 | I9: =COUNTIFS(Tasks!$B$5:$B$300,A9,Tasks!$U$5:$U$300,"نعم") | J9: =COUNTIFS(Tasks!$B$5:$B$300,A9,Tasks!$U$5:$U$300,"جزئي") | K9: =COUNTIFS(Tasks!$B$5:$B$300,A9,Tasks!$U$5:$U$300,"لا") | L9: حسب المهمة: «الآن» / «الآن (seam)» / «بعد JSON» | M9: كل WPs Wave 1 الأخرى (ملفات منفصلة) | N9: شغّل المهام الخالية من JSON الآن؛ المعلّمة JSON=نعم تنتظر WP-J.
A10: WP-T3 | B10: المعلم: طلاب المجموعة | C10: Wave 1 | D10: =COUNTIF(Tasks!$B$5:$B$300,A10) | E10: =COUNTIFS(Tasks!$B$5:$B$300,A10,Tasks!$L$5:$L$300,"S") | F10: =COUNTIFS(Tasks!$B$5:$B$300,A10,Tasks!$L$5:$L$300,"M") | G10: =COUNTIFS(Tasks!$B$5:$B$300,A10,Tasks!$L$5:$L$300,"L") | H10: =E10*$B$3+F10*$D$3+G10*$F$3 | I10: =COUNTIFS(Tasks!$B$5:$B$300,A10,Tasks!$U$5:$U$300,"نعم") | J10: =COUNTIFS(Tasks!$B$5:$B$300,A10,Tasks!$U$5:$U$300,"جزئي") | K10: =COUNTIFS(Tasks!$B$5:$B$300,A10,Tasks!$U$5:$U$300,"لا") | L10: حسب المهمة: «الآن» / «الآن (seam)» / «بعد JSON» | M10: كل WPs Wave 1 الأخرى (ملفات منفصلة) | N10: شغّل المهام الخالية من JSON الآن؛ المعلّمة JSON=نعم تنتظر WP-J.
A11: WP-T4 | B11: المعلم: الدروس (إنشاء/جدولة/تعديل/إلغاء/اجتماع) | C11: Wave 1 | D11: =COUNTIF(Tasks!$B$5:$B$300,A11) | E11: =COUNTIFS(Tasks!$B$5:$B$300,A11,Tasks!$L$5:$L$300,"S") | F11: =COUNTIFS(Tasks!$B$5:$B$300,A11,Tasks!$L$5:$L$300,"M") | G11: =COUNTIFS(Tasks!$B$5:$B$300,A11,Tasks!$L$5:$L$300,"L") | H11: =E11*$B$3+F11*$D$3+G11*$F$3 | I11: =COUNTIFS(Tasks!$B$5:$B$300,A11,Tasks!$U$5:$U$300,"نعم") | J11: =COUNTIFS(Tasks!$B$5:$B$300,A11,Tasks!$U$5:$U$300,"جزئي") | K11: =COUNTIFS(Tasks!$B$5:$B$300,A11,Tasks!$U$5:$U$300,"لا") | L11: حسب المهمة: «الآن» / «الآن (seam)» / «بعد JSON» | M11: كل WPs Wave 1 الأخرى (ملفات منفصلة) | N11: شغّل المهام الخالية من JSON الآن؛ المعلّمة JSON=نعم تنتظر WP-J.
A12: WP-T5 | B12: المعلم: طلبات الحجز + طلبات إعادة الجدولة + لوحة المعلم | C12: Wave 1 | D12: =COUNTIF(Tasks!$B$5:$B$300,A12) | E12: =COUNTIFS(Tasks!$B$5:$B$300,A12,Tasks!$L$5:$L$300,"S") | F12: =COUNTIFS(Tasks!$B$5:$B$300,A12,Tasks!$L$5:$L$300,"M") | G12: =COUNTIFS(Tasks!$B$5:$B$300,A12,Tasks!$L$5:$L$300,"L") | H12: =E12*$B$3+F12*$D$3+G12*$F$3 | I12: =COUNTIFS(Tasks!$B$5:$B$300,A12,Tasks!$U$5:$U$300,"نعم") | J12: =COUNTIFS(Tasks!$B$5:$B$300,A12,Tasks!$U$5:$U$300,"جزئي") | K12: =COUNTIFS(Tasks!$B$5:$B$300,A12,Tasks!$U$5:$U$300,"لا") | L12: حسب المهمة: «الآن» / «الآن (seam)» / «بعد JSON» | M12: كل WPs Wave 1 الأخرى (ملفات منفصلة) | N12: شغّل المهام الخالية من JSON الآن؛ المعلّمة JSON=نعم تنتظر WP-J.
A13: WP-S1 | B13: الطالب: شاشة إنشاء الحجز | C13: Wave 1 | D13: =COUNTIF(Tasks!$B$5:$B$300,A13) | E13: =COUNTIFS(Tasks!$B$5:$B$300,A13,Tasks!$L$5:$L$300,"S") | F13: =COUNTIFS(Tasks!$B$5:$B$300,A13,Tasks!$L$5:$L$300,"M") | G13: =COUNTIFS(Tasks!$B$5:$B$300,A13,Tasks!$L$5:$L$300,"L") | H13: =E13*$B$3+F13*$D$3+G13*$F$3 | I13: =COUNTIFS(Tasks!$B$5:$B$300,A13,Tasks!$U$5:$U$300,"نعم") | J13: =COUNTIFS(Tasks!$B$5:$B$300,A13,Tasks!$U$5:$U$300,"جزئي") | K13: =COUNTIFS(Tasks!$B$5:$B$300,A13,Tasks!$U$5:$U$300,"لا") | L13: حسب المهمة: «الآن» / «الآن (seam)» / «بعد JSON» | M13: كل WPs Wave 1 الأخرى (ملفات منفصلة) | N13: شغّل المهام الخالية من JSON الآن؛ المعلّمة JSON=نعم تنتظر WP-J.
A14: WP-S2 | B14: الطالب: تفاصيل الحجز + الإلغاء + لوحات كورساتي | C14: Wave 1 | D14: =COUNTIF(Tasks!$B$5:$B$300,A14) | E14: =COUNTIFS(Tasks!$B$5:$B$300,A14,Tasks!$L$5:$L$300,"S") | F14: =COUNTIFS(Tasks!$B$5:$B$300,A14,Tasks!$L$5:$L$300,"M") | G14: =COUNTIFS(Tasks!$B$5:$B$300,A14,Tasks!$L$5:$L$300,"L") | H14: =E14*$B$3+F14*$D$3+G14*$F$3 | I14: =COUNTIFS(Tasks!$B$5:$B$300,A14,Tasks!$U$5:$U$300,"نعم") | J14: =COUNTIFS(Tasks!$B$5:$B$300,A14,Tasks!$U$5:$U$300,"جزئي") | K14: =COUNTIFS(Tasks!$B$5:$B$300,A14,Tasks!$U$5:$U$300,"لا") | L14: حسب المهمة: «الآن» / «الآن (seam)» / «بعد JSON» | M14: كل WPs Wave 1 الأخرى (ملفات منفصلة) | N14: شغّل المهام الخالية من JSON الآن؛ المعلّمة JSON=نعم تنتظر WP-J.
A15: WP-S3 | B15: الطالب: طلب إعادة الجدولة | C15: Wave 1 | D15: =COUNTIF(Tasks!$B$5:$B$300,A15) | E15: =COUNTIFS(Tasks!$B$5:$B$300,A15,Tasks!$L$5:$L$300,"S") | F15: =COUNTIFS(Tasks!$B$5:$B$300,A15,Tasks!$L$5:$L$300,"M") | G15: =COUNTIFS(Tasks!$B$5:$B$300,A15,Tasks!$L$5:$L$300,"L") | H15: =E15*$B$3+F15*$D$3+G15*$F$3 | I15: =COUNTIFS(Tasks!$B$5:$B$300,A15,Tasks!$U$5:$U$300,"نعم") | J15: =COUNTIFS(Tasks!$B$5:$B$300,A15,Tasks!$U$5:$U$300,"جزئي") | K15: =COUNTIFS(Tasks!$B$5:$B$300,A15,Tasks!$U$5:$U$300,"لا") | L15: حسب المهمة: «الآن» / «الآن (seam)» / «بعد JSON» | M15: كل WPs Wave 1 الأخرى (ملفات منفصلة) | N15: شغّل المهام الخالية من JSON الآن؛ المعلّمة JSON=نعم تنتظر WP-J.
A16: WP-S4 | B16: الطالب: تقييم المعلم | C16: Wave 1 | D16: =COUNTIF(Tasks!$B$5:$B$300,A16) | E16: =COUNTIFS(Tasks!$B$5:$B$300,A16,Tasks!$L$5:$L$300,"S") | F16: =COUNTIFS(Tasks!$B$5:$B$300,A16,Tasks!$L$5:$L$300,"M") | G16: =COUNTIFS(Tasks!$B$5:$B$300,A16,Tasks!$L$5:$L$300,"L") | H16: =E16*$B$3+F16*$D$3+G16*$F$3 | I16: =COUNTIFS(Tasks!$B$5:$B$300,A16,Tasks!$U$5:$U$300,"نعم") | J16: =COUNTIFS(Tasks!$B$5:$B$300,A16,Tasks!$U$5:$U$300,"جزئي") | K16: =COUNTIFS(Tasks!$B$5:$B$300,A16,Tasks!$U$5:$U$300,"لا") | L16: حسب المهمة: «الآن» / «الآن (seam)» / «بعد JSON» | M16: كل WPs Wave 1 الأخرى (ملفات منفصلة) | N16: شغّل المهام الخالية من JSON الآن؛ المعلّمة JSON=نعم تنتظر WP-J.
A17: WP-S5 | B17: الطالب: تفاصيل الدرس (حضوري/أونلاين) + تحسين الجدول | C17: Wave 1 | D17: =COUNTIF(Tasks!$B$5:$B$300,A17) | E17: =COUNTIFS(Tasks!$B$5:$B$300,A17,Tasks!$L$5:$L$300,"S") | F17: =COUNTIFS(Tasks!$B$5:$B$300,A17,Tasks!$L$5:$L$300,"M") | G17: =COUNTIFS(Tasks!$B$5:$B$300,A17,Tasks!$L$5:$L$300,"L") | H17: =E17*$B$3+F17*$D$3+G17*$F$3 | I17: =COUNTIFS(Tasks!$B$5:$B$300,A17,Tasks!$U$5:$U$300,"نعم") | J17: =COUNTIFS(Tasks!$B$5:$B$300,A17,Tasks!$U$5:$U$300,"جزئي") | K17: =COUNTIFS(Tasks!$B$5:$B$300,A17,Tasks!$U$5:$U$300,"لا") | L17: حسب المهمة: «الآن» / «الآن (seam)» / «بعد JSON» | M17: كل WPs Wave 1 الأخرى (ملفات منفصلة) | N17: شغّل المهام الخالية من JSON الآن؛ المعلّمة JSON=نعم تنتظر WP-J.
... A24: WP-W2 | B24: المحفظة (معلم): إيداع الأرباح بعد العمولة | C24: Wave 1 | D24: =COUNTIF(Tasks!$B$5:$B$300,A24) | E24: =COUNTIFS(Tasks!$B$5:$B$300,A24,Tasks!$L$5:$L$300,"S") | F24: =COUNTIFS(Tasks!$B$5:$B$300,A24,Tasks!$L$5:$L$300,"M") | G24: =COUNTIFS(Tasks!$B$5:$B$300,A24,Tasks!$L$5:$L$300,"L") | H24: =E24*$B$3+F24*$D$3+G24*$F$3 | I24: =COUNTIFS(Tasks!$B$5:$B$300,A24,Tasks!$U$5:$U$300,"نعم") | J24: =COUNTIFS(Tasks!$B$5:$B$300,A24,Tasks!$U$5:$U$300,"جزئي") | K24: =COUNTIFS(Tasks!$B$5:$B$300,A24,Tasks!$U$5:$U$300,"لا") | L24: الآن | M24: WP-00، WP-P1 | N24: يعدّل teacher.earnings.tsx فقط؛ يستخدم دوال المحفظة الموجودة.
A25: WP-QA | B25: التكامل والاختبار والتوثيق | C25: Wave 2 | D25: =COUNTIF(Tasks!$B$5:$B$300,A25) | E25: =COUNTIFS(Tasks!$B$5:$B$300,A25,Tasks!$L$5:$L$300,"S") | F25: =COUNTIFS(Tasks!$B$5:$B$300,A25,Tasks!$L$5:$L$300,"M") | G25: =COUNTIFS(Tasks!$B$5:$B$300,A25,Tasks!$L$5:$L$300,"L") | H25: =E25*$B$3+F25*$D$3+G25*$F$3 | I25: =COUNTIFS(Tasks!$B$5:$B$300,A25,Tasks!$U$5:$U$300,"نعم") | J25: =COUNTIFS(Tasks!$B$5:$B$300,A25,Tasks!$U$5:$U$300,"جزئي") | K25: =COUNTIFS(Tasks!$B$5:$B$300,A25,Tasks!$U$5:$U$300,"لا") | L25: بعد Wave 1 | M25: —
A26: المجموع | D26: =SUM(D6:D25) | E26: =SUM(E6:E25) | F26: =SUM(F6:F25) | G26: =SUM(G6:G25) | H26: =SUM(H6:H25) | I26: =SUM(I6:I25) | J26: =SUM(J6:J25) | K26: =SUM(K6:K25)
A28: المتاح للبدء الآن (بوابة = «الآن»)
A29: عدد المهام | B29: =COUNTIF(Tasks!$V$5:$V$300,"الآن")
A30: نقاط جهدها | B30: =COUNTIFS(Tasks!$V$5:$V$300,"الآن",Tasks!$L$5:$L$300,"S")*$B$3+COUNTIFS(Tasks!$V$5:$V$300,"الآن",Tasks!$L$5:$L$300,"M")*$D$3+COUNTIFS(Tasks!$V$5:$V$300,"الآن",Tasks!$L$5:$L$300,"L")*$F$3

Sheet ParallelPlan
A1: خطة التوازي والدمج
A2: مقترح لتقسيم العمل على جلسات. أي مجموعة من WPs بنفس الـ Wave آمنة التوازي لأن ملفاتها منفصلة (راجع FileOwnership).
A4: المرحلة | B4: المسار/Track | C4: WPs | D4: ملاحظات | E4: شرط البدء | F4: بوابة الإنجاز (Gate)
A5: Wave 0 | B5: Claude ينفّذ كاملًا ثم يشغّل المستخدم validate | C5: WP-00 → W0-Final | D5: WP-00 بالكامل (بلا JSON). بالتوازي معه يمكن للمستخدم بدء WP-P1 وWP-W2 فورًا (يعدّلان ملفات قائمة ولا يمسّان WP-00). WP-J ينتظر العينات. | E5: إجابة Q-01..Q-05 (على الأقل العينات) ← أو البدء بأنواع متساهلة | F5: WP-00 مكتمل + validate أخضر + إغلاق D-01..D-09 + إعلان الملفات المجمّدة
A6: Wave J | B6: عند وصول العينات | C6: WP-J | D6: استبدال PendingResponse بأنواع حقيقية | E6: عينات JSON من المستخدم | F6: J-07 مكتمل
A7: Wave 1 | B7: Track 1: كورسات المعلم | C7: WP-T1 → WP-T3 | D7: T3 يعتمد وظيفيًا على shell من T1 لكن كوديًا مستقل | E7: Wave 0 مغلق | F7: كل مهام الـ WPs مكتملة + validate
A8: Wave 1 | B8: Track 2: مجموعات ودروس | C8: WP-T2 → WP-T4 | D8: الأكبر حجمًا (T4=L)؛ يمكن فصل T4 لجلستين داخليًا لكن بنفس الملفات → جلسة واحدة | E8: Wave 0 مغلق + Q-02 | F8: نفسه
A9: Wave 1 | B9: Track 3: طلبات الحجز (معلم) + أرباح | C9: WP-T5 + WP-W2 | E9: Wave 0 مغلق | F9: نفسه
A10: Wave 1 | B10: Track 4: إنشاء الحجز + تفاصيله | C10: WP-S1 + WP-S2 | D10: يستهلكان stubs لـ W1/S3/S4 | E10: Wave 0 مغلق + Q-04, Q-06 | F10: نفسه
A11: Wave 1 | B11: Track 5: إجراءات الحجز + المحفظة | C11: WP-S3 + WP-S4 + WP-W1 | D11: مكونات صغيرة مستقلة | E11: Wave 0 مغلق | F11: نفسه
A12: Wave 1 | B12: Track 6: الدروس والكورسات (طالب) | C12: WP-S5 + WP-S6 | E12: Wave 0 مغلق | F12: نفسه
A13: Wave 1 | B13: Track 7: أكاديمي + ولي أمر | C13: WP-S7 + WP-S8 + WP-S9 + WP-P1 | D13: كلها صغيرة (S) | E13: Wave 0 مغلق | F13: نفسه
A14: Wave 2 | B14: جلسة واحدة | C14: WP-QA | D14: بعد دمج كل Wave 1 | E14: كل Wave 1 مدموج + Q-17 | F14: validate + e2e + UAT + تحديث التوثيق + إعادة التدقيق
A16: ترتيب الدمج المقترح
A17: 1) WP-00 أولًا (حاجز). 2) بعده أي ترتيب لـ Wave 1 (لا تداخل ملفات). 3) يُفضَّل دمج T1 قبل اختبار T2/T3/T4 معًا، ودمج W1/S3/S4 قبل اختبار S2 كاملًا (اختبار تكاملي فقط).
A18: 4) قبل كل دمج: git pull/rebase، شغّل npm run format && npm run validate، تأكد أن PR لا يلمس routeTree.gen.ts ولا ملفات خارج الملكية.
A19: 5) عند تعارض غير متوقع: أوقف، سجّله في ChangeRequests، لا تحلّه بتعديل ملف غيرك.

Sheet WorkPackages
A1: حزم العمل (Work Packages)
A2: كل WP = وحدة عمل مستقلة بملفات لا يشاركها غيرها. الحالة والنسبة محسوبة تلقائيًا من ورقة Tasks. الأصفر = إدخال.
A4: WP | B4: الاسم | C4: Wave | D4: FRs | E4: النطاق | F4: يعتمد على | G4: الحجم | H4: الفرع (Branch) | I4: المسؤول | J4: الجلسة/Run | K4: عدد المهام | L4: مكتمل | M4: قيد التنفيذ/المراجعة | N4: متوقف | O4: % الإنجاز | P4: الحالة (محسوبة) | Q4: تم الدمج؟ | R4: رابط PR | S4: ملاحظات
A5: WP-00 | B5: الأساس المشترك (Foundation) | C5: Wave 0 | D5: عام | E5: مواءمة طبقة الـ API مع Swagger (طلبات الكتابة + OperationResult) + enums/formatters + مكونات UI مشتركة + تسجيل الصفحات + stubs + routeTree. لا يعتمد على JSON: كل رد غير موثّق يُكتب كـ PendingResponse ويُترك لـ WP-J. ينفّذه Claude بالكامل؛ المستخدم يشغّل validate/توليد routeTree محليًا (00-17). | F5: — | G5: L | H5: feat/wp-00-foundation | I5: Claude + المستخدم | J5: W0-A + W0-B + W0-Final | K5: =COUNTIF(Tasks!$B$5:$B$300,A5) | L5: =COUNTIFS(Tasks!$B$5:$B$300,A5,Tasks!$M$5:$M$300,"مكتمل") | M5: =COUNTIFS(Tasks!$B$5:$B$300,A5,Tasks!$M$5:$M$300,"قيد التنفيذ")+COUNTIFS(Tasks!$B$5:$B$300,A5,Tasks!$M$5:$M$300,"قيد المراجعة") | N5: =COUNTIFS(Tasks!$B$5:$B$300,A5,Tasks!$M$5:$M$300,"متوقف") | O5: =IF(K5=0,0,L5/K5) | P5: =IF(K5=0,"—",IF(L5=K5,"مكتمل",IF(N5>0,"متوقف",IF(L5+M5>0,"قيد التنفيذ","لم يبدأ")))) | Q5: لا
A6: WP-J | B6: أنواع الردود الفعلية (بانتظار عينات JSON) | C6: Wave J | D6: عام | E6: استبدال الأنواع المؤقتة PendingResponse بأنواع حقيقية من عينات JSON، وحسم Q-01..Q-05. لا يبدأ قبل وصول العينات. يمسّ فقط أقسام الأنواع في ملفات API التي أنشأها WP-00. | F6: عينات JSON من المستخدم + إغلاق WP-00 | G6: M | H6: feat/wp-j-response-types | K6: =COUNTIF(Tasks!$B$5:$B$300,A6) | L6: =COUNTIFS(Tasks!$B$5:$B$300,A6,Tasks!$M$5:$M$300,"مكتمل") | M6: =COUNTIFS(Tasks!$B$5:$B$300,A6,Tasks!$M$5:$M$300,"قيد التنفيذ")+COUNTIFS(Tasks!$B$5:$B$300,A6,Tasks!$M$5:$M$300,"قيد المراجعة") | N6: =COUNTIFS(Tasks!$B$5:$B$300,A6,Tasks!$M$5:$M$300,"متوقف") | O6: =IF(K6=0,0,L6/K6) | P6: =IF(K6=0,"—",IF(L6=K6,"مكتمل",IF(N6>0,"متوقف",IF(L6+M6>0,"قيد التنفيذ","لم يبدأ")))) | Q6: لا
A7: WP-T1 | B7: المعلم: قائمة الكورسات + شاشة الكورس + نموذج التفاصيل | C7: Wave 1 | D7: FR-I01, FR-I05 (داعم) | E7: teacher.courses (قائمة) + teacher.course.$id (shell بتبويبات) + تبويب التفاصيل (إنشاء/تعديل كورس حضوري/أونلاين + مسودة). | F7: WP-00 | G7: M | H7: feat/wp-t1-teacher-courses | K7: =COUNTIF(Tasks!$B$5:$B$300,A7) | L7: =COUNTIFS(Tasks!$B$5:$B$300,A7,Tasks!$M$5:$M$300,"مكتمل") | M7: =COUNTIFS(Tasks!$B$5:$B$300,A7,Tasks!$M$5:$M$300,"قيد التنفيذ")+COUNTIFS(Tasks!$B$5:$B$300,A7,Tasks!$M$5:$M$300,"قيد المراجعة") | N7: =COUNTIFS(Tasks!$B$5:$B$300,A7,Tasks!$M$5:$M$300,"متوقف") | O7: =IF(K7=0,0,L7/K7) | P7: =IF(K7=0,"—",IF(L7=K7,"مكتمل",IF(N7>0,"متوقف",IF(L7+M7>0,"قيد التنفيذ","لم يبدأ")))) | Q7: لا
A8: WP-T2 | B8: المعلم: إعداد المجموعة والجدول المتكرر | C8: Wave 1 | D8: FR-I02, FR-I06 | E8: تبويب إعداد المجموعة: الحد الأقصى، أيام الحضور + الوقت، المدة، فترة الكورس (حضوري وأونلاين). | F8: WP-00 | G8: M | H8: feat/wp-t2-group-config | K8: =COUNTIF(Tasks!$B$5:$B$300,A8) | L8: =COUNTIFS(Tasks!$B$5:$B$300,A8,Tasks!$M$5:$M$300,"مكتمل") | M8: =COUNTIFS(Tasks!$B$5:$B$300,A8,Tasks!$M$5:$M$300,"قيد التنفيذ")+COUNTIFS(Tasks!$B$5:$B$300,A8,Tasks!$M$5:$M$300,"قيد المراجعة") | N8: =COUNTIFS(Tasks!$B$5:$B$300,A8,Tasks!$M$5:$M$300,"متوقف") | O8: =IF(K8=0,0,L8/K8) | P8: =IF(K8=0,"—",IF(L8=K8,"مكتمل",IF(N8>0,"متوقف",IF(L8+M8>0,"قيد التنفيذ","لم يبدأ")))) | Q8: لا
A9: WP-T3 | B9: المعلم: طلاب المجموعة | C9: Wave 1 | D9: FR-I03 | E9: تبويب طلاب المجموعة: اسم/هاتف/موقع + بحث + حالة فارغة. | F9: WP-00 | G9: S | H9: feat/wp-t3-group-students | K9: =COUNTIF(Tasks!$B$5:$B$300,A9) | L9: =COUNTIFS(Tasks!$B$5:$B$300,A9,Tasks!$M$5:$M$300,"مكتمل") | M9: =COUNTIFS(Tasks!$B$5:$B$300,A9,Tasks!$M$5:$M$300,"قيد التنفيذ")+COUNTIFS(Tasks!$B$5:$B$300,A9,Tasks!$M$5:$M$300,"قيد المراجعة") | N9: =COUNTIFS(Tasks!$B$5:$B$300,A9,Tasks!$M$5:$M$300,"متوقف") | O9: =IF(K9=0,0,L9/K9) | P9: =IF(K9=0,"—",IF(L9=K9,"مكتمل",IF(N9>0,"متوقف",IF(L9+M9>0,"قيد التنفيذ","لم يبدأ")))) | Q9: لا
A10: WP-T4 | B10: المعلم: الدروس (إنشاء/جدولة/تعديل/إلغاء/اجتماع) | C10: Wave 1 | D10: FR-I04, FR-I08, FR-I07, FR-I09, FR-I10, FR-I11 | E10: تبويب الدروس: قائمة زمنية + نموذج درس حضوري/أونلاين + تعديل + إعداد الاجتماع + إلغاء بسبب. | F10: WP-00 | G10: L | H10: feat/wp-t4-lessons | K10: =COUNTIF(Tasks!$B$5:$B$300,A10) | L10: =COUNTIFS(Tasks!$B$5:$B$300,A10,Tasks!$M$5:$M$300,"مكتمل") | M10: =COUNTIFS(Tasks!$B$5:$B$300,A10,Tasks!$M$5:$M$300,"قيد التنفيذ")+COUNTIFS(Tasks!$B$5:$B$300,A10,Tasks!$M$5:$M$300,"قيد المراجعة") | N10: =COUNTIFS(Tasks!$B$5:$B$300,A10,Tasks!$M$5:$M$300,"متوقف") | O10: =IF(K10=0,0,L10/K10) | P10: =IF(K10=0,"—",IF(L10=K10,"مكتمل",IF(N10>0,"متوقف",IF(L10+M10>0,"قيد التنفيذ","لم يبدأ")))) | Q10: لا
A11: WP-T5 | B11: المعلم: طلبات الحجز + طلبات إعادة الجدولة + لوحة المعلم | C11: Wave 1 | D11: FR-T10 (داعم), FR-T06 (جهة المعلم), FR-S15 (جهة المعلم) | E11: teacher.bookings: قبول/رفض/إنهاء + قرار إعادة الجدولة + استبدال لوحة المعلم المعطّلة بعرض حقيقي. | F11: WP-00 | G11: M | H11: feat/wp-t5-teacher-bookings | K11: =COUNTIF(Tasks!$B$5:$B$300,A11) | L11: =COUNTIFS(Tasks!$B$5:$B$300,A11,Tasks!$M$5:$M$300,"مكتمل") | M11: =COUNTIFS(Tasks!$B$5:$B$300,A11,Tasks!$M$5:$M$300,"قيد التنفيذ")+COUNTIFS(Tasks!$B$5:$B$300,A11,Tasks!$M$5:$M$300,"قيد المراجعة") | N11: =COUNTIFS(Tasks!$B$5:$B$300,A11,Tasks!$M$5:$M$300,"متوقف") | O11: =IF(K11=0,0,L11/K11) | P11: =IF(K11=0,"—",IF(L11=K11,"مكتمل",IF(N11>0,"متوقف",IF(L11+M11>0,"قيد التنفيذ","لم يبدأ")))) | Q11: لا
A12: WP-S1 | B12: الطالب: شاشة إنشاء الحجز | C12: Wave 1 | D12: FR-T06 (+FR-T05) | E12: book.$teacherId: اختيار الوضع/التاريخ/الوقت/المادة/الصف + تقدير السعر + فحص الرصيد + إرسال الحجز + تفعيل زر الحجز في صفحة المعلم. | F12: WP-00 | G12: L | H12: feat/wp-s1-create-booking | K12: =COUNTIF(Tasks!$B$5:$B$300,A12) | L12: =COUNTIFS(Tasks!$B$5:$B$300,A12,Tasks!$M$5:$M$300,"مكتمل") | M12: =COUNTIFS(Tasks!$B$5:$B$300,A12,Tasks!$M$5:$M$300,"قيد التنفيذ")+COUNTIFS(Tasks!$B$5:$B$300,A12,Tasks!$M$5:$M$300,"قيد المراجعة") | N12: =COUNTIFS(Tasks!$B$5:$B$300,A12,Tasks!$M$5:$M$300,"متوقف") | O12: =IF(K12=0,0,L12/K12) | P12: =IF(K12=0,"—",IF(L12=K12,"مكتمل",IF(N12>0,"متوقف",IF(L12+M12>0,"قيد التنفيذ","لم يبدأ")))) | Q12: لا
A13: WP-S2 | B13: الطالب: تفاصيل الحجز + الإلغاء + لوحات كورساتي | C13: Wave 1 | D13: FR-S14 | E13: booking.$id + إلغاء الحجز + لوحتا (الحجوزات المؤكدة / الطلبات المعلقة) مع سجل المرفوض/الملغى. | F13: WP-00 | G13: M | H13: feat/wp-s2-booking-detail-cancel | K13: =COUNTIF(Tasks!$B$5:$B$300,A13) | L13: =COUNTIFS(Tasks!$B$5:$B$300,A13,Tasks!$M$5:$M$300,"مكتمل") | M13: =COUNTIFS(Tasks!$B$5:$B$300,A13,Tasks!$M$5:$M$300,"قيد التنفيذ")+COUNTIFS(Tasks!$B$5:$B$300,A13,Tasks!$M$5:$M$300,"قيد المراجعة") | N13: =COUNTIFS(Tasks!$B$5:$B$300,A13,Tasks!$M$5:$M$300,"متوقف") | O13: =IF(K13=0,0,L13/K13) | P13: =IF(K13=0,"—",IF(L13=K13,"مكتمل",IF(N13>0,"متوقف",IF(L13+M13>0,"قيد التنفيذ","لم يبدأ")))) | Q13: لا
A14: WP-S3 | B14: الطالب: طلب إعادة الجدولة | C14: Wave 1 | D14: FR-S15 | E14: نافذة طلب إعادة جدولة + لوحة تتبع حالة الطلبات. | F14: WP-00 | G14: S | H14: feat/wp-s3-reschedule | K14: =COUNTIF(Tasks!$B$5:$B$300,A14) | L14: =COUNTIFS(Tasks!$B$5:$B$300,A14,Tasks!$M$5:$M$300,"مكتمل") | M14: =COUNTIFS(Tasks!$B$5:$B$300,A14,Tasks!$M$5:$M$300,"قيد التنفيذ")+COUNTIFS(Tasks!$B$5:$B$300,A14,Tasks!$M$5:$M$300,"قيد المراجعة") | N14: =COUNTIFS(Tasks!$B$5:$B$300,A14,Tasks!$M$5:$M$300,"متوقف") | O14: =IF(K14=0,0,L14/K14) | P14: =IF(K14=0,"—",IF(L14=K14,"مكتمل",IF(N14>0,"متوقف",IF(L14+M14>0,"قيد التنفيذ","لم يبدأ")))) | Q14: لا
A15: WP-S4 | B15: الطالب: تقييم المعلم | C15: Wave 1 | D15: FR-T11 | E15: نافذة تقييم (نجوم + مراجعة) للحجز المكتمل + منع التكرار + تحديث الكاشات. | F15: WP-00 | G15: S | H15: feat/wp-s4-rating | K15: =COUNTIF(Tasks!$B$5:$B$300,A15) | L15: =COUNTIFS(Tasks!$B$5:$B$300,A15,Tasks!$M$5:$M$300,"مكتمل") | M15: =COUNTIFS(Tasks!$B$5:$B$300,A15,Tasks!$M$5:$M$300,"قيد التنفيذ")+COUNTIFS(Tasks!$B$5:$B$300,A15,Tasks!$M$5:$M$300,"قيد المراجعة") | N15: =COUNTIFS(Tasks!$B$5:$B$300,A15,Tasks!$M$5:$M$300,"متوقف") | O15: =IF(K15=0,0,L15/K15) | P15: =IF(K15=0,"—",IF(L15=K15,"مكتمل",IF(N15>0,"متوقف",IF(L15+M15>0,"قيد التنفيذ","لم يبدأ")))) | Q15: لا
A16: WP-S5 | B16: الطالب: تفاصيل الدرس (حضوري/أونلاين) + تحسين الجدول | C16: Wave 1 | D16: FR-S06, FR-S07 | E16: lesson.$id + أعمدة القاعة/المنصة/انضمام في schedule + روابط للتفاصيل. | F16: WP-00 | G16: M | H16: feat/wp-s5-lesson-detail | K16: =COUNTIF(Tasks!$B$5:$B$300,A16) | L16: =COUNTIFS(Tasks!$B$5:$B$300,A16,Tasks!$M$5:$M$300,"مكتمل") | M16: =COUNTIFS(Tasks!$B$5:$B$300,A16,Tasks!$M$5:$M$300,"قيد التنفيذ")+COUNTIFS(Tasks!$B$5:$B$300,A16,Tasks!$M$5:$M$300,"قيد المراجعة") | N16: =COUNTIFS(Tasks!$B$5:$B$300,A16,Tasks!$M$5:$M$300,"متوقف") | O16: =IF(K16=0,0,L16/K16) | P16: =IF(K16=0,"—",IF(L16=K16,"مكتمل",IF(N16>0,"متوقف",IF(L16+M16>0,"قيد التنفيذ","لم يبدأ")))) | Q16: لا
A17: WP-S6 | B17: الطالب: تفاصيل الكورس المسجَّل | C17: Wave 1 | D17: FR-S08 | E17: enrolled-course.$id + لوحة (كورساتي المسجّلة). | F17: WP-00 | G17: M | H17: feat/wp-s6-enrolled-course | K17: =COUNTIF(Tasks!$B$5:$B$300,A17) | L17: =COUNTIFS(Tasks!$B$5:$B$300,A17,Tasks!$M$5:$M$300,"مكتمل") | M17: =COUNTIFS(Tasks!$B$5:$B$300,A17,Tasks!$M$5:$M$300,"قيد التنفيذ")+COUNTIFS(Tasks!$B$5:$B$300,A17,Tasks!$M$5:$M$300,"قيد المراجعة") | N17: =COUNTIFS(Tasks!$B$5:$B$300,A17,Tasks!$M$5:$M$300,"متوقف") | O17: =IF(K17=0,0,L17/K17) | P17: =IF(K17=0,"—",IF(L17=K17,"مكتمل",IF(N17>0,"متوقف",IF(L17+M17>0,"قيد التنفيذ","لم يبدأ")))) | Q17: لا
... A24: WP-QA | B24: التكامل والاختبار والتوثيق | C24: Wave 2 | D24: الكل | E24: validate أخضر + e2e + تشغيل UAT + RTL/موبايل + تحديث README/CHANGELOG/ATLAS + إعادة التدقيق. | F24: كل WP من Wave 1 | G24: L | H24: feat/wp-qa-integration | K24: =COUNTIF(Tasks!$B$5:$B$300,A24) | L24: =COUNTIFS(Tasks!$B$5:$B$300,A24,Tasks!$M$5:$M$300,"مكتمل") | M24: =COUNTIFS(Tasks!$B$5:$B$300,A24,Tasks!$M$5:$M$300,"قيد التنفيذ")+COUNTIFS(Tasks!$B$5:$B$300,A24,Tasks!$M$5:$M$300,"قيد المراجعة") | N24: =COUNTIFS(Tasks!$B$5:$B$300,A24,Tasks!$M$5:$M$300,"متوقف") | O24: =IF(K24=0,0,L24/K24) | P24: =IF(K24=0,"—",IF(L24=K24,"مكتمل",IF(N24>0,"متوقف",IF(L24+M24>0,"قيد التنفيذ","لم يبدأ")))) | Q24: لا

Sheet Tasks
A1: المهام التفصيلية (Tasks)
A2: المصدر الوحيد لحالة العمل. حدّث الأعمدة الصفراء فقط (الحالة، المسؤول، الجلسة، التواريخ، التحقق، الملاحظات). الأعمدة الزرقاء صيغ.
A4: ID | B4: WP | C4: Wave | D4: FR (أساسي) | E4: النوع | F4: المهمة | G4: التفاصيل / معيار القبول | H4: الملفات (تحت src/ ما لم يُذكر) | I4: Endpoints | J4: تعتمد على | K4: الأولوية | L4: الحجم | M4: الحالة | N4: المسؤول | O4: الجلسة/Run | P4: الفرع (من WP) | Q4: بدأ | R4: اكتمل | S4: تم التحقق؟ (validate+UAT) | T4: ملاحظات | U4: يعتمد على JSON؟ | V4: بوابة البدء | W4: ينتظر (NE) | X4: حالة الاعتماد (محسوبة)
A5: 00-01 | B5: WP-00 | C5: =IFERROR(INDEX(WorkPackages!$C$5:$C$40,MATCH(B5,WorkPackages!$A$5:$A$40,0)),"") | D5: عام | E5: API | F5: مواءمة bookings.ts مع Swagger | G5: BookingInput = {teacherId, subjectId, gradeId, teachingMode(1|2), date, startTime, durationMinutes, studentNote}. decide يرسل accept (وليس approve). rate يرسل ratingValue + review. كل الدوال ترجع OperationResult (وليس BookingRow). الحالات أرقام 1..6. (طلبات الكتابة + OperationResult؛ ردود القوائم = PendingResponse) | H5: integrations/backend/bookings.ts | I5: Booking/Submit, Decide, Cancel, Complete, Rate, MyBookings, TeacherBookings | J5: — | K5: P0 | L5: M | M5: قيد المراجعة | N5: Claude | O5: W0 | P5: =IFERROR(INDEX(WorkPackages!$H$5:$H$40,MATCH(B5,WorkPackages!$A$5:$A$40,0)),"") | S5: لا | T5: سُلِّم في wp-00-files.zip؛ بانتظار 00-17 (routeTree + validate محليًا) | U5: لا | V5: WP-00 (سُلِّم — بانتظار validate) | X5: =IF(W5="","—",IFERROR(IF(INDEX(BackendChecklist!$H$5:$H$30,MATCH(W5,BackendChecklist!$A$5:$A$30,0))="نعم","جاهز للبدء",IF(V5="الآن (بنمط seam)","يبدأ بنمط seam — الربط ينتظر","ينتظر الباك اند")),"؟"))
A6: 00-02 | B6: WP-00 | C6: =IFERROR(INDEX(WorkPackages!$C$5:$C$40,MATCH(B6,WorkPackages!$A$5:$A$40,0)),"") | D6: عام | E6: API | F6: إضافة دوال إعادة الجدولة (جهة المعلم) | G6: listTeacherRescheduleRequests(status?) + decideReschedule({requestId, approve, rejectionReason}). | H6: integrations/backend/bookings.ts | I6: Booking/TeacherRescheduleRequests, DecideReschedule | J6: 00-01 | K6: P0 | L6: S | M6: قيد المراجعة | N6: Claude | O6: W0 | P6: =IFERROR(INDEX(WorkPackages!$H$5:$H$40,MATCH(B6,WorkPackages!$A$5:$A$40,0)),"") | S6: لا | T6: سُلِّم في wp-00-files.zip؛ بانتظار 00-17 (routeTree + validate محليًا) | U6: لا | V6: WP-00 (سُلِّم — بانتظار validate) | X6: =IF(W6="","—",IFERROR(IF(INDEX(BackendChecklist!$H$5:$H$30,MATCH(W6,BackendChecklist!$A$5:$A$30,0))="نعم","جاهز للبدء",IF(V6="الآن (بنمط seam)","يبدأ بنمط seam — الربط ينتظر","ينتظر الباك اند")),"؟"))
A7: 00-03 | B7: WP-00 | C7: =IFERROR(INDEX(WorkPackages!$C$5:$C$40,MATCH(B7,WorkPackages!$A$5:$A$40,0)),"") | D7: عام | E7: API | F7: مواءمة lessons.ts | G7: Create/Update/ConfigureMeeting/Cancel ترجع OperationResult؛ getLessonSchedule بنوع مرن حسب العينة Q-05؛ توحيد MeetingPlatform عبر enums.ts. (GetSchedule = PendingResponse) | H7: integrations/backend/lessons.ts | I7: Lesson/Create, Update, ConfigureMeeting, Cancel, GetSchedule | J7: 00-07 | K7: P0 | L7: S | M7: قيد المراجعة | N7: Claude | O7: W0 | P7: =IFERROR(INDEX(WorkPackages!$H$5:$H$40,MATCH(B7,WorkPackages!$A$5:$A$40,0)),"") | S7: لا | T7: سُلِّم في wp-00-files.zip؛ بانتظار 00-17 (routeTree + validate محليًا) | U7: لا | V7: WP-00 (سُلِّم — بانتظار validate) | X7: =IF(W7="","—",IFERROR(IF(INDEX(BackendChecklist!$H$5:$H$30,MATCH(W7,BackendChecklist!$A$5:$A$30,0))="نعم","جاهز للبدء",IF(V7="الآن (بنمط seam)","يبدأ بنمط seam — الربط ينتظر","ينتظر الباك اند")),"؟"))
A8: 00-04 | B8: WP-00 | C8: =IFERROR(INDEX(WorkPackages!$C$5:$C$40,MATCH(B8,WorkPackages!$A$5:$A$40,0)),"") | D8: عام | E8: API | F8: إضافة دوال الكورسات الناقصة | G8: createEditCourse(CourseInput) + configureGroupSchedule(input) + getGroupStudents(groupId, keyword?) + getMyCourse(id) + listMyCourses() (حسب Q-01) + نوع TeacherCourseDetail (حسب Q-02/Q-05). | H8: createEditCourse(CourseInput) + configureGroupSchedule(input) + getGroupStudents(groupId, keyword?) + getMyCourse(id) + listMyCourses(). أجسام الطلب من Swagger؛ كل رد غير موثّق = PendingResponse (يُستبدل في WP-J). | I8: Course/CreateEdit, ConfigureGroupSchedule, GetGroupStudents, GetMineById, GetAll | J8: 00-06, 00-07, 00-21 | K8: P0 | L8: M | M8: قيد المراجعة | N8: Claude | O8: W0 | P8: =IFERROR(INDEX(WorkPackages!$H$5:$H$40,MATCH(B8,WorkPackages!$A$5:$A$40,0)),"") | S8: لا | T8: سُلِّم في wp-00-files.zip؛ بانتظار 00-17 (routeTree + validate محليًا) | U8: لا | V8: WP-00 (سُلِّم — بانتظار validate) | X8: =IF(W8="","—",IFERROR(IF(INDEX(BackendChecklist!$H$5:$H$30,MATCH(W8,BackendChecklist!$A$5:$A$30,0))="نعم","جاهز للبدء",IF(V8="الآن (بنمط seam)","يبدأ بنمط seam — الربط ينتظر","ينتظر الباك اند")),"؟"))
A9: 00-05 | B9: WP-00 | C9: =IFERROR(INDEX(WorkPackages!$C$5:$C$40,MATCH(B9,WorkPackages!$A$5:$A$40,0)),"") | D9: عام | E9: API | F9: إضافة 10 دوال ناقصة لـ student.ts | G9: getStudentBooking, getStudentBookingPayment, studentCancelBooking, requestReschedule, getMyRescheduleRequests, getStudentLesson, getStudentCourse, getStudentAttendance, getStudentExamResults, getStudentProgress + أنواعها. | H9: 10 دوال جديدة: بارامترات/أجسام الطلب من Swagger. الردود غير الموثّقة = PendingResponse؛ الاستثناء getStudentProgress يستخدم StudentProgressDto الموجود بالكود. | I9: Student/GetBooking, BookingPayment, CancelBooking, RequestReschedule, MyRescheduleRequests, GetLesson, GetCourse, Attendance, ExamResults, Progress | J9: 00-06, 00-07, 00-21 | K9: P0 | L9: M | M9: قيد المراجعة | N9: Claude | O9: W0 | P9: =IFERROR(INDEX(WorkPackages!$H$5:$H$40,MATCH(B9,WorkPackages!$A$5:$A$40,0)),"") | S9: لا | T9: سُلِّم في wp-00-files.zip؛ بانتظار 00-17 (routeTree + validate محليًا) | U9: لا | V9: WP-00 (سُلِّم — بانتظار validate) | X9: =IF(W9="","—",IFERROR(IF(INDEX(BackendChecklist!$H$5:$H$30,MATCH(W9,BackendChecklist!$A$5:$A$30,0))="نعم","جاهز للبدء",IF(V9="الآن (بنمط seam)","يبدأ بنمط seam — الربط ينتظر","ينتظر الباك اند")),"؟"))
A10: 00-06 | B10: WP-00 | C10: =IFERROR(INDEX(WorkPackages!$C$5:$C$40,MATCH(B10,WorkPackages!$A$5:$A$40,0)),"") | D10: عام | E10: API | F10: ملف op-result.ts | G10: نوع OperationResult + assertOk(result, fallbackAr, fallbackEn) يرمي Error برسالة الباك اند (مع cleanBackendMessage) عند success=false. | H10: integrations/backend/op-result.ts | I10: — | J10: — | K10: P0 | L10: S | M10: قيد المراجعة | N10: Claude | O10: W0 | P10: =IFERROR(INDEX(WorkPackages!$H$5:$H$40,MATCH(B10,WorkPackages!$A$5:$A$40,0)),"") | S10: لا | T10: سُلِّم في wp-00-files.zip؛ بانتظار 00-17 (routeTree + validate محليًا) | U10: لا | V10: WP-00 (سُلِّم — بانتظار validate) | X10: =IF(W10="","—",IFERROR(IF(INDEX(BackendChecklist!$H$5:$H$30,MATCH(W10,BackendChecklist!$A$5:$A$30,0))="نعم","جاهز للبدء",IF(V10="الآن (بنمط seam)","يبدأ بنمط seam — الربط ينتظر","ينتظر الباك اند")),"؟"))
A11: 00-07 | B11: WP-00 | C11: =IFERROR(INDEX(WorkPackages!$C$5:$C$40,MATCH(B11,WorkPackages!$A$5:$A$40,0)),"") | D11: عام | E11: Lib | F11: ملف enums.ts | G11: BookingStatus(1..6)+labels+tones، DeliveryType، MeetingPlatform، AttendanceStatus، RescheduleStatus (الأسماء تُؤكَّد من Q-05)، DayOfWeek. إزالة التكرار من student.ts/lessons.ts بإعادة التصدير. | H11: lib/enums.ts | I11: — | J11: — | K11: P0 | L11: S | M11: قيد المراجعة | N11: Claude | O11: W0 | P11: =IFERROR(INDEX(WorkPackages!$H$5:$H$40,MATCH(B11,WorkPackages!$A$5:$A$40,0)),"") | S11: لا | T11: سُلِّم في wp-00-files.zip؛ بانتظار 00-17 (routeTree + validate محليًا) | U11: لا | V11: WP-00 (سُلِّم — بانتظار validate) | X11: =IF(W11="","—",IFERROR(IF(INDEX(BackendChecklist!$H$5:$H$30,MATCH(W11,BackendChecklist!$A$5:$A$30,0))="نعم","جاهز للبدء",IF(V11="الآن (بنمط seam)","يبدأ بنمط seam — الربط ينتظر","ينتظر الباك اند")),"؟"))
A12: 00-08 | B12: WP-00 | C12: =IFERROR(INDEX(WorkPackages!$C$5:$C$40,MATCH(B12,WorkPackages!$A$5:$A$40,0)),"") | D12: عام | E12: Lib | F12: ملف format.ts + اختبارات | G12: formatDate, formatTime(HH:mm:ss→HH:mm), dayName(date), formatMoney(₪)، combineDateTime، isHttpUrl (يرفض javascript: وغيره). | H12: lib/format.ts, lib/format.test.ts | I12: — | J12: — | K12: P0 | L12: S | M12: قيد المراجعة | N12: Claude | O12: W0 | P12: =IFERROR(INDEX(WorkPackages!$H$5:$H$40,MATCH(B12,WorkPackages!$A$5:$A$40,0)),"") | S12: لا | T12: سُلِّم في wp-00-files.zip؛ بانتظار 00-17 (routeTree + validate محليًا) | U12: لا | V12: WP-00 (سُلِّم — بانتظار validate) | X12: =IF(W12="","—",IFERROR(IF(INDEX(BackendChecklist!$H$5:$H$30,MATCH(W12,BackendChecklist!$A$5:$A$30,0))="نعم","جاهز للبدء",IF(V12="الآن (بنمط seam)","يبدأ بنمط seam — الربط ينتظر","ينتظر الباك اند")),"؟"))
A13: 00-09 | B13: WP-00 | C13: =IFERROR(INDEX(WorkPackages!$C$5:$C$40,MATCH(B13,WorkPackages!$A$5:$A$40,0)),"") | D13: عام | E13: Component | F13: مكونات UI مشتركة | G13: BookingStatusBadge, StarRating (1..5، قابل للقراءة فقط/للإدخال)، SegmentedTabs (لا يوجد Tabs في المشروع)، ConfirmDialog (فوق alert-dialog). | H13: components/app/booking-status-badge.tsx, components/ui/star-rating.tsx, components/ui/segmented-tabs.tsx, components/app/confirm-dialog.tsx | I13: — | J13: 00-07 | K13: P0 | L13: M | M13: قيد المراجعة | N13: Claude | O13: W0 | P13: =IFERROR(INDEX(WorkPackages!$H$5:$H$40,MATCH(B13,WorkPackages!$A$5:$A$40,0)),"") | S13: لا | T13: سُلِّم في wp-00-files.zip؛ بانتظار 00-17 (routeTree + validate محليًا) | U13: لا | V13: WP-00 (سُلِّم — بانتظار validate) | X13: =IF(W13="","—",IFERROR(IF(INDEX(BackendChecklist!$H$5:$H$30,MATCH(W13,BackendChecklist!$A$5:$A$30,0))="نعم","جاهز للبدء",IF(V13="الآن (بنمط seam)","يبدأ بنمط seam — الربط ينتظر","ينتظر الباك اند")),"؟"))
A14: 00-10 | B14: WP-00 | C14: =IFERROR(INDEX(WorkPackages!$C$5:$C$40,MATCH(B14,WorkPackages!$A$5:$A$40,0)),"") | D14: عام | E14: Lib | F14: ملف query-keys.ts | G14: مصنع مفاتيح react-query موحّد + invalidateBookingQueries(qc, id?) لمنع تضارب/نسيان الإبطال بين الـ WPs. | H14: lib/query-keys.ts | I14: — | J14: — | K14: P0 | L14: S | M14: قيد المراجعة | N14: Claude | O14: W0 | P14: =IFERROR(INDEX(WorkPackages!$H$5:$H$40,MATCH(B14,WorkPackages!$A$5:$A$40,0)),"") | S14: لا | T14: يتضمن qk.teacherEarningsCredits() (أُضيف من WP-W2 قبل إغلاق WP-00 — بلا CR) | U14: لا | V14: WP-00 (سُلِّم — بانتظار validate) | X14: =IF(W14="","—",IFERROR(IF(INDEX(BackendChecklist!$H$5:$H$30,MATCH(W14,BackendChecklist!$A$5:$A$30,0))="نعم","جاهز للبدء",IF(V14="الآن (بنمط seam)","يبدأ بنمط seam — الربط ينتظر","ينتظر الباك اند")),"؟"))
A15: 00-11 | B15: WP-00 | C15: =IFERROR(INDEX(WorkPackages!$C$5:$C$40,MATCH(B15,WorkPackages!$A$5:$A$40,0)),"") | D15: عام | E15: Lib | F15: ملف booking-rules.ts + اختبارات | G15: دوال نقية: canCancel/canReschedule/canRate(booking) بناءً على الحالة والتاريخ (ويُعتمد الباك اند كمرجع نهائي). تستهلكها WP-S2/S3/S4. | H15: lib/booking-rules.ts, lib/booking-rules.test.ts | I15: — | J15: 00-07 | K15: P0 | L15: S | M15: قيد المراجعة | N15: Claude | O15: W0 | P15: =IFERROR(INDEX(WorkPackages!$H$5:$H$40,MATCH(B15,WorkPackages!$A$5:$A$40,0)),"") | S15: لا | T15: سُلِّم في wp-00-files.zip؛ بانتظار 00-17 (routeTree + validate محليًا) | U15: لا | V15: WP-00 (سُلِّم — بانتظار validate) | X15: =IF(W15="","—",IFERROR(IF(INDEX(BackendChecklist!$H$5:$H$30,MATCH(W15,BackendChecklist!$A$5:$A$30,0))="نعم","جاهز للبدء",IF(V15="الآن (بنمط seam)","يبدأ بنمط seam — الربط ينتظر","ينتظر الباك اند")),"؟"))
A16: 00-12 | B16: WP-00 | C16: =IFERROR(INDEX(WorkPackages!$C$5:$C$40,MATCH(B16,WorkPackages!$A$5:$A$40,0)),"") | D16: عام | E16: Test | F16: اختبارات طبقة الـ API | G16: bookings/lessons/student/courses (نمط courses.test.ts: mock لـ apiClient) تغطي المسارات، الحقول، ومعالجة OperationResult. | H16: integrations/backend/bookings.test.ts, lessons.test.ts, student.test.ts, courses.test.ts | I16: كل ما سبق | J16: 00-01..00-06 | K16: P0 | L16: M | M16: قيد المراجعة | N16: Claude | O16: W0 | P16: =IFERROR(INDEX(WorkPackages!$H$5:$H$40,MATCH(B16,WorkPackages!$A$5:$A$40,0)),"") | S16: لا | T16: تعديل courses.test.ts (ملك WP-00 أصلًا) | U16: لا | V16: WP-00 (سُلِّم — بانتظار validate) | X16: =IF(W16="","—",IFERROR(IF(INDEX(BackendChecklist!$H$5:$H$30,MATCH(W16,BackendChecklist!$A$5:$A$30,0))="نعم","جاهز للبدء",IF(V16="الآن (بنمط seam)","يبدأ بنمط seam — الربط ينتظر","ينتظر الباك اند")),"؟"))
... A22: 00-19 | B22: WP-00 | C22: =IFERROR(INDEX(WorkPackages!$C$5:$C$40,MATCH(B22,WorkPackages!$A$5:$A$40,0)),"") | D22: عام | E22: Nav | F22: (اختياري) مطابقة القائمة الجانبية لمسارات التفاصيل | G22: app-sidebar يحدد الوحدة النشطة بـ startsWith على مسارات PAGES؛ مسارات مثل /lesson/$id لن تفتح مجموعتها. تحسين اختياري. | H22: components/admin/app-sidebar.tsx | I22: — | J22: 00-13 | K22: P2 | L22: S | M22: قيد المراجعة | N22: Claude | O22: W0 | P22: =IFERROR(INDEX(WorkPackages!$H$5:$H$40,MATCH(B22,WorkPackages!$A$5:$A$40,0)),"") | S22: لا | T22: تعديل app-sidebar.tsx ضمن 00-19 الاختيارية (DETAIL_ROUTE_OWNERS) | U22: لا | V22: WP-00 (سُلِّم — بانتظار validate) | X22: =IF(W22="","—",IFERROR(IF(INDEX(BackendChecklist!$H$5:$H$30,MATCH(W22,BackendChecklist!$A$5:$A$30,0))="نعم","جاهز للبدء",IF(V22="الآن (بنمط seam)","يبدأ بنمط seam — الربط ينتظر","ينتظر الباك اند")),"؟"))
A23: 00-20 | B23: WP-00 | C23: =IFERROR(INDEX(WorkPackages!$C$5:$C$40,MATCH(B23,WorkPackages!$A$5:$A$40,0)),"") | D23: عام | E23: Tracker | F23: إغلاق Wave 0 وتجميد الملفات | G23: تحديث التتبع: Wave 0 مكتمل + إعلان قائمة الملفات المجمّدة + تفعيل Wave 1. | H23: هذا الملف | I23: — | J23: 00-01..00-17, 00-19, 00-21 | K23: P0 | L23: S | M23: لم يبدأ | N23: Claude | O23: W0-Final | P23: =IFERROR(INDEX(WorkPackages!$H$5:$H$40,MATCH(B23,WorkPackages!$A$5:$A$40,0)),"") | S23: لا | U23: لا | V23: WP-00 (سُلِّم — بانتظار validate) | X23: =IF(W23="","—",IFERROR(IF(INDEX(BackendChecklist!$H$5:$H$30,MATCH(W23,BackendChecklist!$A$5:$A$30,0))="نعم","جاهز للبدء",IF(V23="الآن (بنمط seam)","يبدأ بنمط seam — الربط ينتظر","ينتظر الباك اند")),"؟"))
A24: T1-01 | B24: WP-T1 | C24: =IFERROR(INDEX(WorkPackages!$C$5:$C$40,MATCH(B24,WorkPackages!$A$5:$A$40,0)),"") | D24: FR-I01 | E24: UI | F24: قائمة كورسات المعلم | G24: استبدال placeholder «قيد التطوير» بقائمة حقيقية: العنوان، النوع (حضوري/أونلاين)، الحالة (مسودة/منشور/مؤرشف)، السعر، السعة. حالات تحميل/خطأ/فارغ. حذف نص P1-1 القديم. | H24: routes/_authenticated/teacher.courses.tsx | I24: Course/GetAll (أو بديل حسب Q-01) | J24: WP-00 | K24: P0 | L24: M | M24: لم يبدأ | P24: =IFERROR(INDEX(WorkPackages!$H$5:$H$40,MATCH(B24,WorkPackages!$A$5:$A$40,0)),"") | S24: لا | U24: نعم | V24: بعد JSON | W24: NE-10 | X24: =IF(W24="","—",IFERROR(IF(INDEX(BackendChecklist!$H$5:$H$30,MATCH(W24,BackendChecklist!$A$5:$A$30,0))="نعم","جاهز للبدء",IF(V24="الآن (بنمط seam)","يبدأ بنمط seam — الربط ينتظر","ينتظر الباك اند")),"؟"))
A25: T1-02 | B25: WP-T1 | C25: =IFERROR(INDEX(WorkPackages!$C$5:$C$40,MATCH(B25,WorkPackages!$A$5:$A$40,0)),"") | D25: FR-I01 | E25: UI | F25: أزرار «إنشاء كورس حضوري/أونلاين» | G25: تنقّل إلى /teacher/course/new?type=1|2 (التحقق من search param بـ zod). | H25: routes/_authenticated/teacher.courses.tsx | I25: — | J25: T1-01 | K25: P1 | L25: S | M25: قيد المراجعة | N25: المستخدم | O25: A-user (منفّذ) | P25: =IFERROR(INDEX(WorkPackages!$H$5:$H$40,MATCH(B25,WorkPackages!$A$5:$A$40,0)),"") | S25: لا | T25: نفّذه المستخدم؛ أضاف validateSearch (zod) لـteacher.course.$id.tsx (ملف T1) كي يقبل Link search بـtsc | U25: لا | V25: منفّذ — قيد المراجعة | X25: =IF(W25="","—",IFERROR(IF(INDEX(BackendChecklist!$H$5:$H$30,MATCH(W25,BackendChecklist!$A$5:$A$30,0))="نعم","جاهز للبدء",IF(V25="الآن (بنمط seam)","يبدأ بنمط seam — الربط ينتظر","ينتظر الباك اند")),"؟"))
A26: T1-03 | B26: WP-T1 | C26: =IFERROR(INDEX(WorkPackages!$C$5:$C$40,MATCH(B26,WorkPackages!$A$5:$A$40,0)),"") | D26: FR-I01 | E26: UI | F26: نموذج تفاصيل الكورس (حضوري) | G26: الحقول: العنوان، الوصف، المادة، التصنيف، الصف، السعر، الحد الأقصى، اسم المجموعة. تحقق بـ zod ورسائل. إرسال CreateEdit ثم الانتقال لـ /teacher/course/{returnId}. | H26: components/teacher/course-details-tab.tsx | I26: Course/CreateEdit | J26: T1-05 | K26: P0 | L26: M | M26: لم يبدأ | O26: مرشّح للبدء الآن | P26: =IFERROR(INDEX(WorkPackages!$H$5:$H$40,MATCH(B26,WorkPackages!$A$5:$A$40,0)),"") | S26: لا | U26: جزئي | V26: الآن (بنمط seam) | W26: NE-13 | X26: =IF(W26="","—",IFERROR(IF(INDEX(BackendChecklist!$H$5:$H$30,MATCH(W26,BackendChecklist!$A$5:$A$30,0))="نعم","جاهز للبدء",IF(V26="الآن (بنمط seam)","يبدأ بنمط seam — الربط ينتظر","ينتظر الباك اند")),"؟"))
A27: T1-04 | B27: WP-T1 | C27: =IFERROR(INDEX(WorkPackages!$C$5:$C$40,MATCH(B27,WorkPackages!$A$5:$A$40,0)),"") | D27: FR-I05 | E27: UI | F27: نموذج تفاصيل الكورس (أونلاين) | G27: نفس النموذج مع deliveryType=2 وتلميحات خاصة بالأونلاين (المنصة تُحدَّد على مستوى الدرس FR-I07). | H27: components/teacher/course-details-tab.tsx | I27: Course/CreateEdit | J27: T1-03 | K27: P1 | L27: S | M27: لم يبدأ | O27: مرشّح للبدء الآن | P27: =IFERROR(INDEX(WorkPackages!$H$5:$H$40,MATCH(B27,WorkPackages!$A$5:$A$40,0)),"") | S27: لا | U27: جزئي | V27: الآن (بنمط seam) | W27: NE-13 | X27: =IF(W27="","—",IFERROR(IF(INDEX(BackendChecklist!$H$5:$H$30,MATCH(W27,BackendChecklist!$A$5:$A$30,0))="نعم","جاهز للبدء",IF(V27="الآن (بنمط seam)","يبدأ بنمط seam — الربط ينتظر","ينتظر الباك اند")),"؟"))
A28: T1-05 | B28: WP-T1 | C28: =IFERROR(INDEX(WorkPackages!$C$5:$C$40,MATCH(B28,WorkPackages!$A$5:$A$40,0)),"") | D28: FR-I01 | E28: UI | F28: مصادر المادة/التصنيف/الصف | G28: قوائم الاختيار من endpoints مؤكَّدة (Q-04). لو القائمة فاضية: رسالة صادقة بدل بيانات مخترعة. | H28: components/teacher/course-details-tab.tsx | I28: Teacher/CreateEditModal, Constant/GetAll (يُحسم بـ Q-04) | J28: WP-00 | K28: P0 | L28: M | M28: لم يبدأ | P28: =IFERROR(INDEX(WorkPackages!$H$5:$H$40,MATCH(B28,WorkPackages!$A$5:$A$40,0)),"") | S28: لا | U28: نعم | V28: بعد JSON | W28: NE-13 | X28: =IF(W28="","—",IFERROR(IF(INDEX(BackendChecklist!$H$5:$H$30,MATCH(W28,BackendChecklist!$A$5:$A$30,0))="نعم","جاهز للبدء",IF(V28="الآن (بنمط seam)","يبدأ بنمط seam — الربط ينتظر","ينتظر الباك اند")),"؟"))
A29: T1-06 | B29: WP-T1 | C29: =IFERROR(INDEX(WorkPackages!$C$5:$C$40,MATCH(B29,WorkPackages!$A$5:$A$40,0)),"") | D29: FR-I01 | E29: UI | F29: مسار «حفظ كمسودة / نشر» | G29: saveAsDraft + تبديل النشر؛ إظهار حالة الكورس بعد الحفظ. | H29: components/teacher/course-details-tab.tsx | I29: Course/CreateEdit | J29: T1-03 | K29: P1 | L29: S | M29: لم يبدأ | O29: مرشّح للبدء الآن | P29: =IFERROR(INDEX(WorkPackages!$H$5:$H$40,MATCH(B29,WorkPackages!$A$5:$A$40,0)),"") | S29: لا | U29: جزئي | V29: الآن (بنمط seam) | W29: NE-13 | X29: =IF(W29="","—",IFERROR(IF(INDEX(BackendChecklist!$H$5:$H$30,MATCH(W29,BackendChecklist!$A$5:$A$30,0))="نعم","جاهز للبدء",IF(V29="الآن (بنمط seam)","يبدأ بنمط seam — الربط ينتظر","ينتظر الباك اند")),"؟"))
A30: T1-07 | B30: WP-T1 | C30: =IFERROR(INDEX(WorkPackages!$C$5:$C$40,MATCH(B30,WorkPackages!$A$5:$A$40,0)),"") | D30: FR-I01 | E30: UI | F30: Shell شاشة الكورس + التبويبات | G30: teacher.course.$id: ترويسة + SegmentedTabs عبر ?tab= (details|group|students|lessons)، تعطيل التبويبات قبل حفظ الكورس، تمرير course للتبويبات حسب العقد C-01. | H30: routes/_authenticated/teacher.course.$id.tsx | I30: Course/GetMineById | J30: WP-00 | K30: P0 | L30: M | M30: لم يبدأ | P30: =IFERROR(INDEX(WorkPackages!$H$5:$H$40,MATCH(B30,WorkPackages!$A$5:$A$40,0)),"") | S30: لا | U30: نعم | V30: بعد JSON | W30: NE-09 | X30: =IF(W30="","—",IFERROR(IF(INDEX(BackendChecklist!$H$5:$H$30,MATCH(W30,BackendChecklist!$A$5:$A$30,0))="نعم","جاهز للبدء",IF(V30="الآن (بنمط seam)","يبدأ بنمط seam — الربط ينتظر","ينتظر الباك اند")),"؟"))
A31: T1-08 | B31: WP-T1 | C31: =IFERROR(INDEX(WorkPackages!$C$5:$C$40,MATCH(B31,WorkPackages!$A$5:$A$40,0)),"") | D31: FR-I01 | E31: Test | F31: اختبارات مخطط التحقق | G31: اختبارات vitest لقواعد النموذج (حقول مطلوبة، سعر ≥ 0، سعة ≥ 1). | H31: components/teacher/course-details-tab.test.ts | I31: — | J31: T1-03 | K31: P1 | L31: S | M31: لم يبدأ | O31: مرشّح للبدء الآن | P31: =IFERROR(INDEX(WorkPackages!$H$5:$H$40,MATCH(B31,WorkPackages!$A$5:$A$40,0)),"") | S31: لا | U31: جزئي | V31: الآن (بنمط seam) | X31: =IF(W31="","—",IFERROR(IF(INDEX(BackendChecklist!$H$5:$H$30,MATCH(W31,BackendChecklist!$A$5:$A$30,0))="نعم","جاهز للبدء",IF(V31="الآن (بنمط seam)","يبدأ بنمط seam — الربط ينتظر","ينتظر الباك اند")),"؟"))
A32: T2-01 | B32: WP-T2 | C32: =IFERROR(INDEX(WorkPackages!$C$5:$C$40,MATCH(B32,WorkPackages!$A$5:$A$40,0)),"") | D32: FR-I02 | E32: UI | F32: نموذج إعداد مجموعة حضورية | G32: الحد الأقصى للطلاب، تاريخ بداية/نهاية الكورس، مدة الدرس الافتراضية، صفوف أيام الحضور (يوم + وقت) قابلة للإضافة/الحذف → ConfigureGroupSchedule. | H32: components/teacher/group-config-tab.tsx | I32: Course/ConfigureGroupSchedule | J32: WP-00 | K32: P0 | L32: M | M32: لم يبدأ | O32: مرشّح للبدء الآن | P32: =IFERROR(INDEX(WorkPackages!$H$5:$H$40,MATCH(B32,WorkPackages!$A$5:$A$40,0)),"") | S32: لا | U32: جزئي | V32: الآن (بنمط seam) | W32: NE-09 | X32: =IF(W32="","—",IFERROR(IF(INDEX(BackendChecklist!$H$5:$H$30,MATCH(W32,BackendChecklist!$A$5:$A$30,0))="نعم","جاهز للبدء",IF(V32="الآن (بنمط seam)","يبدأ بنمط seam — الربط ينتظر","ينتظر الباك اند")),"؟"))
A33: T2-02 | B33: WP-T2 | C33: =IFERROR(INDEX(WorkPackages!$C$5:$C$40,MATCH(B33,WorkPackages!$A$5:$A$40,0)),"") | D33: FR-I06 | E33: UI | F33: نفس النموذج للمجموعة الأونلاين | G33: حسب deliveryType للكورس: عناوين ونصوص مساعدة مختلفة، نفس الحقول. | H33: components/teacher/group-config-tab.tsx | I33: Course/ConfigureGroupSchedule | J33: T2-01 | K33: P0 | L33: S | M33: لم يبدأ | O33: مرشّح للبدء الآن | P33: =IFERROR(INDEX(WorkPackages!$H$5:$H$40,MATCH(B33,WorkPackages!$A$5:$A$40,0)),"") | S33: لا | U33: جزئي | V33: الآن (بنمط seam) | W33: NE-09 | X33: =IF(W33="","—",IFERROR(IF(INDEX(BackendChecklist!$H$5:$H$30,MATCH(W33,BackendChecklist!$A$5:$A$30,0))="نعم","جاهز للبدء",IF(V33="الآن (بنمط seam)","يبدأ بنمط seam — الربط ينتظر","ينتظر الباك اند")),"؟"))
A34: T2-03 | B34: WP-T2 | C34: =IFERROR(INDEX(WorkPackages!$C$5:$C$40,MATCH(B34,WorkPackages!$A$5:$A$40,0)),"") | D34: FR-I02 | E34: UI | F34: التحقق من صحة الجدول (عميل) | G34: نهاية ≥ بداية، مدة > 0، سعة ≥ 1، يوم واحد على الأقل بدون تكرار نفس اليوم، الوقت صالح. | H34: components/teacher/group-config-tab.tsx | I34: — | J34: T2-01 | K34: P0 | L34: S | M34: قيد المراجعة | N34: المستخدم | O34: A-user (منفّذ) | P34: =IFERROR(INDEX(WorkPackages!$H$5:$H$40,MATCH(B34,WorkPackages!$A$5:$A$40,0)),"") | S34: لا | T34: نفّذه المستخدم (wave1-half-claude-files.zip)؛ بانتظار validate | U34: لا | V34: منفّذ — قيد المراجعة | X34: =IF(W34="","—",IFERROR(IF(INDEX(BackendChecklist!$H$5:$H$30,MATCH(W34,BackendChecklist!$A$5:$A$30,0))="نعم","جاهز للبدء",IF(V34="الآن (بنمط seam)","يبدأ بنمط seam — الربط ينتظر","ينتظر الباك اند")),"؟"))
A35: T2-04 | B35: WP-T2 | C35: =IFERROR(INDEX(WorkPackages!$C$5:$C$40,MATCH(B35,WorkPackages!$A$5:$A$40,0)),"") | D35: FR-I02 | E35: UI | F35: تحميل الإعداد الحالي للتعديل | G35: Alternative Flow: تعديل الجدول/السعة قبل بدء الكورس. يعتمد على ما يرجعه GetMineById (Q-02). لو غير متاح: عرض آخر قيم محفوظة بالجلسة فقط وتوثيق ذلك. | H35: components/teacher/group-config-tab.tsx | I35: Course/GetMineById | J35: T2-01 | K35: P1 | L35: M | M35: لم يبدأ | P35: =IFERROR(INDEX(WorkPackages!$H$5:$H$40,MATCH(B35,WorkPackages!$A$5:$A$40,0)),"") | S35: لا | U35: نعم | V35: بعد JSON | W35: NE-09 | X35: =IF(W35="","—",IFERROR(IF(INDEX(BackendChecklist!$H$5:$H$30,MATCH(W35,BackendChecklist!$A$5:$A$30,0))="نعم","جاهز للبدء",IF(V35="الآن (بنمط seam)","يبدأ بنمط seam — الربط ينتظر","ينتظر الباك اند")),"؟"))
A36: T2-05 | B36: WP-T2 | C36: =IFERROR(INDEX(WorkPackages!$C$5:$C$40,MATCH(B36,WorkPackages!$A$5:$A$40,0)),"") | D36: FR-I06 | E36: UI | F36: عرض أخطاء الباك اند (تعارض/تحقق) | G36: رسائل التعارض مع دروس مجدولة تظهر بوضوح داخل النموذج وتمنع الحفظ (Exception Flow). | H36: components/teacher/group-config-tab.tsx | I36: — | J36: T2-01 | K36: P0 | L36: S | M36: لم يبدأ | O36: مرشّح للبدء الآن | P36: =IFERROR(INDEX(WorkPackages!$H$5:$H$40,MATCH(B36,WorkPackages!$A$5:$A$40,0)),"") | S36: لا | U36: جزئي | V36: الآن (بنمط seam) | W36: NE-09 | X36: =IF(W36="","—",IFERROR(IF(INDEX(BackendChecklist!$H$5:$H$30,MATCH(W36,BackendChecklist!$A$5:$A$30,0))="نعم","جاهز للبدء",IF(V36="الآن (بنمط seam)","يبدأ بنمط seam — الربط ينتظر","ينتظر الباك اند")),"؟"))
A37: T2-06 | B37: WP-T2 | C37: =IFERROR(INDEX(WorkPackages!$C$5:$C$40,MATCH(B37,WorkPackages!$A$5:$A$40,0)),"") | D37: FR-I02 | E37: Test | F37: اختبارات المحققات | G37: اختبارات للتحقق من الجدول (نقية). | H37: components/teacher/group-config-tab.test.ts | I37: — | J37: T2-03 | K37: P1 | L37: S | M37: لم يبدأ | O37: مرشّح للبدء الآن | P37: =IFERROR(INDEX(WorkPackages!$H$5:$H$40,MATCH(B37,WorkPackages!$A$5:$A$40,0)),"") | S37: لا | U37: جزئي | V37: الآن (بنمط seam) | W37: NE-09 | X37: =IF(W37="","—",IFERROR(IF(INDEX(BackendChecklist!$H$5:$H$30,MATCH(W37,BackendChecklist!$A$5:$A$30,0))="نعم","جاهز للبدء",IF(V37="الآن (بنمط seam)","يبدأ بنمط seam — الربط ينتظر","ينتظر الباك اند")),"؟"))
A38: T3-01 | B38: WP-T3 | C38: =IFERROR(INDEX(WorkPackages!$C$5:$C$40,MATCH(B38,WorkPackages!$A$5:$A$40,0)),"") | D38: FR-I03 | E38: UI | F38: جدول طلاب المجموعة | G38: اسم + هاتف + موقع فقط (حقول محدودة حسب ملاحظة الخصوصية في SRS). لا تعرض أي حقل إضافي يرجعه الباك اند. | H38: components/teacher/group-students-tab.tsx | I38: Course/GetGroupStudents | J38: WP-00 | K38: P0 | L38: S | M38: لم يبدأ | P38: =IFERROR(INDEX(WorkPackages!$H$5:$H$40,MATCH(B38,WorkPackages!$A$5:$A$40,0)),"") | S38: لا | U38: نعم | V38: بعد JSON | W38: NE-11 | X38: =IF(W38="","—",IFERROR(IF(INDEX(BackendChecklist!$H$5:$H$30,MATCH(W38,BackendChecklist!$A$5:$A$30,0))="نعم","جاهز للبدء",IF(V38="الآن (بنمط seam)","يبدأ بنمط seam — الربط ينتظر","ينتظر الباك اند")),"؟"))
A39: T3-02 | B39: WP-T3 | C39: =IFERROR(INDEX(WorkPackages!$C$5:$C$40,MATCH(B39,WorkPackages!$A$5:$A$40,0)),"") | D39: FR-I03 | E39: UI | F39: بحث بالاسم | G39: keyword مع useDebouncedValue (موجود بالمشروع). | H39: components/teacher/group-students-tab.tsx | I39: Course/GetGroupStudents | J39: T3-01 | K39: P1 | L39: S | M39: لم يبدأ | P39: =IFERROR(INDEX(WorkPackages!$H$5:$H$40,MATCH(B39,WorkPackages!$A$5:$A$40,0)),"") | S39: لا | U39: نعم | V39: بعد JSON | W39: NE-11 | X39: =IF(W39="","—",IFERROR(IF(INDEX(BackendChecklist!$H$5:$H$30,MATCH(W39,BackendChecklist!$A$5:$A$30,0))="نعم","جاهز للبدء",IF(V39="الآن (بنمط seam)","يبدأ بنمط seam — الربط ينتظر","ينتظر الباك اند")),"؟"))
A40: T3-03 | B40: WP-T3 | C40: =IFERROR(INDEX(WorkPackages!$C$5:$C$40,MATCH(B40,WorkPackages!$A$5:$A$40,0)),"") | D40: FR-I03 | E40: UI | F40: حالات التحميل/الخطأ/الفراغ | G40: رسالة «لا يوجد طلاب مقبولون بعد» عند الفراغ؛ ErrorState مع إعادة المحاولة. | H40: components/teacher/group-students-tab.tsx | I40: — | J40: T3-01 | K40: P0 | L40: S | M40: لم يبدأ | P40: =IFERROR(INDEX(WorkPackages!$H$5:$H$40,MATCH(B40,WorkPackages!$A$5:$A$40,0)),"") | S40: لا | U40: نعم | V40: بعد JSON | W40: NE-11 | X40: =IF(W40="","—",IFERROR(IF(INDEX(BackendChecklist!$H$5:$H$30,MATCH(W40,BackendChecklist!$A$5:$A$30,0))="نعم","جاهز للبدء",IF(V40="الآن (بنمط seam)","يبدأ بنمط seam — الربط ينتظر","ينتظر الباك اند")),"؟"))
A41: T3-04 | B41: WP-T3 | C41: =IFERROR(INDEX(WorkPackages!$C$5:$C$40,MATCH(B41,WorkPackages!$A$5:$A$40,0)),"") | D41: FR-I03 | E41: UI | F41: اختيار المجموعة (إن تعدّدت) | G41: لو الكورس فيه أكثر من مجموعة (Q-02) → قائمة اختيار؛ وإلا تُستخدم الوحيدة تلقائيًا. | H41: components/teacher/group-students-tab.tsx | I41: — | J41: T3-01 | K41: P1 | L41: S | M41: لم يبدأ | P41: =IFERROR(INDEX(WorkPackages!$H$5:$H$40,MATCH(B41,WorkPackages!$A$5:$A$40,0)),"") | S41: لا | U41: نعم | V41: بعد JSON | W41: NE-11 | X41: =IF(W41="","—",IFERROR(IF(INDEX(BackendChecklist!$H$5:$H$30,MATCH(W41,BackendChecklist!$A$5:$A$30,0))="نعم","جاهز للبدء",IF(V41="الآن (بنمط seam)","يبدأ بنمط seam — الربط ينتظر","ينتظر الباك اند")),"؟"))
A42: T4-01 | B42: WP-T4 | C42: =IFERROR(INDEX(WorkPackages!$C$5:$C$40,MATCH(B42,WorkPackages!$A$5:$A$40,0)),"") | D42: FR-I09 | E42: UI | F42: قائمة الدروس (الجدول الزمني) | G42: GetSchedule(courseId, groupId): رقم، موضوع، تاريخ، يوم، وقت، مدة، حالة، + (قاعة | منصة+رابط). مرتبة زمنيًا؛ فلتر حالة/تاريخ؛ حالة فارغة. | H42: components/teacher/lessons-tab.tsx | I42: Lesson/GetSchedule | J42: WP-00 | K42: P0 | L42: M | M42: لم يبدأ | P42: =IFERROR(INDEX(WorkPackages!$H$5:$H$40,MATCH(B42,WorkPackages!$A$5:$A$40,0)),"") | S42: لا | U42: نعم | V42: بعد JSON | W42: NE-12 | X42: =IF(W42="","—",IFERROR(IF(INDEX(BackendChecklist!$H$5:$H$30,MATCH(W42,BackendChecklist!$A$5:$A$30,0))="نعم","جاهز للبدء",IF(V42="الآن (بنمط seam)","يبدأ بنمط seam — الربط ينتظر","ينتظر الباك اند")),"؟"))
A43: T4-02 | B43: WP-T4 | C43: =IFERROR(INDEX(WorkPackages!$C$5:$C$40,MATCH(B43,WorkPackages!$A$5:$A$40,0)),"") | D43: FR-I04 | E43: UI | F43: نموذج درس حضوري | G43: رقم الدرس (orderIndex)، الموضوع، التاريخ، وقت البدء، المدة، القاعة (اختياري). اليوم يُشتق من التاريخ ويُعرض. → Lesson/Create. | H43: components/teacher/lesson-form-dialog.tsx | I43: Lesson/Create | J43: T4-01 | K43: P0 | L43: M | M43: قيد المراجعة | N43: المستخدم | O43: A-user (منفّذ) | P43: =IFERROR(INDEX(WorkPackages!$H$5:$H$40,MATCH(B43,WorkPackages!$A$5:$A$40,0)),"") | S43: لا | T43: نفّذه المستخدم (wave1-half-claude-files.zip)؛ بانتظار validate | U43: لا | V43: منفّذ — قيد المراجعة | X43: =IF(W43="","—",IFERROR(IF(INDEX(BackendChecklist!$H$5:$H$30,MATCH(W43,BackendChecklist!$A$5:$A$30,0))="نعم","جاهز للبدء",IF(V43="الآن (بنمط seam)","يبدأ بنمط seam — الربط ينتظر","ينتظر الباك اند")),"؟"))
A44: T4-03 | B44: WP-T4 | C44: =IFERROR(INDEX(WorkPackages!$C$5:$C$40,MATCH(B44,WorkPackages!$A$5:$A$40,0)),"") | D44: FR-I08 | E44: UI | F44: نموذج درس أونلاين | G44: نفس الحقول + المنصة (Zoom/Meet/Teams/أخرى) + الرابط (http/https فقط) + تعليمات اختيارية. → Lesson/Create. | H44: components/teacher/lesson-form-dialog.tsx | I44: Lesson/Create | J44: T4-02 | K44: P0 | L44: M | M44: قيد المراجعة | N44: المستخدم | O44: A-user (منفّذ) | P44: =IFERROR(INDEX(WorkPackages!$H$5:$H$40,MATCH(B44,WorkPackages!$A$5:$A$40,0)),"") | S44: لا | T44: نفّذه المستخدم (wave1-half-claude-files.zip)؛ بانتظار validate | U44: لا | V44: منفّذ — قيد المراجعة | X44: =IF(W44="","—",IFERROR(IF(INDEX(BackendChecklist!$H$5:$H$30,MATCH(W44,BackendChecklist!$A$5:$A$30,0))="نعم","جاهز للبدء",IF(V44="الآن (بنمط seam)","يبدأ بنمط seam — الربط ينتظر","ينتظر الباك اند")),"؟"))
A45: T4-04 | B45: WP-T4 | C45: =IFERROR(INDEX(WorkPackages!$C$5:$C$40,MATCH(B45,WorkPackages!$A$5:$A$40,0)),"") | D45: FR-I10 | E45: UI | F45: تعديل درس مجدول | G45: متاح فقط لدرس لم يبدأ وغير ملغى. → Lesson/Update. | H45: components/teacher/lesson-form-dialog.tsx | I45: Lesson/Update | J45: T4-02 | K45: P1 | L45: S | M45: قيد المراجعة | N45: المستخدم | O45: A-user (منفّذ) | P45: =IFERROR(INDEX(WorkPackages!$H$5:$H$40,MATCH(B45,WorkPackages!$A$5:$A$40,0)),"") | S45: لا | T45: نفّذه المستخدم (wave1-half-claude-files.zip)؛ بانتظار validate | U45: لا | V45: منفّذ — قيد المراجعة | X45: =IF(W45="","—",IFERROR(IF(INDEX(BackendChecklist!$H$5:$H$30,MATCH(W45,BackendChecklist!$A$5:$A$30,0))="نعم","جاهز للبدء",IF(V45="الآن (بنمط seam)","يبدأ بنمط seam — الربط ينتظر","ينتظر الباك اند")),"؟"))
A46: T4-05 | B46: WP-T4 | C46: =IFERROR(INDEX(WorkPackages!$C$5:$C$40,MATCH(B46,WorkPackages!$A$5:$A$40,0)),"") | D46: FR-I07 | E46: UI | F46: تعديل بيانات الاجتماع فقط | G46: إجراء سريع لدرس أونلاين: منصة/رابط/تعليمات. → Lesson/ConfigureMeeting. التحقق من الرابط. | H46: components/teacher/lessons-tab.tsx | I46: Lesson/ConfigureMeeting | J46: T4-03 | K46: P1 | L46: S | M46: لم يبدأ | O46: مرشّح للبدء الآن | P46: =IFERROR(INDEX(WorkPackages!$H$5:$H$40,MATCH(B46,WorkPackages!$A$5:$A$40,0)),"") | S46: لا | U46: جزئي | V46: الآن (بنمط seam) | W46: NE-12 | X46: =IF(W46="","—",IFERROR(IF(INDEX(BackendChecklist!$H$5:$H$30,MATCH(W46,BackendChecklist!$A$5:$A$30,0))="نعم","جاهز للبدء",IF(V46="الآن (بنمط seam)","يبدأ بنمط seam — الربط ينتظر","ينتظر الباك اند")),"؟"))
A47: T4-06 | B47: WP-T4 | C47: =IFERROR(INDEX(WorkPackages!$C$5:$C$40,MATCH(B47,WorkPackages!$A$5:$A$40,0)),"") | D47: FR-I11 | E47: UI | F47: إلغاء درس بسبب | G47: نافذة تأكيد + سبب اختياري. يبقى الدرس بالسجل بحالة ملغى. → Lesson/Cancel. | H47: components/teacher/lesson-cancel-dialog.tsx | I47: Lesson/Cancel | J47: T4-01 | K47: P1 | L47: S | M47: قيد المراجعة | N47: المستخدم | O47: A-user (منفّذ) | P47: =IFERROR(INDEX(WorkPackages!$H$5:$H$40,MATCH(B47,WorkPackages!$A$5:$A$40,0)),"") | S47: لا | T47: نفّذه المستخدم (wave1-half-claude-files.zip)؛ بانتظار validate | U47: لا | V47: منفّذ — قيد المراجعة | X47: =IF(W47="","—",IFERROR(IF(INDEX(BackendChecklist!$H$5:$H$30,MATCH(W47,BackendChecklist!$A$5:$A$30,0))="نعم","جاهز للبدء",IF(V47="الآن (بنمط seam)","يبدأ بنمط seam — الربط ينتظر","ينتظر الباك اند")),"؟"))
A48: T4-07 | B48: WP-T4 | C48: =IFERROR(INDEX(WorkPackages!$C$5:$C$40,MATCH(B48,WorkPackages!$A$5:$A$40,0)),"") | D48: FR-I04 | E48: UI | F48: عرض أخطاء التعارض/التحقق | G48: رسائل الباك اند (تعارض درس، تاريخ/وقت غير صالح) تظهر داخل النموذج وتمنع الحفظ. | H48: components/teacher/lesson-form-dialog.tsx | I48: — | J48: T4-02 | K48: P0 | L48: S | M48: قيد المراجعة | N48: المستخدم | O48: A-user (منفّذ) | P48: =IFERROR(INDEX(WorkPackages!$H$5:$H$40,MATCH(B48,WorkPackages!$A$5:$A$40,0)),"") | S48: لا | T48: نفّذه المستخدم (wave1-half-claude-files.zip)؛ بانتظار validate | U48: لا | V48: منفّذ — قيد المراجعة | X48: =IF(W48="","—",IFERROR(IF(INDEX(BackendChecklist!$H$5:$H$30,MATCH(W48,BackendChecklist!$A$5:$A$30,0))="نعم","جاهز للبدء",IF(V48="الآن (بنمط seam)","يبدأ بنمط seam — الربط ينتظر","ينتظر الباك اند")),"؟"))
A49: T4-08 | B49: WP-T4 | C49: =IFERROR(INDEX(WorkPackages!$C$5:$C$40,MATCH(B49,WorkPackages!$A$5:$A$40,0)),"") | D49: FR-I08 | E49: Test | F49: اختبارات محققات الدرس/الرابط | G49: isHttpUrl، اشتقاق اليوم، حدود المدة. | H49: components/teacher/lesson-form-dialog.test.ts | I49: — | J49: T4-03 | K49: P1 | L49: S | M49: قيد المراجعة | N49: المستخدم | O49: A-user (منفّذ) | P49: =IFERROR(INDEX(WorkPackages!$H$5:$H$40,MATCH(B49,WorkPackages!$A$5:$A$40,0)),"") | S49: لا | T49: نفّذه المستخدم (wave1-half-claude-files.zip)؛ بانتظار validate | U49: لا | V49: منفّذ — قيد المراجعة | X49: =IF(W49="","—",IFERROR(IF(INDEX(BackendChecklist!$H$5:$H$30,MATCH(W49,BackendChecklist!$A$5:$A$30,0))="نعم","جاهز للبدء",IF(V49="الآن (بنمط seam)","يبدأ بنمط seam — الربط ينتظر","ينتظر الباك اند")),"؟"))
A50: T5-01 | B50: WP-T5 | C50: =IFERROR(INDEX(WorkPackages!$C$5:$C$40,MATCH(B50,WorkPackages!$A$5:$A$40,0)),"") | D50: FR-T10 | E50: UI | F50: قائمة طلبات الحجز (معلم) | G50: TeacherBookings مع فلتر حالة (معلّق/مؤكد/مكتمل/مرفوض/ملغى) + بيانات الطالب والجلسة والوضع والرسوم. | H50: routes/_authenticated/teacher.bookings.tsx | I50: Booking/TeacherBookings | J50: WP-00 | K50: P0 | L50: M | M50: لم يبدأ | P50: =IFERROR(INDEX(WorkPackages!$H$5:$H$40,MATCH(B50,WorkPackages!$A$5:$A$40,0)),"") | S50: لا | U50: نعم | V50: بعد JSON | W50: NE-01 | X50: =IF(W50="","—",IFERROR(IF(INDEX(BackendChecklist!$H$5:$H$30,MATCH(W50,BackendChecklist!$A$5:$A$30,0))="نعم","جاهز للبدء",IF(V50="الآن (بنمط seam)","يبدأ بنمط seam — الربط ينتظر","ينتظر الباك اند")),"؟"))
A51: T5-02 | B51: WP-T5 | C51: =IFERROR(INDEX(WorkPackages!$C$5:$C$40,MATCH(B51,WorkPackages!$A$5:$A$40,0)),"") | D51: FR-T06 | E51: UI | F51: قبول/رفض الطلب | G51: Decide {bookingId, accept, rejectionReason}. السبب مطلوب عند الرفض. إظهار رسالة الباك اند عند فشل الخصم (رصيد الطالب غير كافٍ). | H51: routes/_authenticated/teacher.bookings.tsx | I51: Booking/Decide | J51: T5-01 | K51: P0 | L51: M | M51: لم يبدأ | O51: مرشّح للبدء الآن | P51: =IFERROR(INDEX(WorkPackages!$H$5:$H$40,MATCH(B51,WorkPackages!$A$5:$A$40,0)),"") | S51: لا | U51: جزئي | V51: الآن (بنمط seam) | W51: NE-01 | X51: =IF(W51="","—",IFERROR(IF(INDEX(BackendChecklist!$H$5:$H$30,MATCH(W51,BackendChecklist!$A$5:$A$30,0))="نعم","جاهز للبدء",IF(V51="الآن (بنمط seam)","يبدأ بنمط seam — الربط ينتظر","ينتظر الباك اند")),"؟"))
A52: T5-03 | B52: WP-T5 | C52: =IFERROR(INDEX(WorkPackages!$C$5:$C$40,MATCH(B52,WorkPackages!$A$5:$A$40,0)),"") | D52: FR-T10 | E52: UI | F52: إنهاء حصة مؤكّدة | G52: Complete للحجز المؤكد (Confirmed → Completed) مع تأكيد. | H52: routes/_authenticated/teacher.bookings.tsx | I52: Booking/Complete | J52: T5-01 | K52: P1 | L52: S | M52: لم يبدأ | O52: مرشّح للبدء الآن | P52: =IFERROR(INDEX(WorkPackages!$H$5:$H$40,MATCH(B52,WorkPackages!$A$5:$A$40,0)),"") | S52: لا | U52: جزئي | V52: الآن (بنمط seam) | W52: NE-01 | X52: =IF(W52="","—",IFERROR(IF(INDEX(BackendChecklist!$H$5:$H$30,MATCH(W52,BackendChecklist!$A$5:$A$30,0))="نعم","جاهز للبدء",IF(V52="الآن (بنمط seam)","يبدأ بنمط seam — الربط ينتظر","ينتظر الباك اند")),"؟"))
A53: T5-04 | B53: WP-T5 | C53: =IFERROR(INDEX(WorkPackages!$C$5:$C$40,MATCH(B53,WorkPackages!$A$5:$A$40,0)),"") | D53: FR-S15 | E53: UI | F53: طلبات إعادة الجدولة (جهة المعلم) | G53: TeacherRescheduleRequests + DecideReschedule {requestId, approve, rejectionReason}. | H53: routes/_authenticated/teacher.bookings.tsx | I53: Booking/TeacherRescheduleRequests, DecideReschedule | J53: T5-01 | K53: P0 | L53: M | M53: لم يبدأ | P53: =IFERROR(INDEX(WorkPackages!$H$5:$H$40,MATCH(B53,WorkPackages!$A$5:$A$40,0)),"") | S53: لا | U53: نعم | V53: بعد JSON | W53: NE-01 | X53: =IF(W53="","—",IFERROR(IF(INDEX(BackendChecklist!$H$5:$H$30,MATCH(W53,BackendChecklist!$A$5:$A$30,0))="نعم","جاهز للبدء",IF(V53="الآن (بنمط seam)","يبدأ بنمط seam — الربط ينتظر","ينتظر الباك اند")),"؟"))
A54: T5-05 | B54: WP-T5 | C54: =IFERROR(INDEX(WorkPackages!$C$5:$C$40,MATCH(B54,WorkPackages!$A$5:$A$40,0)),"") | D54: FR-T10 | E54: UI | F54: لوحة المعلم: استبدال اللوحة المعطّلة | G54: حذف نص «معطّل بقصد P0-1/P1-1» (قديم) وعرض عدد الطلبات المعلقة + رابط /teacher/bookings. لا تعرض أي رقم مخترع. | H54: routes/_authenticated/teacher.dashboard.tsx | I54: Booking/TeacherBookings | J54: T5-01 | K54: P1 | L54: S | M54: قيد المراجعة | N54: المستخدم | O54: A-user (منفّذ) | P54: =IFERROR(INDEX(WorkPackages!$H$5:$H$40,MATCH(B54,WorkPackages!$A$5:$A$40,0)),"") | S54: لا | T54: نفّذه المستخدم (wave1-half-claude-files.zip)؛ بانتظار validate | U54: لا | V54: منفّذ — قيد المراجعة | X54: =IF(W54="","—",IFERROR(IF(INDEX(BackendChecklist!$H$5:$H$30,MATCH(W54,BackendChecklist!$A$5:$A$30,0))="نعم","جاهز للبدء",IF(V54="الآن (بنمط seam)","يبدأ بنمط seam — الربط ينتظر","ينتظر الباك اند")),"؟"))
A55: T5-06 | B55: WP-T5 | C55: =IFERROR(INDEX(WorkPackages!$C$5:$C$40,MATCH(B55,WorkPackages!$A$5:$A$40,0)),"") | D55: FR-T10 | E55: Test | F55: حالات الفراغ والخطأ + اختبارات | G55: حالة فارغة لكل تبويب حالة، ErrorState، اختبار للمنطق النقي إن وُجد. | H55: routes/_authenticated/teacher.bookings.tsx | I55: — | J55: T5-01 | K55: P1 | L55: S | M55: لم يبدأ | P55: =IFERROR(INDEX(WorkPackages!$H$5:$H$40,MATCH(B55,WorkPackages!$A$5:$A$40,0)),"") | S55: لا | U55: نعم | V55: بعد JSON | W55: NE-01 | X55: =IF(W55="","—",IFERROR(IF(INDEX(BackendChecklist!$H$5:$H$30,MATCH(W55,BackendChecklist!$A$5:$A$30,0))="نعم","جاهز للبدء",IF(V55="الآن (بنمط seam)","يبدأ بنمط seam — الربط ينتظر","ينتظر الباك اند")),"؟"))
A56: S1-01 | B56: WP-S1 | C56: =IFERROR(INDEX(WorkPackages!$C$5:$C$40,MATCH(B56,WorkPackages!$A$5:$A$40,0)),"") | D56: FR-T06 | E56: UI | F56: تحميل بيانات المعلم والتوفّر | G56: استخدام getTeacherPublicProfile و getTeacherAvailability الموجودتين. 404 → رسالة غير موجود. | H56: routes/_authenticated/book.$teacherId.tsx | I56: Teacher/PublicProfile, Availability | J56: WP-00 | K56: P0 | L56: S | M56: قيد المراجعة | N56: Claude | O56: A-claude (منفّذ) | P56: =IFERROR(INDEX(WorkPackages!$H$5:$H$40,MATCH(B56,WorkPackages!$A$5:$A$40,0)),"") | S56: لا | T56: نفّذه Claude؛ book.$teacherId.tsx: تحميل الملف العام والتوفّر + حالات تحميل/خطأ/غير موجود — بانتظار validate | U56: لا | V56: منفّذ — قيد المراجعة | X56: =IF(W56="","—",IFERROR(IF(INDEX(BackendChecklist!$H$5:$H$30,MATCH(W56,BackendChecklist!$A$5:$A$30,0))="نعم","جاهز للبدء",IF(V56="الآن (بنمط seam)","يبدأ بنمط seam — الربط ينتظر","ينتظر الباك اند")),"؟"))
A57: S1-02 | B57: WP-S1 | C57: =IFERROR(INDEX(WorkPackages!$C$5:$C$40,MATCH(B57,WorkPackages!$A$5:$A$40,0)),"") | D57: FR-T06 | E57: UI | F57: منتقي الوضع/اليوم/الوقت | G57: الوضع (أونلاين/حضوري) حسب ما يدعمه المعلم؛ التاريخ؛ الوقت من فترات التوفّر لنفس يوم الأسبوع؛ المدة (≤ 480 د). | H57: components/student/booking-slot-picker.tsx | I57: Teacher/Availability | J57: S1-01 | K57: P0 | L57: L | M57: قيد المراجعة | N57: Claude | O57: A-claude (منفّذ) | P57: =IFERROR(INDEX(WorkPackages!$H$5:$H$40,MATCH(B57,WorkPackages!$A$5:$A$40,0)),"") | S57: لا | T57: نفّذه Claude؛ booking-slot-picker.tsx + lib/booking-slots.ts (أوقات متاحة حسب اليوم/الوضع/المدة) — بانتظار validate | U57: لا | V57: منفّذ — قيد المراجعة | X57: =IF(W57="","—",IFERROR(IF(INDEX(BackendChecklist!$H$5:$H$30,MATCH(W57,BackendChecklist!$A$5:$A$30,0))="نعم","جاهز للبدء",IF(V57="الآن (بنمط seam)","يبدأ بنمط seam — الربط ينتظر","ينتظر الباك اند")),"؟"))
A58: S1-03 | B58: WP-S1 | C58: =IFERROR(INDEX(WorkPackages!$C$5:$C$40,MATCH(B58,WorkPackages!$A$5:$A$40,0)),"") | D58: FR-T06 | E58: UI | F58: اختيار المادة والصف (IDs) | G58: Submit يتطلب subjectId/gradeId أرقامًا؛ الملف العام يرجع أسماء فقط → المصدر من Q-04. | H58: routes/_authenticated/book.$teacherId.tsx | I58: Teacher/CreateEditModal أو Constant/GetAll (Q-04) | J58: S1-01 | K58: P0 | L58: M | M58: لم يبدأ | P58: =IFERROR(INDEX(WorkPackages!$H$5:$H$40,MATCH(B58,WorkPackages!$A$5:$A$40,0)),"") | S58: لا | U58: نعم | V58: بعد JSON | W58: NE-13 | X58: =IF(W58="","—",IFERROR(IF(INDEX(BackendChecklist!$H$5:$H$30,MATCH(W58,BackendChecklist!$A$5:$A$30,0))="نعم","جاهز للبدء",IF(V58="الآن (بنمط seam)","يبدأ بنمط seam — الربط ينتظر","ينتظر الباك اند")),"؟"))
A59: S1-04 | B59: WP-S1 | C59: =IFERROR(INDEX(WorkPackages!$C$5:$C$40,MATCH(B59,WorkPackages!$A$5:$A$40,0)),"") | D59: FR-T06 | E59: UI | F59: تقدير السعر وفحص الرصيد | G59: سعر تقديري = سعر الساعة × المدة (مع تسمية «تقديري»). getMyWallet → InsufficientBalanceAlert مع رابط /wallet. نص يوضّح متى يُخصم المبلغ (يُؤكَّد بـ Q-06). | H59: routes/_authenticated/book.$teacherId.tsx | I59: Wallet/MyWallet | J59: S1-02 | K59: P0 | L59: M | M59: قيد المراجعة | N59: Claude | O59: A-claude (منفّذ) | P59: =IFERROR(INDEX(WorkPackages!$H$5:$H$40,MATCH(B59,WorkPackages!$A$5:$A$40,0)),"") | S59: لا | T59: نفّذه Claude؛ سعر تقديري + فحص الرصيد (InsufficientBalanceAlert) + نص لحظة الخصم (Q-06 افتراض) — بانتظار validate | U59: لا | V59: منفّذ — قيد المراجعة | X59: =IF(W59="","—",IFERROR(IF(INDEX(BackendChecklist!$H$5:$H$30,MATCH(W59,BackendChecklist!$A$5:$A$30,0))="نعم","جاهز للبدء",IF(V59="الآن (بنمط seam)","يبدأ بنمط seam — الربط ينتظر","ينتظر الباك اند")),"؟"))
A60: S1-05 | B60: WP-S1 | C60: =IFERROR(INDEX(WorkPackages!$C$5:$C$40,MATCH(B60,WorkPackages!$A$5:$A$40,0)),"") | D60: FR-T06 | E60: UI | F60: إرسال الحجز | G60: Booking/Submit → assertOk → الانتقال لـ /booking/{returnId}. عرض رسائل الباك اند للفشل. invalidateBookingQueries. | H60: routes/_authenticated/book.$teacherId.tsx | I60: Booking/Submit | J60: S1-02, S1-03 | K60: P0 | L60: M | M60: لم يبدأ | P60: =IFERROR(INDEX(WorkPackages!$H$5:$H$40,MATCH(B60,WorkPackages!$A$5:$A$40,0)),"") | S60: لا | U60: نعم | V60: بعد JSON | W60: NE-13 | X60: =IF(W60="","—",IFERROR(IF(INDEX(BackendChecklist!$H$5:$H$30,MATCH(W60,BackendChecklist!$A$5:$A$30,0))="نعم","جاهز للبدء",IF(V60="الآن (بنمط seam)","يبدأ بنمط seam — الربط ينتظر","ينتظر الباك اند")),"؟"))
A61: S1-06 | B61: WP-S1 | C61: =IFERROR(INDEX(WorkPackages!$C$5:$C$40,MATCH(B61,WorkPackages!$A$5:$A$40,0)),"") | D61: FR-T06 | E61: UI | F61: تفعيل زر الحجز في صفحة المعلم | G61: استبدال الزر المعطّل بـ Link إلى /book/$id (الزائر يُحوَّل لتسجيل الدخول). إخفاؤه لدور معلم/أدمن. حذف النص القديم «غير مفعّل بالباك اند». | H61: routes/teacher.$id.tsx | I61: — | J61: S1-05 | K61: P0 | L61: S | M61: قيد المراجعة | N61: Claude | O61: A-claude (منفّذ) | P61: =IFERROR(INDEX(WorkPackages!$H$5:$H$40,MATCH(B61,WorkPackages!$A$5:$A$40,0)),"") | S61: لا | T61: نفّذه Claude؛ الكود جاهز لكن خلف BOOKING_FLOW_ENABLED=false حتى يكتمل S1-05 (S1-03/Q-04)؛ الزر المعطّل الحالي باقٍ بنصه الصادق — بانتظار validate | U61: لا | V61: منفّذ — قيد المراجعة | X61: =IF(W61="","—",IFERROR(IF(INDEX(BackendChecklist!$H$5:$H$30,MATCH(W61,BackendChecklist!$A$5:$A$30,0))="نعم","جاهز للبدء",IF(V61="الآن (بنمط seam)","يبدأ بنمط seam — الربط ينتظر","ينتظر الباك اند")),"؟"))
A62: S1-07 | B62: WP-S1 | C62: =IFERROR(INDEX(WorkPackages!$C$5:$C$40,MATCH(B62,WorkPackages!$A$5:$A$40,0)),"") | D62: FR-T06 | E62: UI | F62: ملاحظة الطالب والتحقق | G62: studentNote اختياري؛ التاريخ بالمستقبل؛ المدة ضمن الحد. | H62: routes/_authenticated/book.$teacherId.tsx | I62: — | J62: S1-02 | K62: P1 | L62: S | M62: قيد المراجعة | N62: Claude | O62: A-claude (منفّذ) | P62: =IFERROR(INDEX(WorkPackages!$H$5:$H$40,MATCH(B62,WorkPackages!$A$5:$A$40,0)),"") | S62: لا | T62: نفّذه Claude؛ ملاحظة الطالب + تحقق (تاريخ مستقبلي، مدة 30..480، ضمن التوفّر، طول الملاحظة) — بانتظار validate | U62: لا | V62: منفّذ — قيد المراجعة | X62: =IF(W62="","—",IFERROR(IF(INDEX(BackendChecklist!$H$5:$H$30,MATCH(W62,BackendChecklist!$A$5:$A$30,0))="نعم","جاهز للبدء",IF(V62="الآن (بنمط seam)","يبدأ بنمط seam — الربط ينتظر","ينتظر الباك اند")),"؟"))
A63: S1-08 | B63: WP-S1 | C63: =IFERROR(INDEX(WorkPackages!$C$5:$C$40,MATCH(B63,WorkPackages!$A$5:$A$40,0)),"") | D63: FR-T06 | E63: Test | F63: اختبارات منطق الاختيار | G63: اختبارات نقية لتوليد الأوقات المتاحة وتقدير السعر. | H63: components/student/booking-slot-picker.test.ts | I63: — | J63: S1-02 | K63: P1 | L63: S | M63: قيد المراجعة | N63: Claude | O63: A-claude (منفّذ) | P63: =IFERROR(INDEX(WorkPackages!$H$5:$H$40,MATCH(B63,WorkPackages!$A$5:$A$40,0)),"") | S63: لا | T63: نفّذه Claude؛ booking-slot-picker.test.ts (27 فحصًا لمنطق booking-slots) — بانتظار validate | U63: لا | V63: منفّذ — قيد المراجعة | X63: =IF(W63="","—",IFERROR(IF(INDEX(BackendChecklist!$H$5:$H$30,MATCH(W63,BackendChecklist!$A$5:$A$30,0))="نعم","جاهز للبدء",IF(V63="الآن (بنمط seam)","يبدأ بنمط seam — الربط ينتظر","ينتظر الباك اند")),"؟"))
A64: S2-01 | B64: WP-S2 | C64: =IFERROR(INDEX(WorkPackages!$C$5:$C$40,MATCH(B64,WorkPackages!$A$5:$A$40,0)),"") | D64: FR-S14 | E64: UI | F64: صفحة تفاصيل الحجز | G64: Student/GetBooking: المعلم، التاريخ، الوقت، المدة، الوضع، السعر، الحالة (BookingStatusBadge)، سبب الرفض/الإلغاء إن وجد. | H64: routes/_authenticated/booking.$id.tsx | I64: Student/GetBooking | J64: WP-00 | K64: P0 | L64: M | M64: لم يبدأ | P64: =IFERROR(INDEX(WorkPackages!$H$5:$H$40,MATCH(B64,WorkPackages!$A$5:$A$40,0)),"") | S64: لا | U64: نعم | V64: بعد JSON | W64: NE-02 | X64: =IF(W64="","—",IFERROR(IF(INDEX(BackendChecklist!$H$5:$H$30,MATCH(W64,BackendChecklist!$A$5:$A$30,0))="نعم","جاهز للبدء",IF(V64="الآن (بنمط seam)","يبدأ بنمط seam — الربط ينتظر","ينتظر الباك اند")),"؟"))
A65: S2-02 | B65: WP-S2 | C65: =IFERROR(INDEX(WorkPackages!$C$5:$C$40,MATCH(B65,WorkPackages!$A$5:$A$40,0)),"") | D65: FR-S14 | E65: UI | F65: منطقة الإجراءات حسب الأهلية | G65: دمج: BookingPaymentCard (WP-W1) + CancelBookingDialog + RescheduleDialog (WP-S3) + RateBookingDialog (WP-S4) بحسب booking-rules.ts. الاستيراد من Stubs. | H65: routes/_authenticated/booking.$id.tsx | I65: — | J65: S2-01 | K65: P0 | L65: S | M65: لم يبدأ | P65: =IFERROR(INDEX(WorkPackages!$H$5:$H$40,MATCH(B65,WorkPackages!$A$5:$A$40,0)),"") | S65: لا | U65: نعم | V65: بعد JSON | W65: NE-02 | X65: =IF(W65="","—",IFERROR(IF(INDEX(BackendChecklist!$H$5:$H$30,MATCH(W65,BackendChecklist!$A$5:$A$30,0))="نعم","جاهز للبدء",IF(V65="الآن (بنمط seam)","يبدأ بنمط seam — الربط ينتظر","ينتظر الباك اند")),"؟"))
A66: S2-03 | B66: WP-S2 | C66: =IFERROR(INDEX(WorkPackages!$C$5:$C$40,MATCH(B66,WorkPackages!$A$5:$A$40,0)),"") | D66: FR-S14 | E66: UI | F66: نافذة إلغاء الحجز | G66: سبب اختياري + تأكيد → Student/CancelBooking {bookingId, reason}. عرض رسالة سياسة الإلغاء من الباك اند عند الرفض. بعد النجاح: الحالة Cancelled وتبقى بالسجل. | H66: components/student/cancel-booking-dialog.tsx | I66: Student/CancelBooking | J66: S2-01 | K66: P0 | L66: M | M66: قيد المراجعة | N66: Claude | O66: A-claude (منفّذ) | P66: =IFERROR(INDEX(WorkPackages!$H$5:$H$40,MATCH(B66,WorkPackages!$A$5:$A$40,0)),"") | S66: لا | T66: نفّذه Claude؛ cancel-booking-dialog.tsx (Student/CancelBooking؛ رسالة السياسة من الباك اند) — بانتظار validate | U66: لا | V66: منفّذ — قيد المراجعة | X66: =IF(W66="","—",IFERROR(IF(INDEX(BackendChecklist!$H$5:$H$30,MATCH(W66,BackendChecklist!$A$5:$A$30,0))="نعم","جاهز للبدء",IF(V66="الآن (بنمط seam)","يبدأ بنمط seam — الربط ينتظر","ينتظر الباك اند")),"؟"))
A67: S2-04 | B67: WP-S2 | C67: =IFERROR(INDEX(WorkPackages!$C$5:$C$40,MATCH(B67,WorkPackages!$A$5:$A$40,0)),"") | D67: FR-S14 | E67: UI | F67: لوحتا الحجوزات المؤكدة والطلبات المعلقة | G67: استخراجهما من my-courses (Stubs من WP-00) + رابط لكل صف إلى /booking/$id + عرض المرفوض/الملغى كسجل (Student Access Rules). | H67: components/student/my-courses/confirmed-bookings-panel.tsx, components/student/my-courses/pending-requests-panel.tsx | I67: Student/MyBookings, MyRequests | J67: WP-00 | K67: P1 | L67: M | M67: قيد المراجعة | N67: Claude | O67: A-claude (منفّذ) | P67: =IFERROR(INDEX(WorkPackages!$H$5:$H$40,MATCH(B67,WorkPackages!$A$5:$A$40,0)),"") | S67: لا | T67: نفّذه Claude؛ لوحتان بروابط /booking/$id أو /lesson/$id + سجل مرفوض/ملغى (يستبعد المكرر)؛ ملف جديد my-courses/schedule-row.tsx — بانتظار validate | U67: لا | V67: منفّذ — قيد المراجعة | X67: =IF(W67="","—",IFERROR(IF(INDEX(BackendChecklist!$H$5:$H$30,MATCH(W67,BackendChecklist!$A$5:$A$30,0))="نعم","جاهز للبدء",IF(V67="الآن (بنمط seam)","يبدأ بنمط seam — الربط ينتظر","ينتظر الباك اند")),"؟"))
A68: S2-05 | B68: WP-S2 | C68: =IFERROR(INDEX(WorkPackages!$C$5:$C$40,MATCH(B68,WorkPackages!$A$5:$A$40,0)),"") | D68: FR-S14 | E68: Test | F68: اختبارات + حالات الخطأ | G68: 403/404 على حجز لا يخص الطالب → رسالة وصول مرفوض؛ اختبار نقي لأي منطق جديد. | H68: routes/_authenticated/booking.$id.tsx | I68: — | J68: S2-01 | K68: P1 | L68: S | M68: لم يبدأ | P68: =IFERROR(INDEX(WorkPackages!$H$5:$H$40,MATCH(B68,WorkPackages!$A$5:$A$40,0)),"") | S68: لا | U68: نعم | V68: بعد JSON | W68: NE-02 | X68: =IF(W68="","—",IFERROR(IF(INDEX(BackendChecklist!$H$5:$H$30,MATCH(W68,BackendChecklist!$A$5:$A$30,0))="نعم","جاهز للبدء",IF(V68="الآن (بنمط seam)","يبدأ بنمط seam — الربط ينتظر","ينتظر الباك اند")),"؟"))
A69: S3-01 | B69: WP-S3 | C69: =IFERROR(INDEX(WorkPackages!$C$5:$C$40,MATCH(B69,WorkPackages!$A$5:$A$40,0)),"") | D69: FR-S15 | E69: UI | F69: نافذة طلب إعادة الجدولة | G69: التاريخ المقترح + الوقت المقترح + ملاحظة → Student/RequestReschedule. تظهر فقط للحجز المؤهل. | H69: components/student/reschedule-dialog.tsx | I69: Student/RequestReschedule | J69: WP-00 | K69: P0 | L69: M | M69: قيد المراجعة | N69: Claude | O69: A-claude (منفّذ) | P69: =IFERROR(INDEX(WorkPackages!$H$5:$H$40,MATCH(B69,WorkPackages!$A$5:$A$40,0)),"") | S69: لا | T69: نفّذه Claude؛ reschedule-dialog.tsx (Student/RequestReschedule) — بانتظار validate | U69: لا | V69: منفّذ — قيد المراجعة | X69: =IF(W69="","—",IFERROR(IF(INDEX(BackendChecklist!$H$5:$H$30,MATCH(W69,BackendChecklist!$A$5:$A$30,0))="نعم","جاهز للبدء",IF(V69="الآن (بنمط seam)","يبدأ بنمط seam — الربط ينتظر","ينتظر الباك اند")),"؟"))
A70: S3-02 | B70: WP-S3 | C70: =IFERROR(INDEX(WorkPackages!$C$5:$C$40,MATCH(B70,WorkPackages!$A$5:$A$40,0)),"") | D70: FR-S15 | E70: UI | F70: لوحة طلبات إعادة الجدولة | G70: Student/MyRescheduleRequests مع شارة حالة (أسماء الحالات من Q-05) لتتبّع الطلب. | H70: components/student/my-courses/reschedule-requests-panel.tsx | I70: Student/MyRescheduleRequests | J70: WP-00 | K70: P0 | L70: M | M70: لم يبدأ | P70: =IFERROR(INDEX(WorkPackages!$H$5:$H$40,MATCH(B70,WorkPackages!$A$5:$A$40,0)),"") | S70: لا | U70: نعم | V70: بعد JSON | W70: NE-04 | X70: =IF(W70="","—",IFERROR(IF(INDEX(BackendChecklist!$H$5:$H$30,MATCH(W70,BackendChecklist!$A$5:$A$30,0))="نعم","جاهز للبدء",IF(V70="الآن (بنمط seam)","يبدأ بنمط seam — الربط ينتظر","ينتظر الباك اند")),"؟"))
A71: S3-03 | B71: WP-S3 | C71: =IFERROR(INDEX(WorkPackages!$C$5:$C$40,MATCH(B71,WorkPackages!$A$5:$A$40,0)),"") | D71: FR-S15 | E71: UI | F71: أخطاء التعارض/عدم التوفّر | G71: عرض رسالة الباك اند ومنع الإرسال وطلب وقت آخر (Exception Flow). | H71: components/student/reschedule-dialog.tsx | I71: — | J71: S3-01 | K71: P0 | L71: S | M71: قيد المراجعة | N71: Claude | O71: A-claude (منفّذ) | P71: =IFERROR(INDEX(WorkPackages!$H$5:$H$40,MATCH(B71,WorkPackages!$A$5:$A$40,0)),"") | S71: لا | T71: نفّذه Claude؛ أخطاء التعارض/عدم التوفّر من الباك اند تظهر داخل النافذة وتبقى مفتوحة — بانتظار validate | U71: لا | V71: منفّذ — قيد المراجعة | X71: =IF(W71="","—",IFERROR(IF(INDEX(BackendChecklist!$H$5:$H$30,MATCH(W71,BackendChecklist!$A$5:$A$30,0))="نعم","جاهز للبدء",IF(V71="الآن (بنمط seam)","يبدأ بنمط seam — الربط ينتظر","ينتظر الباك اند")),"؟"))
A72: S3-04 | B72: WP-S3 | C72: =IFERROR(INDEX(WorkPackages!$C$5:$C$40,MATCH(B72,WorkPackages!$A$5:$A$40,0)),"") | D72: FR-S15 | E72: Test | F72: اختبارات التحقق | G72: التاريخ بالمستقبل + الوقت صالح. | H72: components/student/reschedule-dialog.test.ts | I72: — | J72: S3-01 | K72: P1 | L72: S | M72: قيد المراجعة | N72: Claude | O72: A-claude (منفّذ) | P72: =IFERROR(INDEX(WorkPackages!$H$5:$H$40,MATCH(B72,WorkPackages!$A$5:$A$40,0)),"") | S72: لا | T72: نفّذه Claude؛ reschedule-dialog.test.ts + lib/reschedule-validation.ts — بانتظار validate | U72: لا | V72: منفّذ — قيد المراجعة | X72: =IF(W72="","—",IFERROR(IF(INDEX(BackendChecklist!$H$5:$H$30,MATCH(W72,BackendChecklist!$A$5:$A$30,0))="نعم","جاهز للبدء",IF(V72="الآن (بنمط seam)","يبدأ بنمط seam — الربط ينتظر","ينتظر الباك اند")),"؟"))
A73: S4-01 | B73: WP-S4 | C73: =IFERROR(INDEX(WorkPackages!$C$5:$C$40,MATCH(B73,WorkPackages!$A$5:$A$40,0)),"") | D73: FR-T11 | E73: UI | F73: نافذة التقييم | G73: StarRating 1..5 + مراجعة اختيارية → Booking/Rate {bookingId, ratingValue, review}. | H73: components/student/rate-booking-dialog.tsx | I73: Booking/Rate | J73: WP-00 | K73: P0 | L73: M | M73: قيد المراجعة | N73: Claude | O73: A-claude (منفّذ) | P73: =IFERROR(INDEX(WorkPackages!$H$5:$H$40,MATCH(B73,WorkPackages!$A$5:$A$40,0)),"") | S73: لا | T73: نفّذه Claude؛ rate-booking-dialog.tsx (Booking/Rate)؛ S4-02/S4-03 (إخفاء الزر + teacherId) مؤجَّلتان لـJ-02 — بانتظار validate | U73: لا | V73: منفّذ — قيد المراجعة | X73: =IF(W73="","—",IFERROR(IF(INDEX(BackendChecklist!$H$5:$H$30,MATCH(W73,BackendChecklist!$A$5:$A$30,0))="نعم","جاهز للبدء",IF(V73="الآن (بنمط seam)","يبدأ بنمط seam — الربط ينتظر","ينتظر الباك اند")),"؟"))
A74: S4-02 | B74: WP-S4 | C74: =IFERROR(INDEX(WorkPackages!$C$5:$C$40,MATCH(B74,WorkPackages!$A$5:$A$40,0)),"") | D74: FR-T11 | E74: UI | F74: منع التقييم المكرر/غير المؤهل | G74: إخفاء الزر إن أمكن (حسب حقول GetBooking، Q-10) وإلا عرض رسالة الباك اند. | H74: components/student/rate-booking-dialog.tsx | I74: — | J74: S4-01 | K74: P0 | L74: S | M74: لم يبدأ | O74: مرشّح للبدء الآن | P74: =IFERROR(INDEX(WorkPackages!$H$5:$H$40,MATCH(B74,WorkPackages!$A$5:$A$40,0)),"") | S74: لا | U74: نعم | V74: بعد JSON | W74: NE-02 | X74: =IF(W74="","—",IFERROR(IF(INDEX(BackendChecklist!$H$5:$H$30,MATCH(W74,BackendChecklist!$A$5:$A$30,0))="نعم","جاهز للبدء",IF(V74="الآن (بنمط seam)","يبدأ بنمط seam — الربط ينتظر","ينتظر الباك اند")),"؟"))
A75: S4-03 | B75: WP-S4 | C75: =IFERROR(INDEX(WorkPackages!$C$5:$C$40,MATCH(B75,WorkPackages!$A$5:$A$40,0)),"") | D75: FR-T11 | E75: UI | F75: تحديث الكاشات بعد التقييم | G75: invalidate: ["student-booking", id], ["backend-teacher-profile", teacherId]. | H75: components/student/rate-booking-dialog.tsx | I75: — | J75: S4-01 | K75: P1 | L75: S | M75: لم يبدأ | O75: مرشّح للبدء الآن | P75: =IFERROR(INDEX(WorkPackages!$H$5:$H$40,MATCH(B75,WorkPackages!$A$5:$A$40,0)),"") | S75: لا | U75: نعم | V75: بعد JSON | W75: NE-02 | X75: =IF(W75="","—",IFERROR(IF(INDEX(BackendChecklist!$H$5:$H$30,MATCH(W75,BackendChecklist!$A$5:$A$30,0))="نعم","جاهز للبدء",IF(V75="الآن (بنمط seam)","يبدأ بنمط seam — الربط ينتظر","ينتظر الباك اند")),"؟"))
A76: S4-04 | B76: WP-S4 | C76: =IFERROR(INDEX(WorkPackages!$C$5:$C$40,MATCH(B76,WorkPackages!$A$5:$A$40,0)),"") | D76: FR-T11 | E76: Test | F76: اختبارات | G76: حدود النجوم ومنطق الأهلية. | H76: components/student/rate-booking-dialog.test.ts | I76: — | J76: S4-01 | K76: P1 | L76: S | M76: قيد المراجعة | N76: Claude | O76: A-claude (منفّذ) | P76: =IFERROR(INDEX(WorkPackages!$H$5:$H$40,MATCH(B76,WorkPackages!$A$5:$A$40,0)),"") | S76: لا | T76: نفّذه Claude؛ rate-booking-dialog.test.ts + lib/rating.ts (ملف جديد) — بانتظار validate | U76: لا | V76: منفّذ — قيد المراجعة | X76: =IF(W76="","—",IFERROR(IF(INDEX(BackendChecklist!$H$5:$H$30,MATCH(W76,BackendChecklist!$A$5:$A$30,0))="نعم","جاهز للبدء",IF(V76="الآن (بنمط seam)","يبدأ بنمط seam — الربط ينتظر","ينتظر الباك اند")),"؟"))
A77: S5-01 | B77: WP-S5 | C77: =IFERROR(INDEX(WorkPackages!$C$5:$C$40,MATCH(B77,WorkPackages!$A$5:$A$40,0)),"") | D77: FR-S06 | E77: UI | F77: تفاصيل درس حضوري | G77: رقم الدرس، الموضوع، التاريخ، اليوم، وقت البدء، المدة، المعلم، الكورس/المجموعة، القاعة أو «الموقع غير متوفر». | H77: routes/_authenticated/lesson.$id.tsx | I77: Student/GetLesson | J77: WP-00 | K77: P0 | L77: M | M77: لم يبدأ | P77: =IFERROR(INDEX(WorkPackages!$H$5:$H$40,MATCH(B77,WorkPackages!$A$5:$A$40,0)),"") | S77: لا | U77: نعم | V77: بعد JSON | W77: NE-05 | X77: =IF(W77="","—",IFERROR(IF(INDEX(BackendChecklist!$H$5:$H$30,MATCH(W77,BackendChecklist!$A$5:$A$30,0))="نعم","جاهز للبدء",IF(V77="الآن (بنمط seam)","يبدأ بنمط seam — الربط ينتظر","ينتظر الباك اند")),"؟"))
A78: S5-02 | B78: WP-S5 | C78: =IFERROR(INDEX(WorkPackages!$C$5:$C$40,MATCH(B78,WorkPackages!$A$5:$A$40,0)),"") | D78: FR-S07 | E78: UI | F78: تفاصيل درس أونلاين | G78: المنصة + رابط الاجتماع. زر «انضمام» فقط إن canJoin وكان الرابط http/https صالحًا (rel=noopener noreferrer)؛ وإلا تفاصيل بلا زر. | H78: routes/_authenticated/lesson.$id.tsx | I78: Student/GetLesson | J78: S5-01 | K78: P0 | L78: M | M78: لم يبدأ | P78: =IFERROR(INDEX(WorkPackages!$H$5:$H$40,MATCH(B78,WorkPackages!$A$5:$A$40,0)),"") | S78: لا | U78: نعم | V78: بعد JSON | W78: NE-05 | X78: =IF(W78="","—",IFERROR(IF(INDEX(BackendChecklist!$H$5:$H$30,MATCH(W78,BackendChecklist!$A$5:$A$30,0))="نعم","جاهز للبدء",IF(V78="الآن (بنمط seam)","يبدأ بنمط seam — الربط ينتظر","ينتظر الباك اند")),"؟"))
A79: S5-03 | B79: WP-S5 | C79: =IFERROR(INDEX(WorkPackages!$C$5:$C$40,MATCH(B79,WorkPackages!$A$5:$A$40,0)),"") | D79: FR-S06 | E79: UI | F79: معالجة الوصول المرفوض | G79: 403/404 → رسالة «غير مصرّح لك بهذا الدرس». | H79: routes/_authenticated/lesson.$id.tsx | I79: — | J79: S5-01 | K79: P0 | L79: S | M79: لم يبدأ | P79: =IFERROR(INDEX(WorkPackages!$H$5:$H$40,MATCH(B79,WorkPackages!$A$5:$A$40,0)),"") | S79: لا | U79: نعم | V79: بعد JSON | W79: NE-05 | X79: =IF(W79="","—",IFERROR(IF(INDEX(BackendChecklist!$H$5:$H$30,MATCH(W79,BackendChecklist!$A$5:$A$30,0))="نعم","جاهز للبدء",IF(V79="الآن (بنمط seam)","يبدأ بنمط seam — الربط ينتظر","ينتظر الباك اند")),"؟"))
A80: S5-04 | B80: WP-S5 | C80: =IFERROR(INDEX(WorkPackages!$C$5:$C$40,MATCH(B80,WorkPackages!$A$5:$A$40,0)),"") | D80: FR-S06 | E80: UI | F80: تحسين صفحة الجدول | G80: أعمدة: النوع (حضوري/أونلاين)، القاعة أو المنصة، اليوم، زر انضمام؛ صف الدرس يربط إلى /lesson/$id وصف الحجز إلى /booking/$id. | H80: routes/_authenticated/schedule.tsx | I80: Student/Schedule | J80: S5-01 | K80: P0 | L80: M | M80: قيد المراجعة | N80: Claude | O80: A-claude (منفّذ) | P80: =IFERROR(INDEX(WorkPackages!$H$5:$H$40,MATCH(B80,WorkPackages!$A$5:$A$40,0)),"") | S80: لا | T80: نفّذه Claude؛ schedule.tsx: أعمدة النوع/اليوم/القاعة-المنصة + زر انضمام آمن + روابط التفاصيل — بانتظار validate | U80: لا | V80: منفّذ — قيد المراجعة | X80: =IF(W80="","—",IFERROR(IF(INDEX(BackendChecklist!$H$5:$H$30,MATCH(W80,BackendChecklist!$A$5:$A$30,0))="نعم","جاهز للبدء",IF(V80="الآن (بنمط seam)","يبدأ بنمط seam — الربط ينتظر","ينتظر الباك اند")),"؟"))
A81: S5-05 | B81: WP-S5 | C81: =IFERROR(INDEX(WorkPackages!$C$5:$C$40,MATCH(B81,WorkPackages!$A$5:$A$40,0)),"") | D81: FR-S07 | E81: UI | F81: فلاتر الجدول (اختياري) | G81: المدى الزمني/الكورس/المعلم/الوضع عبر filter الموجود في getStudentSchedule. | H81: routes/_authenticated/schedule.tsx | I81: Student/Schedule | J81: S5-04 | K81: P2 | L81: S | M81: قيد المراجعة | N81: Claude | O81: A-claude (منفّذ) | P81: =IFERROR(INDEX(WorkPackages!$H$5:$H$40,MATCH(B81,WorkPackages!$A$5:$A$40,0)),"") | S81: لا | T81: نفّذه Claude؛ فلاتر مدى زمني + نوع الحصة (placeholderData يحفظ النتائج) — بانتظار validate | U81: لا | V81: منفّذ — قيد المراجعة | X81: =IF(W81="","—",IFERROR(IF(INDEX(BackendChecklist!$H$5:$H$30,MATCH(W81,BackendChecklist!$A$5:$A$30,0))="نعم","جاهز للبدء",IF(V81="الآن (بنمط seam)","يبدأ بنمط seam — الربط ينتظر","ينتظر الباك اند")),"؟"))
A82: S5-06 | B82: WP-S5 | C82: =IFERROR(INDEX(WorkPackages!$C$5:$C$40,MATCH(B82,WorkPackages!$A$5:$A$40,0)),"") | D82: FR-S07 | E82: Test | F82: اختبارات الانضمام والتحقق من الرابط | G82: حالات canJoin و isHttpUrl. | H82: test-units/lesson.$id.test.ts | I82: — | J82: S5-02 | K82: P1 | L82: S | M82: قيد المراجعة | N82: Claude | O82: A-claude (منفّذ) | P82: =IFERROR(INDEX(WorkPackages!$H$5:$H$40,MATCH(B82,WorkPackages!$A$5:$A$40,0)),"") | S82: لا | T82: نفّذه Claude؛ src/test-units/lesson.$id.test.ts + lib/schedule-join.ts (joinHref/locationLabel/detailTarget) — بانتظار validate | U82: لا | V82: منفّذ — قيد المراجعة | X82: =IF(W82="","—",IFERROR(IF(INDEX(BackendChecklist!$H$5:$H$30,MATCH(W82,BackendChecklist!$A$5:$A$30,0))="نعم","جاهز للبدء",IF(V82="الآن (بنمط seam)","يبدأ بنمط seam — الربط ينتظر","ينتظر الباك اند")),"؟"))
A83: S6-01 | B83: WP-S6 | C83: =IFERROR(INDEX(WorkPackages!$C$5:$C$40,MATCH(B83,WorkPackages!$A$5:$A$40,0)),"") | D83: FR-S08 | E83: UI | F83: صفحة تفاصيل الكورس المسجَّل | G83: Student/GetCourse: معلومات الكورس + المجموعة + جدول الدروس (رقم، موضوع، تاريخ، يوم، وقت، مدة، قاعة/رابط) بقراءة فقط. | H83: routes/_authenticated/enrolled-course.$id.tsx | I83: Student/GetCourse | J83: WP-00 | K83: P0 | L83: M | M83: لم يبدأ | P83: =IFERROR(INDEX(WorkPackages!$H$5:$H$40,MATCH(B83,WorkPackages!$A$5:$A$40,0)),"") | S83: لا | U83: نعم | V83: بعد JSON | W83: NE-06 | X83: =IF(W83="","—",IFERROR(IF(INDEX(BackendChecklist!$H$5:$H$30,MATCH(W83,BackendChecklist!$A$5:$A$30,0))="نعم","جاهز للبدء",IF(V83="الآن (بنمط seam)","يبدأ بنمط seam — الربط ينتظر","ينتظر الباك اند")),"؟"))
A84: S6-02 | B84: WP-S6 | C84: =IFERROR(INDEX(WorkPackages!$C$5:$C$40,MATCH(B84,WorkPackages!$A$5:$A$40,0)),"") | D84: FR-S08 | E84: UI | F84: لوحة «كورساتي المسجّلة» داخل كورساتي | G84: من activeCourses (getStudentDashboard) أو endpoint أدق حسب Q-05؛ رابط لكل كورس. | H84: components/student/my-courses/enrolled-courses-panel.tsx | I84: Student/Dashboard | J84: WP-00 | K84: P0 | L84: S | M84: قيد المراجعة | N84: Claude | O84: A-claude (منفّذ) | P84: =IFERROR(INDEX(WorkPackages!$H$5:$H$40,MATCH(B84,WorkPackages!$A$5:$A$40,0)),"") | S84: لا | T84: نفّذه Claude؛ enrolled-courses-panel.tsx من activeCourses (رابط /enrolled-course/$id) — بانتظار validate | U84: لا | V84: منفّذ — قيد المراجعة | X84: =IF(W84="","—",IFERROR(IF(INDEX(BackendChecklist!$H$5:$H$30,MATCH(W84,BackendChecklist!$A$5:$A$30,0))="نعم","جاهز للبدء",IF(V84="الآن (بنمط seam)","يبدأ بنمط seam — الربط ينتظر","ينتظر الباك اند")),"؟"))
A85: S6-03 | B85: WP-S6 | C85: =IFERROR(INDEX(WorkPackages!$C$5:$C$40,MATCH(B85,WorkPackages!$A$5:$A$40,0)),"") | D85: FR-S08 | E85: UI | F85: حالات فارغة/غير مسجَّل | G85: كورس بلا دروس → معلومات + رسالة فراغ؛ غير مسجَّل → وصول مرفوض. | H85: routes/_authenticated/enrolled-course.$id.tsx | I85: — | J85: S6-01 | K85: P0 | L85: S | M85: لم يبدأ | P85: =IFERROR(INDEX(WorkPackages!$H$5:$H$40,MATCH(B85,WorkPackages!$A$5:$A$40,0)),"") | S85: لا | U85: نعم | V85: بعد JSON | W85: NE-06 | X85: =IF(W85="","—",IFERROR(IF(INDEX(BackendChecklist!$H$5:$H$30,MATCH(W85,BackendChecklist!$A$5:$A$30,0))="نعم","جاهز للبدء",IF(V85="الآن (بنمط seam)","يبدأ بنمط seam — الربط ينتظر","ينتظر الباك اند")),"؟"))
A86: S6-04 | B86: WP-S6 | C86: =IFERROR(INDEX(WorkPackages!$C$5:$C$40,MATCH(B86,WorkPackages!$A$5:$A$40,0)),"") | D86: FR-S08 | E86: Test | F86: اختبارات | G86: منطق ترتيب الدروس/تجميعها. | H86: test-units/enrolled-course.$id.test.ts | I86: — | J86: S6-01 | K86: P1 | L86: S | M86: لم يبدأ | P86: =IFERROR(INDEX(WorkPackages!$H$5:$H$40,MATCH(B86,WorkPackages!$A$5:$A$40,0)),"") | S86: لا | U86: نعم | V86: بعد JSON | W86: NE-06 | X86: =IF(W86="","—",IFERROR(IF(INDEX(BackendChecklist!$H$5:$H$30,MATCH(W86,BackendChecklist!$A$5:$A$30,0))="نعم","جاهز للبدء",IF(V86="الآن (بنمط seam)","يبدأ بنمط seam — الربط ينتظر","ينتظر الباك اند")),"؟"))
A87: S7-01 | B87: WP-S7 | C87: =IFERROR(INDEX(WorkPackages!$C$5:$C$40,MATCH(B87,WorkPackages!$A$5:$A$40,0)),"") | D87: FR-S09 | E87: UI | F87: سجل الحضور | G87: جدول: الدرس/الكورس، التاريخ، الحالة (حاضر/غائب/متأخر/معذور) بشارات ملوّنة. | H87: routes/_authenticated/attendance.tsx | I87: Student/Attendance | J87: WP-00 | K87: P0 | L87: M | M87: لم يبدأ | P87: =IFERROR(INDEX(WorkPackages!$H$5:$H$40,MATCH(B87,WorkPackages!$A$5:$A$40,0)),"") | S87: لا | U87: نعم | V87: بعد JSON | W87: NE-07 | X87: =IF(W87="","—",IFERROR(IF(INDEX(BackendChecklist!$H$5:$H$30,MATCH(W87,BackendChecklist!$A$5:$A$30,0))="نعم","جاهز للبدء",IF(V87="الآن (بنمط seam)","يبدأ بنمط seam — الربط ينتظر","ينتظر الباك اند")),"؟"))
A88: S7-02 | B88: WP-S7 | C88: =IFERROR(INDEX(WorkPackages!$C$5:$C$40,MATCH(B88,WorkPackages!$A$5:$A$40,0)),"") | D88: FR-S09 | E88: UI | F88: نسبة الحضور | G88: تُعرض فقط عند توفر سجلات كافية؛ المصدر المفضّل ما يرجعه الباك اند (Q-05) أو Student/Progress. لا تحسب رقمًا مضللًا. | H88: routes/_authenticated/attendance.tsx | I88: Student/Attendance, Progress | J88: S7-01 | K88: P0 | L88: S | M88: قيد المراجعة | N88: Claude | O88: A-claude (منفّذ) | P88: =IFERROR(INDEX(WorkPackages!$H$5:$H$40,MATCH(B88,WorkPackages!$A$5:$A$40,0)),"") | S88: لا | T88: نفّذه Claude؛ attendance-rate-card.tsx يستخدم lib/progress.ts (WP-S9)؛ السجل التفصيلي S7-01 ينتظر JSON — بانتظار validate | U88: لا | V88: منفّذ — قيد المراجعة | X88: =IF(W88="","—",IFERROR(IF(INDEX(BackendChecklist!$H$5:$H$30,MATCH(W88,BackendChecklist!$A$5:$A$30,0))="نعم","جاهز للبدء",IF(V88="الآن (بنمط seam)","يبدأ بنمط seam — الربط ينتظر","ينتظر الباك اند")),"؟"))
A89: S7-03 | B89: WP-S7 | C89: =IFERROR(INDEX(WorkPackages!$C$5:$C$40,MATCH(B89,WorkPackages!$A$5:$A$40,0)),"") | D89: FR-S09 | E89: UI | F89: فلاتر التاريخ والكورس | G89: from/to/courseId. | H89: routes/_authenticated/attendance.tsx | I89: Student/Attendance | J89: S7-01 | K89: P1 | L89: S | M89: لم يبدأ | O89: مرشّح للبدء الآن | P89: =IFERROR(INDEX(WorkPackages!$H$5:$H$40,MATCH(B89,WorkPackages!$A$5:$A$40,0)),"") | S89: لا | U89: نعم | V89: بعد JSON | W89: NE-07 | X89: =IF(W89="","—",IFERROR(IF(INDEX(BackendChecklist!$H$5:$H$30,MATCH(W89,BackendChecklist!$A$5:$A$30,0))="نعم","جاهز للبدء",IF(V89="الآن (بنمط seam)","يبدأ بنمط seam — الربط ينتظر","ينتظر الباك اند")),"؟"))
A90: S7-04 | B90: WP-S7 | C90: =IFERROR(INDEX(WorkPackages!$C$5:$C$40,MATCH(B90,WorkPackages!$A$5:$A$40,0)),"") | D90: FR-S09 | E90: UI | F90: حالات فارغة/خطأ | G90: رسالة فراغ مناسبة + ErrorState مع إعادة المحاولة. | H90: routes/_authenticated/attendance.tsx | I90: — | J90: S7-01 | K90: P0 | L90: S | M90: لم يبدأ | O90: مرشّح للبدء الآن | P90: =IFERROR(INDEX(WorkPackages!$H$5:$H$40,MATCH(B90,WorkPackages!$A$5:$A$40,0)),"") | S90: لا | U90: نعم | V90: بعد JSON | W90: NE-07 | X90: =IF(W90="","—",IFERROR(IF(INDEX(BackendChecklist!$H$5:$H$30,MATCH(W90,BackendChecklist!$A$5:$A$30,0))="نعم","جاهز للبدء",IF(V90="الآن (بنمط seam)","يبدأ بنمط seam — الربط ينتظر","ينتظر الباك اند")),"؟"))
A91: S7-05 | B91: WP-S7 | C91: =IFERROR(INDEX(WorkPackages!$C$5:$C$40,MATCH(B91,WorkPackages!$A$5:$A$40,0)),"") | D91: FR-S09 | E91: Test | F91: اختبارات | G91: تسميات الحالات وتجميع النسبة إن حُسبت محليًا. | H91: test-units/attendance.test.ts | I91: — | J91: S7-01 | K91: P1 | L91: S | M91: لم يبدأ | P91: =IFERROR(INDEX(WorkPackages!$H$5:$H$40,MATCH(B91,WorkPackages!$A$5:$A$40,0)),"") | S91: لا | U91: نعم | V91: بعد JSON | W91: NE-07 | X91: =IF(W91="","—",IFERROR(IF(INDEX(BackendChecklist!$H$5:$H$30,MATCH(W91,BackendChecklist!$A$5:$A$30,0))="نعم","جاهز للبدء",IF(V91="الآن (بنمط seam)","يبدأ بنمط seam — الربط ينتظر","ينتظر الباك اند")),"؟"))
A92: S8-01 | B92: WP-S8 | C92: =IFERROR(INDEX(WorkPackages!$C$5:$C$40,MATCH(B92,WorkPackages!$A$5:$A$40,0)),"") | D92: FR-S10 | E92: UI | F92: جدول نتائج الامتحانات | G92: العنوان، التاريخ، الدرجة، المجموع، النسبة المحسوبة، الملاحظات. | H92: routes/_authenticated/exam-results.tsx | I92: Student/ExamResults | J92: WP-00 | K92: P0 | L92: M | M92: لم يبدأ | P92: =IFERROR(INDEX(WorkPackages!$H$5:$H$40,MATCH(B92,WorkPackages!$A$5:$A$40,0)),"") | S92: لا | U92: نعم | V92: بعد JSON | W92: NE-08 | X92: =IF(W92="","—",IFERROR(IF(INDEX(BackendChecklist!$H$5:$H$30,MATCH(W92,BackendChecklist!$A$5:$A$30,0))="نعم","جاهز للبدء",IF(V92="الآن (بنمط seam)","يبدأ بنمط seam — الربط ينتظر","ينتظر الباك اند")),"؟"))
A93: S8-02 | B93: WP-S8 | C93: =IFERROR(INDEX(WorkPackages!$C$5:$C$40,MATCH(B93,WorkPackages!$A$5:$A$40,0)),"") | D93: FR-S10 | E93: UI | F93: فلتر الكورس | G93: courseId اختياري. | H93: routes/_authenticated/exam-results.tsx | I93: Student/ExamResults | J93: S8-01 | K93: P1 | L93: S | M93: لم يبدأ | O93: مرشّح للبدء الآن | P93: =IFERROR(INDEX(WorkPackages!$H$5:$H$40,MATCH(B93,WorkPackages!$A$5:$A$40,0)),"") | S93: لا | U93: نعم | V93: بعد JSON | W93: NE-08 | X93: =IF(W93="","—",IFERROR(IF(INDEX(BackendChecklist!$H$5:$H$30,MATCH(W93,BackendChecklist!$A$5:$A$30,0))="نعم","جاهز للبدء",IF(V93="الآن (بنمط seam)","يبدأ بنمط seam — الربط ينتظر","ينتظر الباك اند")),"؟"))
A94: S8-03 | B94: WP-S8 | C94: =IFERROR(INDEX(WorkPackages!$C$5:$C$40,MATCH(B94,WorkPackages!$A$5:$A$40,0)),"") | D94: FR-S10 | E94: UI | F94: حالات فارغة/خطأ | G94: «لا توجد نتائج امتحانات متاحة» + ErrorState. | H94: routes/_authenticated/exam-results.tsx | I94: — | J94: S8-01 | K94: P0 | L94: S | M94: لم يبدأ | O94: مرشّح للبدء الآن | P94: =IFERROR(INDEX(WorkPackages!$H$5:$H$40,MATCH(B94,WorkPackages!$A$5:$A$40,0)),"") | S94: لا | U94: نعم | V94: بعد JSON | W94: NE-08 | X94: =IF(W94="","—",IFERROR(IF(INDEX(BackendChecklist!$H$5:$H$30,MATCH(W94,BackendChecklist!$A$5:$A$30,0))="نعم","جاهز للبدء",IF(V94="الآن (بنمط seam)","يبدأ بنمط seam — الربط ينتظر","ينتظر الباك اند")),"؟"))
A95: S8-04 | B95: WP-S8 | C95: =IFERROR(INDEX(WorkPackages!$C$5:$C$40,MATCH(B95,WorkPackages!$A$5:$A$40,0)),"") | D95: FR-S10 | E95: Test | F95: اختبار حساب النسبة | G95: total=0 لا يقسم على صفر. | H95: test-units/exam-results.test.ts | I95: — | J95: S8-01 | K95: P1 | L95: S | M95: قيد المراجعة | N95: Claude | O95: A-claude (منفّذ) | P95: =IFERROR(INDEX(WorkPackages!$H$5:$H$40,MATCH(B95,WorkPackages!$A$5:$A$40,0)),"") | S95: لا | T95: نفّذه Claude؛ lib/exam-percent.ts + src/test-units/exam-results.test.ts — بانتظار validate | U95: لا | V95: منفّذ — قيد المراجعة | X95: =IF(W95="","—",IFERROR(IF(INDEX(BackendChecklist!$H$5:$H$30,MATCH(W95,BackendChecklist!$A$5:$A$30,0))="نعم","جاهز للبدء",IF(V95="الآن (بنمط seam)","يبدأ بنمط seam — الربط ينتظر","ينتظر الباك اند")),"؟"))
A96: S9-01 | B96: WP-S9 | C96: =IFERROR(INDEX(WorkPackages!$C$5:$C$40,MATCH(B96,WorkPackages!$A$5:$A$40,0)),"") | D96: FR-S11 | E96: UI | F96: مؤشرات التقدم | G96: Student/Progress: نسبة الحضور، متوسط الامتحانات، عدد الجلسات، عدد الامتحانات (StudentProgressDto معروف). | H96: routes/_authenticated/progress.tsx | I96: Student/Progress | J96: WP-00 | K96: P0 | L96: S | M96: قيد المراجعة | N96: المستخدم | O96: A-user (منفّذ) | P96: =IFERROR(INDEX(WorkPackages!$H$5:$H$40,MATCH(B96,WorkPackages!$A$5:$A$40,0)),"") | S96: لا | T96: نفّذه المستخدم؛ progress.tsx حلّ محل stub WP-00؛ النوع من الكود (يُتحقق بـJ-04) | U96: لا | V96: منفّذ — قيد المراجعة | X96: =IF(W96="","—",IFERROR(IF(INDEX(BackendChecklist!$H$5:$H$30,MATCH(W96,BackendChecklist!$A$5:$A$30,0))="نعم","جاهز للبدء",IF(V96="الآن (بنمط seam)","يبدأ بنمط seam — الربط ينتظر","ينتظر الباك اند")),"؟"))
A97: S9-02 | B97: WP-S9 | C97: =IFERROR(INDEX(WorkPackages!$C$5:$C$40,MATCH(B97,WorkPackages!$A$5:$A$40,0)),"") | D97: FR-S11 | E97: UI | F97: القيم غير المتاحة | G97: null → «—» وشرح (لا سجلات كافية) بدل 0%. | H97: routes/_authenticated/progress.tsx | I97: — | J97: S9-01 | K97: P0 | L97: S | M97: قيد المراجعة | N97: المستخدم | O97: A-user (منفّذ) | P97: =IFERROR(INDEX(WorkPackages!$H$5:$H$40,MATCH(B97,WorkPackages!$A$5:$A$40,0)),"") | S97: لا | T97: نفّذه المستخدم (wave1-half-claude-files.zip)؛ بانتظار validate | U97: لا | V97: منفّذ — قيد المراجعة | X97: =IF(W97="","—",IFERROR(IF(INDEX(BackendChecklist!$H$5:$H$30,MATCH(W97,BackendChecklist!$A$5:$A$30,0))="نعم","جاهز للبدء",IF(V97="الآن (بنمط seam)","يبدأ بنمط seam — الربط ينتظر","ينتظر الباك اند")),"؟"))
A98: S9-03 | B98: WP-S9 | C98: =IFERROR(INDEX(WorkPackages!$C$5:$C$40,MATCH(B98,WorkPackages!$A$5:$A$40,0)),"") | D98: FR-S11 | E98: UI | F98: شرائط/عدّادات التقدم | G98: استخدام Progress + StatGrid الموجودين في kit. | H98: routes/_authenticated/progress.tsx | I98: — | J98: S9-01 | K98: P1 | L98: S | M98: قيد المراجعة | N98: المستخدم | O98: A-user (منفّذ) | P98: =IFERROR(INDEX(WorkPackages!$H$5:$H$40,MATCH(B98,WorkPackages!$A$5:$A$40,0)),"") | S98: لا | T98: نفّذه المستخدم (wave1-half-claude-files.zip)؛ بانتظار validate | U98: لا | V98: منفّذ — قيد المراجعة | X98: =IF(W98="","—",IFERROR(IF(INDEX(BackendChecklist!$H$5:$H$30,MATCH(W98,BackendChecklist!$A$5:$A$30,0))="نعم","جاهز للبدء",IF(V98="الآن (بنمط seam)","يبدأ بنمط seam — الربط ينتظر","ينتظر الباك اند")),"؟"))
A99: S9-04 | B99: WP-S9 | C99: =IFERROR(INDEX(WorkPackages!$C$5:$C$40,MATCH(B99,WorkPackages!$A$5:$A$40,0)),"") | D99: FR-S11 | E99: UI | F99: حالات تحميل/خطأ | G99: ErrorState/LoadingState الموحدة. | H99: routes/_authenticated/progress.tsx | I99: — | J99: S9-01 | K99: P0 | L99: S | M99: قيد المراجعة | N99: المستخدم | O99: A-user (منفّذ) | P99: =IFERROR(INDEX(WorkPackages!$H$5:$H$40,MATCH(B99,WorkPackages!$A$5:$A$40,0)),"") | S99: لا | T99: نفّذه المستخدم (wave1-half-claude-files.zip)؛ بانتظار validate | U99: لا | V99: منفّذ — قيد المراجعة | X99: =IF(W99="","—",IFERROR(IF(INDEX(BackendChecklist!$H$5:$H$30,MATCH(W99,BackendChecklist!$A$5:$A$30,0))="نعم","جاهز للبدء",IF(V99="الآن (بنمط seam)","يبدأ بنمط seam — الربط ينتظر","ينتظر الباك اند")),"؟"))
A100: S9-05 | B100: WP-S9 | C100: =IFERROR(INDEX(WorkPackages!$C$5:$C$40,MATCH(B100,WorkPackages!$A$5:$A$40,0)),"") | D100: FR-S11 | E100: Test | F100: اختبارات | G100: تنسيق القيم الفارغة. | H100: test-units/progress.test.ts | I100: — | J100: S9-01 | K100: P1 | L100: S | M100: قيد المراجعة | N100: المستخدم | O100: A-user (منفّذ) | P100: =IFERROR(INDEX(WorkPackages!$H$5:$H$40,MATCH(B100,WorkPackages!$A$5:$A$40,0)),"") | S100: لا | T100: نفّذه المستخدم (wave1-half-claude-files.zip)؛ بانتظار validate | U100: لا | V100: منفّذ — قيد المراجعة | X100: =IF(W100="","—",IFERROR(IF(INDEX(BackendChecklist!$H$5:$H$30,MATCH(W100,BackendChecklist!$A$5:$A$30,0))="نعم","جاهز للبدء",IF(V100="الآن (بنمط seam)","يبدأ بنمط seam — الربط ينتظر","ينتظر الباك اند")),"؟"))
A101: P1-01 | B101: WP-P1 | C101: =IFERROR(INDEX(WorkPackages!$C$5:$C$40,MATCH(B101,WorkPackages!$A$5:$A$40,0)),"") | D101: FR-P11 | E101: UI | F101: عرض عدد الإشعارات غير المقروءة | G101: StatGrid في تقرير ولي الأمر: unreadNotificationsCount للابن النشط + إجمالي الأبناء (يُوثَّق بوضوح بالواجهة أن العدد مأخوذ من كل ابن، Q-11). صفر عند عدم الوجود. | H101: routes/_authenticated/parent.report.tsx | I101: Parent/MyChildren | J101: WP-00 | K101: P0 | L101: S | M101: قيد المراجعة | N101: المستخدم | O101: A-user (منفّذ) | P101: =IFERROR(INDEX(WorkPackages!$H$5:$H$40,MATCH(B101,WorkPackages!$A$5:$A$40,0)),"") | S101: لا | T101: نفّذه المستخدم (wp-p1-w2-files.zip)؛ بانتظار npm run validate محليًا | U101: لا | V101: منفّذ — قيد المراجعة | X101: =IF(W101="","—",IFERROR(IF(INDEX(BackendChecklist!$H$5:$H$30,MATCH(W101,BackendChecklist!$A$5:$A$30,0))="نعم","جاهز للبدء",IF(V101="الآن (بنمط seam)","يبدأ بنمط seam — الربط ينتظر","ينتظر الباك اند")),"؟"))
A102: P1-02 | B102: WP-P1 | C102: =IFERROR(INDEX(WorkPackages!$C$5:$C$40,MATCH(B102,WorkPackages!$A$5:$A$40,0)),"") | D102: FR-P11 | E102: UI | F102: فشل الجلب لا يكسر اللوحة | G102: Exception Flow: عرض اللوحة بدون العدد + تنبيه غير حاجب. | H102: routes/_authenticated/parent.report.tsx | I102: — | J102: P1-01 | K102: P1 | L102: S | M102: قيد المراجعة | N102: المستخدم | O102: A-user (منفّذ) | P102: =IFERROR(INDEX(WorkPackages!$H$5:$H$40,MATCH(B102,WorkPackages!$A$5:$A$40,0)),"") | S102: لا | T102: نفّذه المستخدم (wp-p1-w2-files.zip)؛ بانتظار npm run validate محليًا | U102: لا | V102: منفّذ — قيد المراجعة | X102: =IF(W102="","—",IFERROR(IF(INDEX(BackendChecklist!$H$5:$H$30,MATCH(W102,BackendChecklist!$A$5:$A$30,0))="نعم","جاهز للبدء",IF(V102="الآن (بنمط seam)","يبدأ بنمط seam — الربط ينتظر","ينتظر الباك اند")),"؟"))
A103: P1-03 | B103: WP-P1 | C103: =IFERROR(INDEX(WorkPackages!$C$5:$C$40,MATCH(B103,WorkPackages!$A$5:$A$40,0)),"") | D103: FR-P08 | E103: UI | F103: معالجة رفض الوصول (403) | G103: أخطاء ChildAttendance/ChildExamResults لابن غير مرتبط تظهر كـ«غير مصرّح»؛ اختيار الابن من getMyChildren فقط، بدون إدخال يدوي لـ studentId. | H103: routes/_authenticated/parent.report.tsx | I103: Parent/ChildAttendance, ChildExamResults | J103: P1-01 | K103: P0 | L103: S | M103: قيد المراجعة | N103: المستخدم | O103: A-user (منفّذ) | P103: =IFERROR(INDEX(WorkPackages!$H$5:$H$40,MATCH(B103,WorkPackages!$A$5:$A$40,0)),"") | S103: لا | T103: نفّذه المستخدم (wp-p1-w2-files.zip)؛ بانتظار npm run validate محليًا | U103: لا | V103: منفّذ — قيد المراجعة | X103: =IF(W103="","—",IFERROR(IF(INDEX(BackendChecklist!$H$5:$H$30,MATCH(W103,BackendChecklist!$A$5:$A$30,0))="نعم","جاهز للبدء",IF(V103="الآن (بنمط seam)","يبدأ بنمط seam — الربط ينتظر","ينتظر الباك اند")),"؟"))
A104: P1-04 | B104: WP-P1 | C104: =IFERROR(INDEX(WorkPackages!$C$5:$C$40,MATCH(B104,WorkPackages!$A$5:$A$40,0)),"") | D104: FR-P11 | E104: UI | F104: بانر «قراءة فقط» | G104: FR-P12: توضيح أن ولي الأمر لا يعدّل بيانات أكاديمية. | H104: routes/_authenticated/parent.report.tsx | I104: — | J104: P1-01 | K104: P2 | L104: S | M104: قيد المراجعة | N104: المستخدم | O104: A-user (منفّذ) | P104: =IFERROR(INDEX(WorkPackages!$H$5:$H$40,MATCH(B104,WorkPackages!$A$5:$A$40,0)),"") | S104: لا | T104: نفّذه المستخدم (wp-p1-w2-files.zip)؛ بانتظار npm run validate محليًا | U104: لا | V104: منفّذ — قيد المراجعة | X104: =IF(W104="","—",IFERROR(IF(INDEX(BackendChecklist!$H$5:$H$30,MATCH(W104,BackendChecklist!$A$5:$A$30,0))="نعم","جاهز للبدء",IF(V104="الآن (بنمط seam)","يبدأ بنمط seam — الربط ينتظر","ينتظر الباك اند")),"؟"))
A105: P1-05 | B105: WP-P1 | C105: =IFERROR(INDEX(WorkPackages!$C$5:$C$40,MATCH(B105,WorkPackages!$A$5:$A$40,0)),"") | D105: FR-P11 | E105: UI | F105: عمود حالة الحضور | G105: عرض status (حاضر/غائب/متأخر/معذور) بجدول الحضور (موجود بالـDTO وغير معروض). | H105: routes/_authenticated/parent.report.tsx | I105: Parent/ChildAttendance | J105: P1-01 | K105: P1 | L105: S | M105: قيد المراجعة | N105: المستخدم | O105: A-user (منفّذ) | P105: =IFERROR(INDEX(WorkPackages!$H$5:$H$40,MATCH(B105,WorkPackages!$A$5:$A$40,0)),"") | S105: لا | T105: نفّذه المستخدم (wp-p1-w2-files.zip)؛ بانتظار npm run validate محليًا | U105: لا | V105: منفّذ — قيد المراجعة | X105: =IF(W105="","—",IFERROR(IF(INDEX(BackendChecklist!$H$5:$H$30,MATCH(W105,BackendChecklist!$A$5:$A$30,0))="نعم","جاهز للبدء",IF(V105="الآن (بنمط seam)","يبدأ بنمط seam — الربط ينتظر","ينتظر الباك اند")),"؟"))
A106: P1-06 | B106: WP-P1 | C106: =IFERROR(INDEX(WorkPackages!$C$5:$C$40,MATCH(B106,WorkPackages!$A$5:$A$40,0)),"") | D106: FR-P11 | E106: UI | F106: عدد غير المقروء لكل ابن بصفحة الإعدادات | G106: إضافته للأبناء المرتبطين. | H106: routes/_authenticated/parent.settings.tsx | I106: Parent/MyChildren | J106: P1-01 | K106: P2 | L106: S | M106: قيد المراجعة | N106: المستخدم | O106: A-user (منفّذ) | P106: =IFERROR(INDEX(WorkPackages!$H$5:$H$40,MATCH(B106,WorkPackages!$A$5:$A$40,0)),"") | S106: لا | T106: نفّذه المستخدم (wp-p1-w2-files.zip)؛ بانتظار npm run validate محليًا | U106: لا | V106: منفّذ — قيد المراجعة | X106: =IF(W106="","—",IFERROR(IF(INDEX(BackendChecklist!$H$5:$H$30,MATCH(W106,BackendChecklist!$A$5:$A$30,0))="نعم","جاهز للبدء",IF(V106="الآن (بنمط seam)","يبدأ بنمط seam — الربط ينتظر","ينتظر الباك اند")),"؟"))
...

Sheet FR_Matrix
A1: مصفوفة المتطلبات (FR) والتتبّع
A2: الأساس = تقرير جاهزية الفرونت (30 FR) + 7 FRs داعمة من SRS. الحالة الحالية محسوبة من Tasks وUAT: «جاهز» تتطلب اكتمال كل المهام ونجاح كل بنود UAT.
A4: FR | B4: العنوان (EN) | C4: العنوان (AR) | D4: الوحدة (SRS) | E4: الدور | F4: أولوية SRS | G4: حالة التقرير (الأساس) | H4: تفاصيل التقرير | I4: ضمن الـ30؟ | J4: WPs | K4: مهام (كلي) | L4: مكتمل | M4: قيد التنفيذ | N4: UAT كلي | O4: UAT نجح | P4: UAT فشل | Q4: الحالة الحالية (محسوبة) | R4: ملاحظات
A5: FR-I02 | B5: Configure In-Person Student Group | C5: إعداد مجموعة طلاب حضورية | D5: Instructor Course & Lesson Mgmt | E5: معلم | F5: Must | G5: غير جاهز | H5: لا توجد واجهة للمعلم لإعداد مجموعة حضورية وجدولها | I5: نعم | J5: WP-T2 | K5: =COUNTIF(Tasks!$D$5:$D$300,A5) | L5: =COUNTIFS(Tasks!$D$5:$D$300,A5,Tasks!$M$5:$M$300,"مكتمل") | M5: =COUNTIFS(Tasks!$D$5:$D$300,A5,Tasks!$M$5:$M$300,"قيد التنفيذ")+COUNTIFS(Tasks!$D$5:$D$300,A5,Tasks!$M$5:$M$300,"قيد المراجعة") | N5: =COUNTIF(UAT!$B$5:$B$300,A5) | O5: =COUNTIFS(UAT!$B$5:$B$300,A5,UAT!$H$5:$H$300,"نجح") | P5: =COUNTIFS(UAT!$B$5:$B$300,A5,UAT!$H$5:$H$300,"فشل") | Q5: =IF(G5="جاهز","جاهز (أصلي)",IF(K5=0,"—",IF(AND(L5=K5,N5>0,O5=N5),"جاهز",IF(L5=K5,"مكتمل – بانتظار UAT",IF(L5+M5>0,"قيد التنفيذ","لم يبدأ")))))
A6: FR-I03 | B6: View In-Person Group Students | C6: عرض طلاب المجموعة | D6: Instructor Course & Lesson Mgmt | E6: معلم | F6: Must | G6: غير جاهز | H6: لا توجد صفحة تعرض طلاب المجموعة للمعلم | I6: نعم | J6: WP-T3 | K6: =COUNTIF(Tasks!$D$5:$D$300,A6) | L6: =COUNTIFS(Tasks!$D$5:$D$300,A6,Tasks!$M$5:$M$300,"مكتمل") | M6: =COUNTIFS(Tasks!$D$5:$D$300,A6,Tasks!$M$5:$M$300,"قيد التنفيذ")+COUNTIFS(Tasks!$D$5:$D$300,A6,Tasks!$M$5:$M$300,"قيد المراجعة") | N6: =COUNTIF(UAT!$B$5:$B$300,A6) | O6: =COUNTIFS(UAT!$B$5:$B$300,A6,UAT!$H$5:$H$300,"نجح") | P6: =COUNTIFS(UAT!$B$5:$B$300,A6,UAT!$H$5:$H$300,"فشل") | Q6: =IF(G6="جاهز","جاهز (أصلي)",IF(K6=0,"—",IF(AND(L6=K6,N6>0,O6=N6),"جاهز",IF(L6=K6,"مكتمل – بانتظار UAT",IF(L6+M6>0,"قيد التنفيذ","لم يبدأ")))))
A7: FR-I04 | B7: Create/Schedule In-Person Lessons | C7: إنشاء وجدولة دروس حضورية | D7: Instructor Course & Lesson Mgmt | E7: معلم | F7: Must | G7: غير جاهز | H7: lessons.ts يحتوي API فقط بدون واجهة إنشاء/جدولة | I7: نعم | J7: WP-T4 | K7: =COUNTIF(Tasks!$D$5:$D$300,A7) | L7: =COUNTIFS(Tasks!$D$5:$D$300,A7,Tasks!$M$5:$M$300,"مكتمل") | M7: =COUNTIFS(Tasks!$D$5:$D$300,A7,Tasks!$M$5:$M$300,"قيد التنفيذ")+COUNTIFS(Tasks!$D$5:$D$300,A7,Tasks!$M$5:$M$300,"قيد المراجعة") | N7: =COUNTIF(UAT!$B$5:$B$300,A7) | O7: =COUNTIFS(UAT!$B$5:$B$300,A7,UAT!$H$5:$H$300,"نجح") | P7: =COUNTIFS(UAT!$B$5:$B$300,A7,UAT!$H$5:$H$300,"فشل") | Q7: =IF(G7="جاهز","جاهز (أصلي)",IF(K7=0,"—",IF(AND(L7=K7,N7>0,O7=N7),"جاهز",IF(L7=K7,"مكتمل – بانتظار UAT",IF(L7+M7>0,"قيد التنفيذ","لم يبدأ")))))
A8: FR-I06 | B8: Configure Online Course Group | C8: إعداد مجموعة كورس أونلاين | D8: Instructor Course & Lesson Mgmt | E8: معلم | F8: Must | G8: غير جاهز | H8: لا توجد واجهة للمعلم لإعداد المجموعة الإلكترونية | I8: نعم | J8: WP-T2 | K8: =COUNTIF(Tasks!$D$5:$D$300,A8) | L8: =COUNTIFS(Tasks!$D$5:$D$300,A8,Tasks!$M$5:$M$300,"مكتمل") | M8: =COUNTIFS(Tasks!$D$5:$D$300,A8,Tasks!$M$5:$M$300,"قيد التنفيذ")+COUNTIFS(Tasks!$D$5:$D$300,A8,Tasks!$M$5:$M$300,"قيد المراجعة") | N8: =COUNTIF(UAT!$B$5:$B$300,A8) | O8: =COUNTIFS(UAT!$B$5:$B$300,A8,UAT!$H$5:$H$300,"نجح") | P8: =COUNTIFS(UAT!$B$5:$B$300,A8,UAT!$H$5:$H$300,"فشل") | Q8: =IF(G8="جاهز","جاهز (أصلي)",IF(K8=0,"—",IF(AND(L8=K8,N8>0,O8=N8),"جاهز",IF(L8=K8,"مكتمل – بانتظار UAT",IF(L8+M8>0,"قيد التنفيذ","لم يبدأ")))))
A9: FR-I08 | B9: Create/Schedule Online Lessons | C9: إنشاء وجدولة دروس أونلاين | D9: Instructor Course & Lesson Mgmt | E9: معلم | F9: Must | G9: غير جاهز | H9: API موجود في lessons.ts بدون واجهة للمعلم | I9: نعم | J9: WP-T4 | K9: =COUNTIF(Tasks!$D$5:$D$300,A9) | L9: =COUNTIFS(Tasks!$D$5:$D$300,A9,Tasks!$M$5:$M$300,"مكتمل") | M9: =COUNTIFS(Tasks!$D$5:$D$300,A9,Tasks!$M$5:$M$300,"قيد التنفيذ")+COUNTIFS(Tasks!$D$5:$D$300,A9,Tasks!$M$5:$M$300,"قيد المراجعة") | N9: =COUNTIF(UAT!$B$5:$B$300,A9) | O9: =COUNTIFS(UAT!$B$5:$B$300,A9,UAT!$H$5:$H$300,"نجح") | P9: =COUNTIFS(UAT!$B$5:$B$300,A9,UAT!$H$5:$H$300,"فشل") | Q9: =IF(G9="جاهز","جاهز (أصلي)",IF(K9=0,"—",IF(AND(L9=K9,N9>0,O9=N9),"جاهز",IF(L9=K9,"مكتمل – بانتظار UAT",IF(L9+M9>0,"قيد التنفيذ","لم يبدأ")))))
A10: FR-T06 | B10: Process Booking Payment | C10: معالجة دفع الحجز | D10: Teacher Discovery & Booking | E10: طالب/نظام | F10: Must | G10: غير جاهز | H10: لا توجد شاشة حجز؛ زر الحجز في صفحة المعلم معطّل | I10: نعم | J10: WP-S1, WP-T5 | K10: =COUNTIF(Tasks!$D$5:$D$300,A10) | L10: =COUNTIFS(Tasks!$D$5:$D$300,A10,Tasks!$M$5:$M$300,"مكتمل") | M10: =COUNTIFS(Tasks!$D$5:$D$300,A10,Tasks!$M$5:$M$300,"قيد التنفيذ")+COUNTIFS(Tasks!$D$5:$D$300,A10,Tasks!$M$5:$M$300,"قيد المراجعة") | N10: =COUNTIF(UAT!$B$5:$B$300,A10) | O10: =COUNTIFS(UAT!$B$5:$B$300,A10,UAT!$H$5:$H$300,"نجح") | P10: =COUNTIFS(UAT!$B$5:$B$300,A10,UAT!$H$5:$H$300,"فشل") | Q10: =IF(G10="جاهز","جاهز (أصلي)",IF(K10=0,"—",IF(AND(L10=K10,N10>0,O10=N10),"جاهز",IF(L10=K10,"مكتمل – بانتظار UAT",IF(L10+M10>0,"قيد التنفيذ","لم يبدأ")))))
A11: FR-T11 | B11: Rate Teacher After Completed Session | C11: تقييم المعلم بعد الجلسة | D11: Teacher Discovery & Booking | E11: طالب | F11: Should | G11: غير جاهز | H11: rateBooking() موجود API فقط بدون UI للتقييم | I11: نعم | J11: WP-S4 | K11: =COUNTIF(Tasks!$D$5:$D$300,A11) | L11: =COUNTIFS(Tasks!$D$5:$D$300,A11,Tasks!$M$5:$M$300,"مكتمل") | M11: =COUNTIFS(Tasks!$D$5:$D$300,A11,Tasks!$M$5:$M$300,"قيد التنفيذ")+COUNTIFS(Tasks!$D$5:$D$300,A11,Tasks!$M$5:$M$300,"قيد المراجعة") | N11: =COUNTIF(UAT!$B$5:$B$300,A11) | O11: =COUNTIFS(UAT!$B$5:$B$300,A11,UAT!$H$5:$H$300,"نجح") | P11: =COUNTIFS(UAT!$B$5:$B$300,A11,UAT!$H$5:$H$300,"فشل") | Q11: =IF(G11="جاهز","جاهز (أصلي)",IF(K11=0,"—",IF(AND(L11=K11,N11>0,O11=N11),"جاهز",IF(L11=K11,"مكتمل – بانتظار UAT",IF(L11+M11>0,"قيد التنفيذ","لم يبدأ")))))
A12: FR-W03a | B12: Deduct Enrollment Fee from Student Wallet | C12: خصم رسوم التسجيل من محفظة الطالب | D12: Wallet Management | E12: نظام | F12: Must | G12: جزئي | H12: صفحة المحفظة تعرض الرصيد لكن لا توجد واجهة خصم/تسجيل | I12: نعم | J12: WP-W1 | K12: =COUNTIF(Tasks!$D$5:$D$300,A12) | L12: =COUNTIFS(Tasks!$D$5:$D$300,A12,Tasks!$M$5:$M$300,"مكتمل") | M12: =COUNTIFS(Tasks!$D$5:$D$300,A12,Tasks!$M$5:$M$300,"قيد التنفيذ")+COUNTIFS(Tasks!$D$5:$D$300,A12,Tasks!$M$5:$M$300,"قيد المراجعة") | N12: =COUNTIF(UAT!$B$5:$B$300,A12) | O12: =COUNTIFS(UAT!$B$5:$B$300,A12,UAT!$H$5:$H$300,"نجح") | P12: =COUNTIFS(UAT!$B$5:$B$300,A12,UAT!$H$5:$H$300,"فشل") | Q12: =IF(G12="جاهز","جاهز (أصلي)",IF(K12=0,"—",IF(AND(L12=K12,N12>0,O12=N12),"جاهز",IF(L12=K12,"مكتمل – بانتظار UAT",IF(L12+M12>0,"قيد التنفيذ","لم يبدأ")))))
A13: FR-W03b | B13: Credit Instructor Wallet After Commission | C13: إيداع أرباح المعلم بعد العمولة | D13: Wallet Management | E13: نظام | F13: Must | G13: جزئي | H13: واجهة أرباح المعلم موجودة لكن عملية الخصم/الإيداع في الباك اند | I13: نعم | J13: WP-W2 | K13: =COUNTIF(Tasks!$D$5:$D$300,A13) | L13: =COUNTIFS(Tasks!$D$5:$D$300,A13,Tasks!$M$5:$M$300,"مكتمل") | M13: =COUNTIFS(Tasks!$D$5:$D$300,A13,Tasks!$M$5:$M$300,"قيد التنفيذ")+COUNTIFS(Tasks!$D$5:$D$300,A13,Tasks!$M$5:$M$300,"قيد المراجعة") | N13: =COUNTIF(UAT!$B$5:$B$300,A13) | O13: =COUNTIFS(UAT!$B$5:$B$300,A13,UAT!$H$5:$H$300,"نجح") | P13: =COUNTIFS(UAT!$B$5:$B$300,A13,UAT!$H$5:$H$300,"فشل") | Q13: =IF(G13="جاهز","جاهز (أصلي)",IF(K13=0,"—",IF(AND(L13=K13,N13>0,O13=N13),"جاهز",IF(L13=K13,"مكتمل – بانتظار UAT",IF(L13+M13>0,"قيد التنفيذ","لم يبدأ")))))
A14: FR-P04 | B14: View Student Attendance | C14: عرض حضور الطالب (ولي أمر) | D14: Parent Academic Monitoring | E14: ولي أمر | F14: Must | G14: جاهز | H14: parent.report.tsx يعرض سجل حضور الطالب | I14: نعم | J14: — | K14: =COUNTIF(Tasks!$D$5:$D$300,A14) | L14: =COUNTIFS(Tasks!$D$5:$D$300,A14,Tasks!$M$5:$M$300,"مكتمل") | M14: =COUNTIFS(Tasks!$D$5:$D$300,A14,Tasks!$M$5:$M$300,"قيد التنفيذ")+COUNTIFS(Tasks!$D$5:$D$300,A14,Tasks!$M$5:$M$300,"قيد المراجعة") | N14: =COUNTIF(UAT!$B$5:$B$300,A14) | O14: =COUNTIFS(UAT!$B$5:$B$300,A14,UAT!$H$5:$H$300,"نجح") | P14: =COUNTIFS(UAT!$B$5:$B$300,A14,UAT!$H$5:$H$300,"فشل") | Q14: =IF(G14="جاهز","جاهز (أصلي)",IF(K14=0,"—",IF(AND(L14=K14,N14>0,O14=N14),"جاهز",IF(L14=K14,"مكتمل – بانتظار UAT",IF(L14+M14>0,"قيد التنفيذ","لم يبدأ")))))
A15: FR-P05 | B15: View Student Examination Results | C15: عرض نتائج الامتحانات (ولي أمر) | D15: Parent Academic Monitoring | E15: ولي أمر | F15: Must | G15: جاهز | H15: parent.report.tsx يعرض نتائج الامتحانات | I15: نعم | J15: — | K15: =COUNTIF(Tasks!$D$5:$D$300,A15) | L15: =COUNTIFS(Tasks!$D$5:$D$300,A15,Tasks!$M$5:$M$300,"مكتمل") | M15: =COUNTIFS(Tasks!$D$5:$D$300,A15,Tasks!$M$5:$M$300,"قيد التنفيذ")+COUNTIFS(Tasks!$D$5:$D$300,A15,Tasks!$M$5:$M$300,"قيد المراجعة") | N15: =COUNTIF(UAT!$B$5:$B$300,A15) | O15: =COUNTIFS(UAT!$B$5:$B$300,A15,UAT!$H$5:$H$300,"نجح") | P15: =COUNTIFS(UAT!$B$5:$B$300,A15,UAT!$H$5:$H$300,"فشل") | Q15: =IF(G15="جاهز","جاهز (أصلي)",IF(K15=0,"—",IF(AND(L15=K15,N15>0,O15=N15),"جاهز",IF(L15=K15,"مكتمل – بانتظار UAT",IF(L15+M15>0,"قيد التنفيذ","لم يبدأ")))))
A16: FR-P06 | B16: Calculate Student Attendance Rate | C16: احتساب نسبة الحضور | D16: Parent Academic Monitoring | E16: نظام | F16: Must | G16: جاهز | H16: النسبة تظهر في تقرير الابن | I16: نعم | J16: — | K16: =COUNTIF(Tasks!$D$5:$D$300,A16) | L16: =COUNTIFS(Tasks!$D$5:$D$300,A16,Tasks!$M$5:$M$300,"مكتمل") | M16: =COUNTIFS(Tasks!$D$5:$D$300,A16,Tasks!$M$5:$M$300,"قيد التنفيذ")+COUNTIFS(Tasks!$D$5:$D$300,A16,Tasks!$M$5:$M$300,"قيد المراجعة") | N16: =COUNTIF(UAT!$B$5:$B$300,A16) | O16: =COUNTIFS(UAT!$B$5:$B$300,A16,UAT!$H$5:$H$300,"نجح") | P16: =COUNTIFS(UAT!$B$5:$B$300,A16,UAT!$H$5:$H$300,"فشل") | Q16: =IF(G16="جاهز","جاهز (أصلي)",IF(K16=0,"—",IF(AND(L16=K16,N16>0,O16=N16),"جاهز",IF(L16=K16,"مكتمل – بانتظار UAT",IF(L16+M16>0,"قيد التنفيذ","لم يبدأ")))))
... A41: FR-T10 | B41: Manage Teacher Booking Requests | C41: إدارة طلبات الحجز (معلم) | D41: Teacher Discovery & Booking | E41: معلم | F41: Must | G41: غير مغطى بالتقرير | H41: خارج الـ30. بدونه لا يكتمل مسار FR-T06/S14/S15 | I41: لا (داعم) | J41: WP-T5 | K41: =COUNTIF(Tasks!$D$5:$D$300,A41) | L41: =COUNTIFS(Tasks!$D$5:$D$300,A41,Tasks!$M$5:$M$300,"مكتمل") | M41: =COUNTIFS(Tasks!$D$5:$D$300,A41,Tasks!$M$5:$M$300,"قيد التنفيذ")+COUNTIFS(Tasks!$D$5:$D$300,A41,Tasks!$M$5:$M$300,"قيد المراجعة") | N41: =COUNTIF(UAT!$B$5:$B$300,A41) | O41: =COUNTIFS(UAT!$B$5:$B$300,A41,UAT!$H$5:$H$300,"نجح") | P41: =COUNTIFS(UAT!$B$5:$B$300,A41,UAT!$H$5:$H$300,"فشل") | Q41: =IF(G41="جاهز","جاهز (أصلي)",IF(K41=0,"—",IF(AND(L41=K41,N41>0,O41=N41),"جاهز",IF(L41=K41,"مكتمل – بانتظار UAT",IF(L41+M41>0,"قيد التنفيذ","لم يبدأ")))))

Sheet UAT
A1: قبول المستخدم (UAT) — معايير القبول من SRS
A2: كل صف = فحص واحد. الأصفر = إدخال النتيجة. نتائج «نجح» لكل صفوف FR مع اكتمال مهامه = FR «جاهز» في FR_Matrix.
A4: UAT | B4: FR | C4: النوع | D4: الفحص | E4: النتيجة المتوقعة | F4: WP | G4: الدور/الحساب | H4: النتيجة | I4: نفّذه | J4: التاريخ | K4: ملاحظات / Bug
A5: UAT-001 | B5: FR-I02 | C5: رئيسي | D5: المعلم يفتح تبويب المجموعة لكورس حضوري ويدخل: السعة، تاريخ البداية/النهاية، مدة الدرس، أيام الحضور + الوقت ثم يحفظ | E5: الحفظ ينجح وتظهر القيم المحفوظة عند إعادة الفتح | F5: WP-T2 | G5: معلم | H5: لم يُختبر
A6: UAT-002 | B6: FR-I02 | C6: استثناء | D6: إدخال جدول غير صالح (نهاية قبل البداية / سعة 0 / بلا أيام / يوم مكرر) | E6: رسالة تحقق واضحة ولا يحدث حفظ | F6: WP-T2 | G6: معلم | H6: لم يُختبر
A7: UAT-003 | B7: FR-I02 | C7: بديل | D7: تعديل السعة أو الجدول قبل بداية الكورس | E7: يتم الحفظ ويُعكس التعديل | F7: WP-T2 | G7: معلم | H7: لم يُختبر
A8: UAT-004 | B8: FR-I06 | C8: رئيسي | D8: نفس الإعداد لكورس أونلاين | E8: الحفظ ينجح | F8: WP-T2 | G8: معلم | H8: لم يُختبر
A9: UAT-005 | B9: FR-I06 | C9: استثناء | D9: جدول يتعارض مع درس مجدول | E9: تحذير تعارض من الباك اند ويمنع الحفظ | F9: WP-T2 | G9: معلم | H9: لم يُختبر
A10: UAT-006 | B10: FR-I03 | C10: رئيسي | D10: فتح تبويب «طلاب المجموعة» لمجموعة فيها طلاب مقبولون | E10: تظهر قائمة (اسم، هاتف، موقع) فقط | F10: WP-T3 | G10: معلم | H10: لم يُختبر
A11: UAT-007 | B11: FR-I03 | C11: بديل | D11: البحث بالاسم | E11: تُفلتر القائمة | F11: WP-T3 | G11: معلم | H11: لم يُختبر
A12: UAT-008 | B12: FR-I03 | C12: استثناء | D12: مجموعة بلا طلاب | E12: رسالة فراغ مناسبة (ليست خطأ) | F12: WP-T3 | G12: معلم | H12: لم يُختبر
A13: UAT-009 | B13: FR-I04 | C13: رئيسي | D13: إضافة درس حضوري: رقم، موضوع، تاريخ، وقت، مدة، (قاعة) | E13: يظهر الدرس في جدول الكورس مع اليوم الصحيح | F13: WP-T4 | G13: معلم | H13: لم يُختبر
A14: UAT-010 | B14: FR-I04 | C14: استثناء | D14: درس يتعارض مع درس آخر أو تاريخ/وقت غير صالح | E14: رسالة خطأ ولا يُحفظ | F14: WP-T4 | G14: معلم | H14: لم يُختبر
A15: UAT-011 | B15: FR-I04 | C15: بديل | D15: تعديل درس قبل موعده | E15: يُحفظ التعديل؛ ولا يمكن تعديل درس بدأ | F15: WP-T4 | G15: معلم | H15: لم يُختبر
A16: UAT-012 | B16: FR-I08 | C16: رئيسي | D16: إضافة درس أونلاين مع منصة ورابط http/https | E16: يظهر الدرس مع المنصة والرابط | F16: WP-T4 | G16: معلم | H16: لم يُختبر
... A68: UAT-064 | B68: FR-T10 | C68: بديل | D68: رفض بسبب | E68: السبب يظهر للطالب | F68: WP-T5 | G68: معلم + طالب | H68: لم يُختبر

Sheet FileOwnership
A1: ملكية الملفات (منع التعارض)
A2: كل مسار مالك واحد فقط. عمود «فحص التعارض» يكشف أي مسار مكرر. أضف أي ملف جديد هنا قبل البدء بكتابته.
A4: # | B4: المسار | C4: المالك | D4: الإجراء | E4: Stub أنشأه | F4: الخطورة | G4: فحص التعارض | H4: ملاحظة
A5: 1 | B5: src/integrations/backend/bookings.ts | C5: WP-00 | D5: تعديل | E5: — | F5: عالٍ | G5: =IF(COUNTIF($B$5:$B$300,B5)>1,"⚠ مكرر","✔") | H5: بعد WP-00 مجمّد. من يحتاج دالة جديدة يضعها في ملف ext/ الخاص به ويطلب CR.
A6: 2 | B6: src/integrations/backend/lessons.ts | C6: WP-00 | D6: تعديل | E6: — | F6: عالٍ | G6: =IF(COUNTIF($B$5:$B$300,B6)>1,"⚠ مكرر","✔") | H6: مجمّد بعد WP-00
A7: 3 | B7: src/integrations/backend/courses.ts | C7: WP-00 | D7: تعديل | E7: — | F7: عالٍ | G7: =IF(COUNTIF($B$5:$B$300,B7)>1,"⚠ مكرر","✔") | H7: مجمّد بعد WP-00
A8: 4 | B8: src/integrations/backend/student.ts | C8: WP-00 | D8: تعديل | E8: — | F8: عالٍ | G8: =IF(COUNTIF($B$5:$B$300,B8)>1,"⚠ مكرر","✔") | H8: مجمّد بعد WP-00
A9: 5 | B9: src/integrations/backend/op-result.ts | C9: WP-00 | D9: إنشاء | E9: — | F9: متوسط | G9: =IF(COUNTIF($B$5:$B$300,B9)>1,"⚠ مكرر","✔") | H9: مجمّد بعد WP-00
A10: 6 | B10: src/integrations/backend/bookings.test.ts | C10: WP-00 | D10: إنشاء | E10: — | F10: منخفض | G10: =IF(COUNTIF($B$5:$B$300,B10)>1,"⚠ مكرر","✔")
A11: 7 | B11: src/integrations/backend/lessons.test.ts | C11: WP-00 | D11: إنشاء | E11: — | F11: منخفض | G11: =IF(COUNTIF($B$5:$B$300,B11)>1,"⚠ مكرر","✔")
A12: 8 | B12: src/integrations/backend/student.test.ts | C12: WP-00 | D12: إنشاء | E12: — | F12: منخفض | G12: =IF(COUNTIF($B$5:$B$300,B12)>1,"⚠ مكرر","✔")
A13: 9 | B13: src/integrations/backend/courses.test.ts | C13: WP-00 | D13: تعديل | E13: — | F13: منخفض | G13: =IF(COUNTIF($B$5:$B$300,B13)>1,"⚠ مكرر","✔")
A14: 10 | B14: src/lib/enums.ts | C14: WP-00 | D14: إنشاء | E14: — | F14: متوسط | G14: =IF(COUNTIF($B$5:$B$300,B14)>1,"⚠ مكرر","✔") | H14: مجمّد بعد WP-00
A15: 11 | B15: src/lib/format.ts | C15: WP-00 | D15: إنشاء | E15: — | F15: متوسط | G15: =IF(COUNTIF($B$5:$B$300,B15)>1,"⚠ مكرر","✔") | H15: مجمّد بعد WP-00
A16: 12 | B16: src/lib/format.test.ts | C16: WP-00 | D16: إنشاء | E16: — | F16: منخفض | G16: =IF(COUNTIF($B$5:$B$300,B16)>1,"⚠ مكرر","✔")
A17: 13 | B17: src/lib/query-keys.ts | C17: WP-00 | D17: إنشاء | E17: — | F17: متوسط | G17: =IF(COUNTIF($B$5:$B$300,B17)>1,"⚠ مكرر","✔") | H17: أُضيف إليه qk.teacherEarningsCredits() من WP-W2 قبل إغلاق WP-00 (بلا CR). كل مفاتيح react-query الجديدة من هنا فقط
A18: 14 | B18: src/lib/booking-rules.ts | C18: WP-00 | D18: إنشاء | E18: — | F18: متوسط | G18: =IF(COUNTIF($B$5:$B$300,B18)>1,"⚠ مكرر","✔")
A19: 15 | B19: src/lib/booking-rules.test.ts | C19: WP-00 | D19: إنشاء | E19: — | F19: منخفض | G19: =IF(COUNTIF($B$5:$B$300,B19)>1,"⚠ مكرر","✔")
A20: 16 | B20: src/components/app/booking-status-badge.tsx | C20: WP-00 | D20: إنشاء | E20: — | F20: منخفض | G20: =IF(COUNTIF($B$5:$B$300,B20)>1,"⚠ مكرر","✔")
A21: 17 | B21: src/components/ui/star-rating.tsx | C21: WP-00 | D21: إنشاء | E21: — | F21: منخفض | G21: =IF(COUNTIF($B$5:$B$300,B21)>1,"⚠ مكرر","✔")
A22: 18 | B22: src/components/ui/segmented-tabs.tsx | C22: WP-00 | D22: إنشاء | E22: — | F22: منخفض | G22: =IF(COUNTIF($B$5:$B$300,B22)>1,"⚠ مكرر","✔")
A23: 19 | B23: src/components/app/confirm-dialog.tsx | C23: WP-00 | D23: إنشاء | E23: — | F23: منخفض | G23: =IF(COUNTIF($B$5:$B$300,B23)>1,"⚠ مكرر","✔")
A24: 20 | B24: src/lib/rbac-static-data.ts | C24: WP-00 | D24: تعديل | E24: — | F24: عالٍ | G24: =IF(COUNTIF($B$5:$B$300,B24)>1,"⚠ مكرر","✔") | H24: تسجيل التنقّل مرة واحدة. ممنوع على Wave 1.
A25: 21 | B25: src/routes/_authenticated/my-courses.tsx | C25: WP-00 | D25: تعديل | E25: — | F25: عالٍ | G25: =IF(COUNTIF($B$5:$B$300,B25)>1,"⚠ مكرر","✔") | H25: يُعاد تركيبه من لوحات ثم يُجمَّد
A26: 22 | B26: src/components/admin/app-sidebar.tsx | C26: WP-00 | D26: تعديل (اختياري) | E26: — | F26: متوسط | G26: =IF(COUNTIF($B$5:$B$300,B26)>1,"⚠ مكرر","✔") | H26: فقط مهمة 00-19
A27: 23 | B27: src/routeTree.gen.ts | C27: WP-00 / WP-QA فقط | D27: تلقائي | E27: — | F27: عالٍ جدًا | G27: =IF(COUNTIF($B$5:$B$300,B27)>1,"⚠ مكرر","✔") | H27: لا تعدّله يدويًا ولا تضعه في PR أي WP آخر. عند التعارض: احذفه وأعد التوليد
A28: 24 | B28: src/routes/_authenticated/teacher.courses.tsx | C28: WP-T1 | D28: استبدال | E28: WP-00 (لا يحتاج) | F28: متوسط | G28: =IF(COUNTIF($B$5:$B$300,B28)>1,"⚠ مكرر","✔") | H28: موجود حاليًا كـ placeholder
A29: 25 | B29: src/routes/_authenticated/teacher.course.$id.tsx | C29: WP-T1 | D29: إنشاء | E29: WP-00 | F29: متوسط | G29: =IF(COUNTIF($B$5:$B$300,B29)>1,"⚠ مكرر","✔") | H29: Shell بتبويبات؛ يستورد مكونات T2/T3/T4
A30: 26 | B30: src/components/teacher/course-details-tab.tsx | C30: WP-T1 | D30: إنشاء | E30: WP-00 | F30: منخفض | G30: =IF(COUNTIF($B$5:$B$300,B30)>1,"⚠ مكرر","✔")
A31: 27 | B31: src/components/teacher/course-details-tab.test.ts | C31: WP-T1 | D31: إنشاء | E31: — | F31: منخفض | G31: =IF(COUNTIF($B$5:$B$300,B31)>1,"⚠ مكرر","✔")
A32: 28 | B32: src/components/teacher/group-config-tab.tsx | C32: WP-T2 | D32: إنشاء | E32: WP-00 | F32: منخفض | G32: =IF(COUNTIF($B$5:$B$300,B32)>1,"⚠ مكرر","✔")
A33: 29 | B33: src/components/teacher/group-config-tab.test.ts | C33: WP-T2 | D33: إنشاء | E33: — | F33: منخفض | G33: =IF(COUNTIF($B$5:$B$300,B33)>1,"⚠ مكرر","✔")
A34: 30 | B34: src/components/teacher/group-students-tab.tsx | C34: WP-T3 | D34: إنشاء | E34: WP-00 | F34: منخفض | G34: =IF(COUNTIF($B$5:$B$300,B34)>1,"⚠ مكرر","✔")
A35: 31 | B35: src/components/teacher/lessons-tab.tsx | C35: WP-T4 | D35: إنشاء | E35: WP-00 | F35: منخفض | G35: =IF(COUNTIF($B$5:$B$300,B35)>1,"⚠ مكرر","✔")
A36: 32 | B36: src/components/teacher/lesson-form-dialog.tsx | C36: WP-T4 | D36: إنشاء | E36: WP-00 | F36: منخفض | G36: =IF(COUNTIF($B$5:$B$300,B36)>1,"⚠ مكرر","✔")
A37: 33 | B37: src/components/teacher/lesson-form-dialog.test.ts | C37: WP-T4 | D37: إنشاء | E37: — | F37: منخفض | G37: =IF(COUNTIF($B$5:$B$300,B37)>1,"⚠ مكرر","✔")
A38: 34 | B38: src/components/teacher/lesson-cancel-dialog.tsx | C38: WP-T4 | D38: إنشاء | E38: WP-00 | F38: منخفض | G38: =IF(COUNTIF($B$5:$B$300,B38)>1,"⚠ مكرر","✔")
A39: 35 | B39: src/routes/_authenticated/teacher.bookings.tsx | C39: WP-T5 | D39: إنشاء | E39: WP-00 | F39: منخفض | G39: =IF(COUNTIF($B$5:$B$300,B39)>1,"⚠ مكرر","✔")
A40: 36 | B40: src/routes/_authenticated/teacher.dashboard.tsx | C40: WP-T5 | D40: تعديل | E40: — | F40: منخفض | G40: =IF(COUNTIF($B$5:$B$300,B40)>1,"⚠ مكرر","✔") | H40: استبدال اللوحة المعطّلة فقط
A41: 37 | B41: src/routes/_authenticated/book.$teacherId.tsx | C41: WP-S1 | D41: إنشاء | E41: WP-00 | F41: متوسط | G41: =IF(COUNTIF($B$5:$B$300,B41)>1,"⚠ مكرر","✔")
A42: 38 | B42: src/routes/teacher.$id.tsx | C42: WP-S1 | D42: تعديل | E42: — | F42: متوسط | G42: =IF(COUNTIF($B$5:$B$300,B42)>1,"⚠ مكرر","✔") | H42: صفحة عامة؛ زر الحجز فقط
A43: 39 | B43: src/components/student/booking-slot-picker.tsx | C43: WP-S1 | D43: إنشاء | E43: WP-00 | F43: منخفض | G43: =IF(COUNTIF($B$5:$B$300,B43)>1,"⚠ مكرر","✔")
A44: 40 | B44: src/components/student/booking-slot-picker.test.ts | C44: WP-S1 | D44: إنشاء | E44: — | F44: منخفض | G44: =IF(COUNTIF($B$5:$B$300,B44)>1,"⚠ مكرر","✔")
A45: 41 | B45: src/routes/_authenticated/booking.$id.tsx | C45: WP-S2 | D45: إنشاء | E45: WP-00 | F45: متوسط | G45: =IF(COUNTIF($B$5:$B$300,B45)>1,"⚠ مكرر","✔") | H45: يستورد مكونات W1/S3/S4
A46: 42 | B46: src/components/student/cancel-booking-dialog.tsx | C46: WP-S2 | D46: إنشاء | E46: WP-00 | F46: منخفض | G46: =IF(COUNTIF($B$5:$B$300,B46)>1,"⚠ مكرر","✔")
A47: 43 | B47: src/components/student/my-courses/confirmed-bookings-panel.tsx | C47: WP-S2 | D47: إنشاء | E47: WP-00 | F47: منخفض | G47: =IF(COUNTIF($B$5:$B$300,B47)>1,"⚠ مكرر","✔")
A48: 44 | B48: src/components/student/my-courses/pending-requests-panel.tsx | C48: WP-S2 | D48: إنشاء | E48: WP-00 | F48: منخفض | G48: =IF(COUNTIF($B$5:$B$300,B48)>1,"⚠ مكرر","✔")
A49: 45 | B49: src/components/student/reschedule-dialog.tsx | C49: WP-S3 | D49: إنشاء | E49: WP-00 | F49: منخفض | G49: =IF(COUNTIF($B$5:$B$300,B49)>1,"⚠ مكرر","✔")
A50: 46 | B50: src/components/student/reschedule-dialog.test.ts | C50: WP-S3 | D50: إنشاء | E50: — | F50: منخفض | G50: =IF(COUNTIF($B$5:$B$300,B50)>1,"⚠ مكرر","✔")
A51: 47 | B51: src/components/student/my-courses/reschedule-requests-panel.tsx | C51: WP-S3 | D51: إنشاء | E51: WP-00 | F51: منخفض | G51: =IF(COUNTIF($B$5:$B$300,B51)>1,"⚠ مكرر","✔")
A52: 48 | B52: src/components/student/rate-booking-dialog.tsx | C52: WP-S4 | D52: إنشاء | E52: WP-00 | F52: منخفض | G52: =IF(COUNTIF($B$5:$B$300,B52)>1,"⚠ مكرر","✔")
A53: 49 | B53: src/components/student/rate-booking-dialog.test.ts | C53: WP-S4 | D53: إنشاء | E53: — | F53: منخفض | G53: =IF(COUNTIF($B$5:$B$300,B53)>1,"⚠ مكرر","✔")
A54: 50 | B54: src/routes/_authenticated/lesson.$id.tsx | C54: WP-S5 | D54: إنشاء | E54: WP-00 | F54: منخفض | G54: =IF(COUNTIF($B$5:$B$300,B54)>1,"⚠ مكرر","✔")
A55: 51 | B55: src/test-units/lesson.$id.test.ts | C55: WP-S5 | D55: إنشاء | E55: — | F55: منخفض | G55: =IF(COUNTIF($B$5:$B$300,B55)>1,"⚠ مكرر","✔")
A56: 52 | B56: src/routes/_authenticated/schedule.tsx | C56: WP-S5 | D56: تعديل | E56: — | F56: متوسط | G56: =IF(COUNTIF($B$5:$B$300,B56)>1,"⚠ مكرر","✔")
A57: 53 | B57: src/routes/_authenticated/enrolled-course.$id.tsx | C57: WP-S6 | D57: إنشاء | E57: WP-00 | F57: منخفض | G57: =IF(COUNTIF($B$5:$B$300,B57)>1,"⚠ مكرر","✔")
... A69: 65 | B69: src/routes/_authenticated/wallet.tsx | C69: WP-W1 | D69: تعديل | E69: — | F69: منخفض | G69: =IF(COUNTIF($B$5:$B$300,B69)>1,"⚠ مكرر","✔")
A70: 66 | B70: src/components/wallet/wallet-balance-panel.tsx | C70: WP-W1 | D70: تعديل | E70: — | F70: متوسط | G70: =IF(COUNTIF($B$5:$B$300,B70)>1,"⚠ مكرر","✔") | H70: يستهلكه teacher.earnings أيضًا: أي تغيير على props يكون اختياريًا فقط
A71: 67 | B71: src/components/wallet/insufficient-balance-alert.tsx | C71: WP-W1 | D71: إنشاء | E71: WP-00 | F71: منخفض | G71: =IF(COUNTIF($B$5:$B$300,B71)>1,"⚠ مكرر","✔") | H71: يستهلكه WP-S1 وWP-S2
A72: 68 | B72: src/components/student/booking-payment-card.tsx | C72: WP-W1 | D72: إنشاء | E72: WP-00 | F72: منخفض | G72: =IF(COUNTIF($B$5:$B$300,B72)>1,"⚠ مكرر","✔") | H72: يستهلكه WP-S2
A73: 69 | B73: src/components/student/booking-payment-card.test.ts | C73: WP-W1 | D73: إنشاء | E73: — | F73: منخفض | G73: =IF(COUNTIF($B$5:$B$300,B73)>1,"⚠ مكرر","✔")
A74: 70 | B74: src/routes/_authenticated/teacher.earnings.tsx | C74: WP-W2 | D74: تعديل | E74: — | F74: منخفض | G74: =IF(COUNTIF($B$5:$B$300,B74)>1,"⚠ مكرر","✔")
A75: 71 | B75: src/test-units/teacher.earnings.test.ts | C75: WP-W2 | D75: إنشاء | E75: — | F75: منخفض | G75: =IF(COUNTIF($B$5:$B$300,B75)>1,"⚠ مكرر","✔")
A76: 72 | B76: e2e/*.spec.ts | C76: WP-QA | D76: إنشاء | E76: — | F76: منخفض | G76: =IF(COUNTIF($B$5:$B$300,B76)>1,"⚠ مكرر","✔")
A77: 73 | B77: README.md | C77: WP-QA | D77: تعديل | E77: — | F77: متوسط | G77: =IF(COUNTIF($B$5:$B$300,B77)>1,"⚠ مكرر","✔")
A78: 74 | B78: CHANGELOG.md | C78: WP-QA | D78: تعديل | E78: — | F78: متوسط | G78: =IF(COUNTIF($B$5:$B$300,B78)>1,"⚠ مكرر","✔") | H78: سطر جديد فوق فقط (append-only)
A79: 75 | B79: PROJECT-ATLAS.md | C79: WP-QA | D79: تعديل | E79: — | F79: متوسط | G79: =IF(COUNTIF($B$5:$B$300,B79)>1,"⚠ مكرر","✔")
A80: 76 | B80: src/integrations/backend/pending-json.ts | C80: WP-00 | D80: إنشاء | E80: — | F80: منخفض | G80: =IF(COUNTIF($B$5:$B$300,B80)>1,"⚠ مكرر","✔") | H80: النوع المؤقت للردود غير الموثّقة؛ يُقلَّص تدريجيًا بواسطة WP-J
A81: 77 | B81: src/lib/parent-report.ts | C81: WP-P1 | D81: إنشاء | E81: — | F81: منخفض | G81: =IF(COUNTIF($B$5:$B$300,B81)>1,"⚠ مكرر","✔") | H81: منطق نقي لتقرير ولي الأمر (سجّله المستخدم في v1.4)
A82: 78 | B82: src/lib/earnings.ts | C82: WP-W2 | D82: إنشاء | E82: — | F82: منخفض | G82: =IF(COUNTIF($B$5:$B$300,B82)>1,"⚠ مكرر","✔") | H82: منطق نقي لأرباح المعلم (سجّله المستخدم في v1.4)
A83: 79 | B83: src/lib/booking-slots.ts | C83: WP-S1 | D83: إنشاء | E83: — | F83: منخفض | G83: =IF(COUNTIF($B$5:$B$300,B83)>1,"⚠ مكرر","✔") | H83: محفوظ لـClaude (A-claude): توليد الأوقات المتاحة وتقدير السعر
A84: 80 | B84: src/lib/reschedule-validation.ts | C84: WP-S3 | D84: إنشاء | E84: — | F84: منخفض | G84: =IF(COUNTIF($B$5:$B$300,B84)>1,"⚠ مكرر","✔") | H84: محفوظ لـClaude (A-claude): تحقق نافذة إعادة الجدولة
A85: 81 | B85: src/lib/schedule-join.ts | C85: WP-S5 | D85: إنشاء | E85: — | F85: منخفض | G85: =IF(COUNTIF($B$5:$B$300,B85)>1,"⚠ مكرر","✔") | H85: محفوظ لـClaude (A-claude): قواعد عرض زر الانضمام/الرابط
A86: 82 | B86: src/lib/exam-percent.ts | C86: WP-S8 | D86: إنشاء | E86: — | F86: منخفض | G86: =IF(COUNTIF($B$5:$B$300,B86)>1,"⚠ مكرر","✔") | H86: محفوظ لـClaude (A-claude): حساب نسبة الامتحان
A87: 83 | B87: src/components/student/attendance-rate-card.tsx | C87: WP-S7 | D87: إنشاء | E87: — | F87: منخفض | G87: =IF(COUNTIF($B$5:$B$300,B87)>1,"⚠ مكرر","✔") | H87: محفوظ لـClaude (A-claude): بطاقة نسبة الحضور (S7-02)
A88: 84 | B88: src/lib/progress.ts | C88: WP-S9 | D88: إنشاء | E88: — | F88: منخفض | G88: =IF(COUNTIF($B$5:$B$300,B88)>1,"⚠ مكرر","✔") | H88: منطق نقي لصفحة التقدم (سجّله المستخدم v1.5)
A89: 85 | B89: src/components/teacher/lesson-form-schema.ts | C89: WP-T4 | D89: إنشاء | E89: — | F89: منخفض | G89: =IF(COUNTIF($B$5:$B$300,B89)>1,"⚠ مكرر","✔") | H89: مخطط zod لنموذج الدرس (سجّله المستخدم v1.5)
A90: 86 | B90: src/components/teacher/group-schedule-validation.ts | C90: WP-T2 | D90: إنشاء | E90: — | F90: منخفض | G90: =IF(COUNTIF($B$5:$B$300,B90)>1,"⚠ مكرر","✔") | H90: محققات جدول المجموعة (سجّله المستخدم v1.5)
A91: 87 | B91: src/lib/rating.ts | C91: WP-S4 | D91: إنشاء | E91: — | F91: منخفض | G91: =IF(COUNTIF($B$5:$B$300,B91)>1,"⚠ مكرر","✔") | H91: تحقق نقي للتقييم (Claude v1.5)
... A104: 100 | B104: src/routes/_authenticated/notifications.tsx | C104: مجمّد | D104: ممنوع | E104: — | F104: — | G104: =IF(COUNTIF($B$5:$B$300,B104)>1,"⚠ مكرر","✔") | H104: جاهزة FR-S12

Sheet Contracts
A1: العقود بين الـ WPs (واجهات المكونات والاتفاقات)
A2: هذا ما يجعل الـ WPs تعمل بالتوازي بدون انتظار بعضها: كل مكوّن مُستهلَك له Stub من WP-00 بنفس الـ props. لا يغيّر مالك مكوّن توقيعه بدون CR.
A4: ID | B4: الاسم | C4: الملف (تحت src/) | D4: التوقيع / الـ props / القاعدة | E4: المالك | F4: المستهلكون | G4: ملاحظات
A5: C-01 | B5: تبويبات شاشة الكورس (4 مكونات) | C5: components/teacher/{course-details-tab,group-config-tab,group-students-tab,lessons-tab}.tsx | D5: props: { course: TeacherCourseDetail; onChanged: () => void } | E5: T1 / T2 / T3 / T4 | F5: WP-T1 (shell) | G5: الـ shell هو الذي يجلب الكورس ويمرّره. النوع يُعرَّف في courses.ts (WP-00) ويُعدَّل بعد عينة Q-05.
A6: C-02 | B6: بطاقة حالة دفع الحجز | C6: components/student/booking-payment-card.tsx | D6: props: { bookingId: number } | E6: WP-W1 | F6: WP-S2 | G6: تجلب Student/BookingPayment داخليًا.
A7: C-03 | B7: تنبيه الرصيد غير الكافي | C7: components/wallet/insufficient-balance-alert.tsx | D7: props: { required: number; balance: number } | E7: WP-W1 | F7: WP-S1, WP-S2
A8: C-04 | B8: نافذة إلغاء الحجز | C8: components/student/cancel-booking-dialog.tsx | D8: props: { booking: StudentBookingDetail; open: boolean; onOpenChange(o:boolean): void } | E8: WP-S2 | F8: WP-S2 (booking.$id) | G8: داخلية لـ WP-S2.
A9: C-05 | B9: نافذة إعادة الجدولة | C9: components/student/reschedule-dialog.tsx | D9: props: { booking: StudentBookingDetail; open: boolean; onOpenChange(o:boolean): void } | E9: WP-S3 | F9: WP-S2
A10: C-06 | B10: نافذة التقييم | C10: components/student/rate-booking-dialog.tsx | D10: props: { booking: StudentBookingDetail; open: boolean; onOpenChange(o:boolean): void } | E10: WP-S4 | F10: WP-S2
A11: C-07 | B11: لوحة طلبات إعادة الجدولة | C11: components/student/my-courses/reschedule-requests-panel.tsx | D11: props: {} (تجلب بنفسها) | E11: WP-S3 | F11: my-courses.tsx (WP-00)
A12: C-08 | B12: لوحة الكورسات المسجّلة | C12: components/student/my-courses/enrolled-courses-panel.tsx | D12: props: {} | E12: WP-S6 | F12: my-courses.tsx (WP-00)
A13: C-09 | B13: لوحتا الحجوزات والطلبات | C13: components/student/my-courses/{confirmed-bookings-panel,pending-requests-panel}.tsx | D13: props: {} | E13: WP-S2 | F13: my-courses.tsx (WP-00)
A14: C-10 | B14: شارة حالة الحجز | C14: components/app/booking-status-badge.tsx | D14: props: { status: number } | E14: WP-00 | F14: كل WP | G14: القيم 1..6 (Pending, Accepted, Rejected, Cancelled, Confirmed, Completed).
A15: C-11 | B15: نجوم التقييم | C15: components/ui/star-rating.tsx | D15: props: { value: number; onChange?(v:number): void; readOnly?: boolean } | E15: WP-00 | F15: WP-S4, WP-T5
A16: C-12 | B16: تبويبات مقسّمة | C16: components/ui/segmented-tabs.tsx | D16: props: { value: string; onChange(v:string): void; items: {value:string; label:string; disabled?:boolean}[] } | E16: WP-00 | F16: WP-T1, WP-T5
A17: C-13 | B17: نافذة تأكيد | C17: components/app/confirm-dialog.tsx | D17: props: { open; onOpenChange; title; description; confirmLabel; onConfirm; loading?; destructive? } | E17: WP-00 | F17: كل WP
A18: C-14 | B18: نتيجة العملية | C18: integrations/backend/op-result.ts | D18: assertOk(result: OperationResult, fallbackAr: string, fallbackEn: string): void | E18: WP-00 | F18: كل WP | G18: كل POST/PUT يرجع OperationResult {success, message, returnId..}. تحقق منه دائمًا.
A19: C-15 | B19: قواعد أهلية الحجز | C19: lib/booking-rules.ts | D19: canCancel(b) / canReschedule(b) / canRate(b): boolean | E19: WP-00 | F19: WP-S2, S3, S4 | G19: الباك اند هو المرجع النهائي؛ هذه فقط لإخفاء/إظهار الأزرار.
A20: C-16 | B20: مفاتيح react-query | C20: lib/query-keys.ts | D20: qk.studentBooking(id) .. + invalidateBookingQueries(qc, id?) | E20: WP-00 | F20: كل WP | G20: ممنوع ابتكار مفاتيح جديدة خارج الملف.
A21: C-17 | B21: إعادة استخدام Guard keys (بدون إضافة PAGES) | C21: — | D21: lesson.$id→student_schedule | enrolled-course.$id→student_my_courses | booking.$id→student_my_courses | book.$teacherId→student_my_courses | teacher.course.$id→teacher_courses | E21: WP-00 | F21: WP-S1,S2,S5,S6,T1 | G21: الصفحات الجديدة بالتنقّل: student_attendance, student_exam_results, student_progress, teacher_bookings فقط.
A22: C-18 | B22: مسارات (URLs) متفق عليها | C22: — | D22: /teacher/course/$id (id أو new) | /teacher/bookings | /book/$teacherId | /booking/$id | /lesson/$id | /enrolled-course/$id | /attendance | /exam-results | /progress | E22: WP-00 | F22: كل WP | G22: أسماء مفردة (course/booking/lesson) لتجنّب nesting مع my-courses/teacher.courses. أي اسم آخر عبر CR.
A23: C-19 | B23: Props لـ WalletBalancePanel | C23: components/wallet/wallet-balance-panel.tsx | D23: الحالية: { actionSlot? } — الإضافات اختيارية فقط | E23: WP-W1 | F23: WP-W2 (+ wallet.tsx) | G23: W2 لا يعدّل الملف؛ يبني لوحته داخل teacher.earnings.tsx.
A24: C-20 | B24: أنواع الردود المؤقتة | C24: integrations/backend/pending-json.ts | D24: PendingResponse = { id?: number } & Record<string, unknown> — كل رد غير موثّق بالـSwagger يُصدَّر باسمه المتفق عليه كـ alias لهذا النوع (// PENDING-JSON) | E24: WP-00 → WP-J | F24: كل Wave 1 | G24: الأسماء: StudentBookingDetail, StudentBookingPayment, StudentRescheduleRequest, StudentLessonDetail, StudentCourseDetail, StudentAttendanceRow, StudentExamResultRow, TeacherCourseDetail, GroupStudentRow, TeacherBookingRow, TeacherRescheduleRequestRow. لا تقرأ حقولًا منها قبل J (العمود «يعتمد على JSON؟»).
A25: C-21 | B25: enums.ts | C25: lib/enums.ts | D25: BookingStatus={Pending:1,Accepted:2,Rejected:3,Cancelled:4,Confirmed:5,Completed:6} · bookingStatusLabel(s,bi) · bookingStatusTone(s) · DeliveryType={InPerson:1,Online:2} · MeetingPlatform={Zoom:1,GoogleMeet:2,MicrosoftTeams:3,Other:4}(+label) · AttendanceStatus={Present:1,Absent:2,Late:3,Excused:4}(+label/tone) · DayOfWeek(+label) · type Bi=<T>(ar:T,en:T)=>T. RescheduleStatus يُضاف في J-02 (الأسماء غير موثّقة). | E25: WP-00 | F25: كل Wave 1
A26: C-22 | B26: op-result.ts | C26: integrations/backend/op-result.ts | D26: interface OperationResult {success:boolean; message?:string|null; returnId?:number|null} · assertOk(result, fallbackAr, fallbackEn): void | E26: WP-00 | F26: كل Wave 1
A29: سجل مفاتيح react-query (مصدرها lib/query-keys.ts — WP-00)
A30: المفتاح | B30: النوع | C30: المعاملات | D30: يستخدمه | E30: يُبطَل بعد
A31: student-dashboard | B31: موجود | C31: — | D31: dashboard | E31: إرسال/إلغاء حجز
A32: student-my-bookings | B32: موجود | C32: — | D32: كورساتي | E32: إرسال/قرار/إلغاء/إعادة جدولة/تقييم
A33: student-my-requests | B33: موجود | C33: status? | D33: كورساتي | E33: إرسال/قرار/إلغاء
A34: student-schedule | B34: موجود | C34: filter | D34: الجدول | E34: قرار/إلغاء/إعادة جدولة/إلغاء درس
A35: student-notifications | B35: موجود | C35: — | D35: الإشعارات | E35: —
A36: my-wallet / my-wallet-history | B36: موجود | C36: page | D36: المحفظة | E36: قبول حجز (خصم)/إلغاء (استرجاع)
A37: parent-children / parent-child-attendance / parent-child-exams | B37: موجود | C37: studentId | D37: تقرير ولي الأمر | E37: —
A38: backend-teacher-profile / backend-teacher-availability | B38: موجود | C38: teacherId | D38: صفحة المعلم + شاشة الحجز | E38: تقييم (profile)
A39: published-courses | B39: موجود | C39: — | D39: الكتالوج العام | E39: —
A40: student-booking | B40: جديد | C40: id | D40: booking.$id (WP-S2/S3/S4/W1) | E40: كل إجراء على الحجز
A41: student-booking-payment | B41: جديد | C41: bookingId | D41: booking-payment-card (W1) | E41: قرار المعلم/إلغاء
... A53: teacher-lessons | B53: جديد | C53: courseId,groupId | D53: lessons-tab (T4) | E53: إنشاء/تعديل/إلغاء درس + إعداد المجموعة

Sheet API_Map
A1: خريطة الـ API (Swagger ↔ الكود)
A2: المصدر: Swagger_UI.pdf. «جاهز» = توجد دالة بالكود (لم تُجرَّب على الباك اند الحي). «عينة مطلوبة»: Swagger لا يوثّق schema الرد → المستخدم يلصق JSON حقيقيًا ثم يضع «نعم» في «وصلت العينة».
A4: # | B4: Controller | C4: Method | D4: Path | E4: المعاملات / Body | F4: الرد الموثّق | G4: الدالة بالكود | H4: الملف | I4: حالة الربط | J4: يستخدمه | K4: عينة مطلوبة؟ | L4: وصلت العينة؟ | M4: ملاحظات
A5: 1 | B5: Booking | C5: POST | D5: /api/Booking/Submit | E5: body: teacherId, subjectId, gradeId, teachingMode(1|2), date, startTime, durationMinutes(مثال 480), studentNote | F5: OperationResult | G5: submitBooking | H5: bookings.ts | I5: يحتاج تصحيح | J5: WP-S1 | K5: لا | L5: — | M5: الرد موثّق (OperationResult) — المطلوب فقط تأكيد أن returnId = رقم الحجز الجديد (Q-21)؛ الكود القديم كان يتوقع BookingRow (D-01)
A6: 2 | B6: Booking | C6: POST | D6: /api/Booking/Decide | E6: body: bookingId, accept, rejectionReason | F6: OperationResult | G6: decideBooking | H6: bookings.ts | I6: يحتاج تصحيح | J6: WP-T5 | K6: لا | L6: — | M6: الكود يرسل approve بدل accept
A7: 3 | B7: Booking | C7: POST | D7: /api/Booking/Cancel | E7: query: bookingId, reason | F7: OperationResult | G7: cancelBooking | H7: bookings.ts | I7: يحتاج تصحيح | J7: (بديل) | K7: لا | L7: — | M7: الطالب يفضّل Student/CancelBooking
A8: 4 | B8: Booking | C8: POST | D8: /api/Booking/Complete | E8: query: bookingId | F8: OperationResult | G8: completeBooking | H8: bookings.ts | I8: يحتاج تصحيح | J8: WP-T5 | K8: لا | L8: —
A9: 5 | B9: Booking | C9: POST | D9: /api/Booking/Rate | E9: body: bookingId, ratingValue, review | F9: OperationResult | G9: rateBooking | H9: bookings.ts | I9: يحتاج تصحيح | J9: WP-S4 | K9: لا | L9: — | M9: الكود يرسل rating/comment
A10: 6 | B10: Booking | C10: GET | D10: /api/Booking/MyBookings | E10: — | F10: غير موثّق | G10: listMyBookings | H10: bookings.ts | I10: يحتاج تحقق | J10: — | K10: لا | L10: — | M10: لا تستخدمه أي مهمة بالخطة (الطالب يستخدم Student/MyBookings)؛ لا عينة مطلوبة
A11: 7 | B11: Booking | C11: GET | D11: /api/Booking/TeacherBookings | E11: query: status(1..6) | F11: غير موثّق | G11: listTeacherBookings | H11: bookings.ts | I11: يحتاج تصحيح | J11: WP-T5 | K11: نعم | L11: لا | M11: الكود يرسل اسم الحالة نصًا؛ المطلوب رقم
A12: 8 | B12: Booking | C12: GET | D12: /api/Booking/TeacherRescheduleRequests | E12: query: status(1..4) | F12: غير موثّق | G12: — | H12: bookings.ts | I12: ناقص | J12: WP-T5 | K12: نعم | L12: لا | M12: أسماء الحالات 1..4 غير موثّقة
A13: 9 | B13: Booking | C13: POST | D13: /api/Booking/DecideReschedule | E13: body: requestId, approve, rejectionReason | F13: OperationResult | G13: — | H13: bookings.ts | I13: ناقص | J13: WP-T5 | K13: لا | L13: —
A14: 10 | B14: Course | C14: POST | D14: /api/Course/GetPublished | E14: body: DataTable (searchValue, sortColumn, sortColumnDirection, pageSize, skip) | F14: غير موثّق (مربوط سابقًا) | G14: listPublishedCoursesPage | H14: courses.ts | I14: جاهز | J14: (عام) | K14: لا | L14: —
A15: 11 | B15: Course | C15: POST | D15: /api/Course/GetAll | E15: body: DataTable | F15: غير موثّق | G15: listAllCoursesForAdmin | H15: courses.ts | I15: يحتاج تحقق | J15: WP-T1 | K15: نعم | L15: لا | M15: هل يفلتر حسب المعلم؟ (Q-01)
A16: 12 | B16: Course | C16: GET | D16: /api/Course/GetById | E16: query: id | F16: غير موثّق | G16: getPublishedCourse | H16: courses.ts | I16: جاهز | J16: (عام) | K16: لا | L16: —
A17: 13 | B17: Course | C17: GET | D17: /api/Course/GetMineById | E17: query: id | F17: غير موثّق | G17: — | H17: courses.ts | I17: ناقص | J17: WP-T1, T2, T3, T4 | K17: نعم | L17: لا | M17: هل يرجع المجموعات/groupId؟ (Q-02)
A18: 14 | B18: Course | C18: GET | D18: /api/Course/GetGroupStudents | E18: query: groupId, keyword | F18: غير موثّق | G18: — | H18: courses.ts | I18: ناقص | J18: WP-T3 | K18: نعم | L18: لا | M18: الحقول المرجعة (اسم/هاتف/موقع؟)
A19: 15 | B19: Course | C19: POST | D19: /api/Course/CreateEdit | E19: body: id, teacherId, subjectId, categoryId, title, description, price, deliveryType(1|2), maxStudents, groupName, gradeId, saveAsDraft | F19: OperationResult | G19: — | H19: courses.ts | I19: ناقص | J19: WP-T1 | K19: لا | L19: — | M19: teacherId مطلوب بالـ DTO (Q-03)
A20: 16 | B20: Course | C20: POST | D20: /api/Course/ConfigureGroupSchedule | E20: body: groupId, maxStudents, courseStartDate, courseEndDate, defaultLessonDurationMinutes, scheduleDays[{dayOfWeek,startTime}] | F20: OperationResult | G20: — | H20: courses.ts | I20: ناقص | J20: WP-T2 | K20: لا | L20: —
A21: 17 | B21: Lesson | C21: POST | D21: /api/Lesson/Create | E21: body: id, groupId, courseId, title, scheduledDate, startTime, durationMinutes, orderIndex, meetingPlatform, meetingUrl, meetingInstructions, room | F21: OperationResult | G21: createLesson | H21: lessons.ts | I21: يحتاج تصحيح | J21: WP-T4 | K21: لا | L21: — | M21: الكود يتوقع LessonRow
A22: 18 | B22: Lesson | C22: PUT | D22: /api/Lesson/Update | E22: نفس Create | F22: OperationResult | G22: updateLesson | H22: lessons.ts | I22: يحتاج تصحيح | J22: WP-T4 | K22: لا | L22: —
A23: 19 | B23: Lesson | C23: PUT | D23: /api/Lesson/ConfigureMeeting | E23: body: lessonId, meetingPlatform, meetingUrl, meetingInstructions | F23: OperationResult | G23: configureLessonMeeting | H23: lessons.ts | I23: يحتاج تصحيح | J23: WP-T4 | K23: لا | L23: —
A24: 20 | B24: Lesson | C24: PUT | D24: /api/Lesson/Cancel | E24: body: lessonId, reason | F24: OperationResult | G24: cancelLesson | H24: lessons.ts | I24: يحتاج تصحيح | J24: WP-T4 | K24: لا | L24: —
A25: 21 | B25: Lesson | C25: GET | D25: /api/Lesson/GetSchedule | E25: query: courseId, groupId | F25: غير موثّق | G25: getLessonSchedule | H25: lessons.ts | I25: يحتاج تحقق | J25: WP-T4 | K25: نعم | L25: لا
A26: 22 | B26: Parent | C26: GET | D26: /api/Parent/MyChildren | E26: — | F26: غير موثّق (النوع بالكود) | G26: getMyChildren | H26: parent.ts | I26: جاهز | J26: WP-P1 | K26: لا | L26: — | M26: unreadNotificationsCount موجود بالنوع
A27: 23 | B27: Parent | C27: GET | D27: /api/Parent/ChildAttendance | E27: query: studentId, from, to | F27: غير موثّق | G27: getChildAttendance | H27: parent.ts | I27: جاهز | J27: WP-P1 | K27: لا | L27: —
A28: 24 | B28: Parent | C28: GET | D28: /api/Parent/ChildExamResults | E28: query: studentId | F28: غير موثّق | G28: getChildExamResults | H28: parent.ts | I28: جاهز | J28: WP-P1 | K28: لا | L28: —
A29: 25 | B29: Student | C29: GET | D29: /api/Student/Dashboard | E29: — | F29: غير موثّق (النوع بالكود) | G29: getStudentDashboard | H29: student.ts | I29: جاهز | J29: WP-S6 | K29: لا | L29: — | M29: activeCourses لـ WP-S6
A30: 26 | B30: Student | C30: GET | D30: /api/Student/MyRequests | E30: query: status(1..6) | F30: غير موثّق | G30: getStudentMyRequests | H30: student.ts | I30: جاهز | J30: WP-S2 | K30: لا | L30: —
A31: 27 | B31: Student | C31: GET | D31: /api/Student/GetBooking | E31: query: id | F31: غير موثّق | G31: — | H31: student.ts | I31: ناقص | J31: WP-S2, S3, S4 | K31: نعم | L31: لا | M31: هل يتضمن isRated/تفاصيل الدفع؟
A32: 28 | B32: Student | C32: GET | D32: /api/Student/MyBookings | E32: — | F32: غير موثّق | G32: getStudentMyBookings | H32: student.ts | I32: جاهز | J32: WP-S2 | K32: لا | L32: —
A33: 29 | B33: Student | C33: GET | D33: /api/Student/BookingPayment | E33: query: bookingId | F33: غير موثّق | G33: — | H33: student.ts | I33: ناقص | J33: WP-W1 | K33: نعم | L33: لا
A34: 30 | B34: Student | C34: POST | D34: /api/Student/CancelBooking | E34: body: bookingId, reason | F34: OperationResult | G34: — | H34: student.ts | I34: ناقص | J34: WP-S2 | K34: لا | L34: —
A35: 31 | B35: Student | C35: POST | D35: /api/Student/RequestReschedule | E35: body: bookingId, proposedDate, proposedStartTime, note | F35: OperationResult | G35: — | H35: student.ts | I35: ناقص | J35: WP-S3 | K35: لا | L35: —
A36: 32 | B36: Student | C36: GET | D36: /api/Student/MyRescheduleRequests | E36: — | F36: غير موثّق | G36: — | H36: student.ts | I36: ناقص | J36: WP-S3 | K36: نعم | L36: لا | M36: أسماء حالات الطلب
A37: 33 | B37: Student | C37: GET | D37: /api/Student/Schedule | E37: query: From, To, CourseId, TeacherId, Mode(1|2) | F37: غير موثّق (النوع بالكود) | G37: getStudentSchedule | H37: student.ts | I37: جاهز | J37: WP-S5 | K37: لا | L37: —
A38: 34 | B38: Student | C38: GET | D38: /api/Student/GetLesson | E38: query: id | F38: غير موثّق | G38: — | H38: student.ts | I38: ناقص | J38: WP-S5 | K38: نعم | L38: لا
A39: 35 | B39: Student | C39: GET | D39: /api/Student/GetCourse | E39: query: id | F39: غير موثّق | G39: — | H39: student.ts | I39: ناقص | J39: WP-S6 | K39: نعم | L39: لا
A40: 36 | B40: Student | C40: GET | D40: /api/Student/Attendance | E40: query: from, to, courseId | F40: غير موثّق | G40: — | H40: student.ts | I40: ناقص | J40: WP-S7 | K40: نعم | L40: لا
A41: 37 | B41: Student | C41: GET | D41: /api/Student/ExamResults | E41: query: courseId | F41: غير موثّق | G41: — | H41: student.ts | I41: ناقص | J41: WP-S8 | K41: نعم | L41: لا
A42: 38 | B42: Student | C42: GET | D42: /api/Student/Progress | E42: — | F42: غير موثّق (StudentProgressDto بالكود) | G42: — | H42: student.ts | I42: ناقص | J42: WP-S9, S7 | K42: لا | L42: — | M42: النوع موجود بالكود فقط
A43: 39 | B43: Student | C43: GET | D43: /api/Student/Notifications | E43: query: unreadOnly, skip, pageSize | F43: غير موثّق | G43: getStudentNotifications | H43: student.ts | I43: جاهز | J43: (FR-S12) | K43: لا | L43: —
A44: 40 | B44: Student | C44: POST | D44: /api/Student/MarkNotificationRead | E44: query: id | F44: OperationResult | G44: markStudentNotificationRead | H44: student.ts | I44: جاهز | J44: (FR-S12) | K44: لا | L44: —
A45: 41 | B45: Teacher | C45: POST | D45: /api/Teacher/Search | E45: body: TeacherSearchFilterDto | F45: غير موثّق | G45: searchTeachers | H45: teachers.ts | I45: جاهز | J45: (عام) | K45: لا | L45: —
A46: 42 | B46: Teacher | C46: GET | D46: /api/Teacher/PublicProfile | E46: query: id | F46: غير موثّق | G46: getTeacherPublicProfile | H46: teachers.ts | I46: جاهز | J46: WP-S1 | K46: لا | L46: — | M46: الأسماء فقط للمواد/الصفوف (بدون IDs)
A47: 43 | B47: Teacher | C47: GET | D47: /api/Teacher/Availability | E47: query: teacherId, mode, date | F47: غير موثّق | G47: getTeacherAvailability | H47: teachers.ts | I47: جاهز | J47: WP-S1 | K47: لا | L47: —
A48: 44 | B48: Teacher | C48: POST | D48: /api/Teacher/SetAvailability | E48: body: slots[...] | F48: OperationResult | G48: setMyTeacherAvailability | H48: teachers.ts | I48: جاهز | J48: (FR-T09) | K48: لا | L48: —
A49: 45 | B49: Teacher | C49: POST | D49: /api/Teacher/UpdateProfile | E49: body: TeacherProfileInputDto | F49: OperationResult | G49: updateMyTeacherProfile | H49: teachers.ts | I49: جاهز | J49: (FR-T08) | K49: لا | L49: —
A50: 46 | B50: Teacher | C50: GET | D50: /api/Teacher/CreateEditModal | E50: query: id | F50: غير موثّق | G50: getGradesList | H50: teachers.ts | I50: يحتاج تحقق | J50: WP-T1, S1 | K50: نعم | L50: لا | M50: مصدر محتمل للصفوف والمواد (Q-04)
A51: 47 | B51: Constant | C51: POST | D51: /api/Constant/GetAll | E51: body: DataTable | F51: غير موثّق | G51: (admin-constants.ts) | H51: admin-constants.ts | I51: يحتاج تحقق | J51: WP-T1, S1 | K51: نعم | L51: لا | M51: مصدر محتمل لـ subjectId/categoryId (Q-04)
A52: 48 | B52: Wallet | C52: GET | D52: /api/Wallet/MyWallet | E52: — | F52: غير موثّق (النوع بالكود) | G52: getMyWallet | H52: wallet.ts | I52: جاهز | J52: WP-S1 | K52: لا | L52: —
A53: 49 | B53: Wallet | C53: POST | D53: /api/Wallet/GetTransactionHistory | E53: body: DataTable | F53: غير موثّق | G53: getTransactionHistory | H53: wallet.ts | I53: جاهز | J53: WP-W1, W2 | K53: لا | L53: — | M53: بلا فلتر نوع من الباك اند
A54: 50 | B54: Wallet | C54: POST | D54: /api/Wallet/SubmitTopUpRequest | E54: form: Amount, BankReferenceNo, ReceiptFile | F54: OperationResult | G54: submitTopUpRequest | H54: wallet.ts | I54: جاهز | J54: (FR-W01) | K54: لا | L54: —
A55: 51 | B55: Wallet | C55: POST | D55: /api/Wallet/SubmitWithdrawalRequest | E55: body: amount, bankIBAN, bankName, accountHolderName | F55: OperationResult | G55: submitWithdrawalRequest | H55: wallet.ts | I55: جاهز | J55: (FR-W04) | K55: لا | L55: —
A56: 52 | B56: Wallet | C56: * | D56: /api/Wallet/{GetPending*,VerifyTopUpRequest,DecideWithdrawalRequest,CompleteWithdrawal,GetReceiptImage} | E56: أدمن | F56: — | G56: (wallet.ts) | H56: wallet.ts | I56: جاهز | J56: (أدمن) | K56: لا | L56: — | M56: خارج النطاق
A57: 53 | B57: Auth/User/UserPermission/Page | C57: * | D57: /api/Auth/*, /api/User/*, /api/UserPermission/*, /api/Page/* | E57: — | F57: — | G57: — | H57: — | I57: خارج النطاق | J57: — | K57: لا | L57: — | M57: لم تُفحص ضمن هذه الخطة

Sheet Discrepancies
A1: فروقات Swagger ↔ الكود الحالي
A2: تُغلق فروقات WP-00 قبل بدء Wave 1.
A4: ID | B4: الملف | C4: المشكلة | D4: الإصلاح | E4: WP / المهمة | F4: الخطورة | G4: الحالة | H4: ملاحظات
A5: D-01 | B5: bookings.ts | C5: submitBooking: الكود يرسل {teacherId, courseId, date, startTime, durationMinutes} ويتوقع BookingRow؛ Swagger: {teacherId, subjectId, gradeId, teachingMode, date, startTime, durationMinutes, studentNote} والرد OperationResult | D5: إعادة تعريف BookingInput وقيمة الإرجاع | E5: WP-00 (00-01) | F5: حرج | G5: مفتوح
A6: D-02 | B6: bookings.ts | C6: decideBooking يرسل approve؛ Swagger الحقل accept | D6: تغيير اسم الحقل | E6: WP-00 (00-01) | F6: حرج | G6: مفتوح
A7: D-03 | B7: bookings.ts | C7: rateBooking يرسل rating/comment؛ Swagger ratingValue/review | D7: تغيير الحقول | E7: WP-00 (00-01) | F7: حرج | G7: مفتوح
A8: D-04 | B8: bookings.ts | C8: cancelBooking لا يمرّر reason (query) ويتوقع BookingRow؛ كما يوجد Student/CancelBooking (body) غير مربوط | D8: تمرير reason + اعتماد Student/CancelBooking في واجهة الطالب | E8: WP-00 / WP-S2 | F8: مهم | G8: مفتوح
A9: D-05 | B9: bookings.ts | C9: listTeacherBookings يرسل status كنص (Pending..)؛ Swagger رقم 1..6. وBookingStatus نصي هنا بينما رقمي بـ student.ts | D9: توحيد على الأرقام عبر enums.ts | E9: WP-00 (00-01, 00-07) | F9: حرج | G9: مفتوح
A10: D-06 | B10: lessons.ts | C10: كل الدوال تتوقع LessonRow؛ Swagger يرجع OperationResult | D10: تغيير الإرجاع + assertOk | E10: WP-00 (00-03) | F10: مهم | G10: مفتوح
A11: D-07 | B11: courses.ts | C11: لا توجد دوال: CreateEdit, ConfigureGroupSchedule, GetGroupStudents, GetMineById | D11: إضافتها | E11: WP-00 (00-04) | F11: حرج | G11: مفتوح
A12: D-08 | B12: student.ts | C12: غير موجودة: GetBooking, BookingPayment, CancelBooking, RequestReschedule, MyRescheduleRequests, GetLesson, GetCourse, Attendance, ExamResults, Progress | D12: إضافتها | E12: WP-00 (00-05) | F12: حرج | G12: مفتوح
A13: D-09 | B13: bookings.ts | C13: غير موجودة: TeacherRescheduleRequests, DecideReschedule | D13: إضافتها | E13: WP-00 (00-02) | F13: مهم | G13: مفتوح
A14: D-10 | B14: student.ts + lessons.ts | C14: MeetingPlatform معرّف مرتين | D14: توحيده بـ enums.ts | E14: WP-00 (00-07) | F14: منخفض | G14: مفتوح
A15: D-11 | B15: teacher.dashboard.tsx | C15: لوحة «طلبات الحجز» معطّلة بنص يشير لـ P0-1/P1-1 — قد لا يكون صحيحًا الآن بعد تحديث الباك اند | D15: التحقق ثم الاستبدال | E15: WP-T5 (T5-05) | F15: مهم | G15: مفتوح
A16: D-12 | B16: teacher.courses.tsx | C16: placeholder «قيد التطوير» بنص P1-1/P1-3 قديم | D16: استبدال | E16: WP-T1 (T1-01) | F16: مهم | G16: مفتوح
... A21: D-17 | B21: audit report | C21: جدول التقرير يحوي 11 جاهز/5 جزئي بالأسطر وملخصه 11/6/13: صُنِّف FR-P08 جزئيًا لمطابقة الملخص | D21: تأكيد من المستخدم (Q-18) | E21: — | F21: معلومة | G21: مفتوح

Sheet OpenQuestions
A1: الأسئلة المفتوحة (تحتاج إجابة قبل/أثناء التنفيذ)
A2: «حاجب» = يوقف WPs معيّنة. «الافتراض الافتراضي» = ما يعمل به المطوّر لحين الإجابة. عند الإجابة: غيّر الحالة وسجّل الإجابة وحدّث المتأثرين.
A4: ID | B4: السؤال | C4: لماذا يهم | D4: يؤثر على | E4: الخطورة | F4: الافتراض الافتراضي | G4: من يجيب | H4: الحالة | I4: الإجابة | J4: تاريخ الإجابة
A5: Q-01 | B5: كيف يحصل المعلم على قائمة كورساته؟ هل Course/GetAll يفلتر حسب المعلم المسجَّل أم يرجع كل الكورسات؟ | C5: بدونه لا تصح قائمة كورساتي (قد تُعرض كورسات معلمين آخرين) | D5: WP-T1 | E5: حاجب | F5: نستدعي GetAll ونفلتر محليًا بـ teacherId إذا توفر؛ وإلا نوقف المهمة | G5: فريق الباك اند | H5: مفتوح
A6: Q-02 | B6: كيف نعرف groupId لكل كورس؟ ما شكل رد GetById/GetMineById؟ هل للكورس أكثر من مجموعة؟ | C6: ConfigureGroupSchedule وGetGroupStudents وGetSchedule تحتاج groupId | D6: WP-T1, T2, T3, T4 | E6: حاجب | F6: نفترض مجموعة واحدة ويُقرأ groupId من رد GetMineById | G6: فريق الباك اند | H6: مفتوح
A7: Q-03 | B7: هل Course/CreateEdit يأخذ teacherId من الجلسة أم يجب أن نرسله؟ وكيف يعرف المعلم رقم Teacher.Id الخاص به؟ (هل حُلّ ربط الحساب بالمعلم؟) | C7: الـDTO يتطلب teacherId | D7: WP-T1 | E7: حاجب | F7: لا نرسل teacherId إن كان الباك اند يتجاهله؛ نختبر بحساب معلم حقيقي | G7: فريق الباك اند | H7: مفتوح
A8: Q-04 | B8: من أين نجلب قوائم المواد/التصنيفات/الصفوف (IDs)؟ Teacher/CreateEditModal أم Constant/GetAll (وبأي parentId)؟ وهل ملف المعلم العام يرجّع IDs للمواد والصفوف؟ | C8: نموذج الكورس ونموذج الحجز يتطلبان subjectId/gradeId/categoryId | D8: WP-T1, S1 | E8: حاجب | F8: نقرأ من Teacher/CreateEditModal ونعرض رسالة صادقة إن كانت القوائم فارغة | G8: فريق الباك اند | H8: مفتوح
A9: Q-05 | B9: عينات JSON حقيقية لردود: Booking/MyBookings, TeacherBookings, TeacherRescheduleRequests · Student/GetBooking, GetLesson, GetCourse, Attendance, ExamResults, BookingPayment, MyRescheduleRequests · Course/GetGroupStudents, GetMineById, GetAll · Lesson/GetSchedule | C9: Swagger لا يوثّق schema لهذه الردود؛ الأنواع ستكون تخمينًا | D9: WP-00 + أغلب Wave 1 | E9: حاجب | F9: أنواع متساهلة (حقول اختيارية) مع علامة TODO | G9: المستخدم (من Try it out) | H9: مفتوح
A10: Q-06 | B10: متى يُخصم مبلغ الحجز بالضبط؟ عند قبول المعلم (كما في تعليق الكود وSRS FR-T06) أم عند الإرسال؟ وماذا يحدث لو رصيد الطالب غير كافٍ عند القبول؟ | C10: يحدد نص الواجهة ومنطق تنبيه الرصيد | D10: WP-S1, S2, T5, W1 | E10: مهم | F10: نفترض الخصم عند قبول المعلم | G10: فريق الباك اند | H10: مفتوح
A11: Q-07 | B11: من يحق له Booking/Submit: الطالب فقط أم ولي الأمر أيضًا (باسم الابن)؟ | C11: يحدد من يرى زر الحجز | D11: WP-S1 | E11: مهم | F11: الطالب فقط | G11: صاحب المنتج | H11: مفتوح
A12: Q-08 | B12: سياسة الإلغاء: هل يرجع الباك اند الموعد النهائي/نص السياسة أم رسالة خطأ فقط؟ وهل يوجد استرجاع للمبلغ؟ | C12: FR-S14 يطلب عرض السياسة عند الرفض | D12: WP-S2 | E12: مهم | F12: نعرض رسالة الباك اند كما هي | G12: فريق الباك اند | H12: مفتوح
A13: Q-09 | B13: قواعد أهلية إعادة الجدولة (الحالات المسموحة، المهلة، عدد المرات)؟ | C13: منطق إظهار الزر | D13: WP-S3 | E13: مهم | F13: Confirmed ولم يبدأ فقط | G13: فريق الباك اند | H13: مفتوح
A14: Q-10 | B14: هل Student/GetBooking يرجع حقلًا يدل أن الحجز مُقيَّم سابقًا (isRated/rating)؟ | C14: لإخفاء زر التقييم | D14: WP-S4 | E14: عادي | F14: نُظهر الزر لـ Completed ونعرض رسالة الباك اند عند التكرار | G14: فريق الباك اند | H14: مفتوح
A15: Q-11 | B15: عدد الإشعارات غير المقروءة بـ Parent/MyChildren: هل هو لكل ابن أم لحساب ولي الأمر؟ وهل يوجد endpoint لقائمة إشعارات ولي الأمر؟ (غير موجود بـ Swagger) | C15: SRS FR-P11 يطلب عدد إشعارات حساب ولي الأمر | D15: WP-P1 | E15: مهم | F15: نعرض عدد الابن النشط + إجمالي الأبناء بتسمية واضحة | G15: فريق الباك اند | H15: مفتوح
A16: Q-12 | B16: هل يوجد endpoint/حقل لنسبة العمولة أو ملخص الأرباح؟ (غير موجود بـ Swagger) | C16: FR-W03b: عرض صافي الإيداع | D16: WP-W2 | E16: عادي | F16: لا نعرض أرقام عمولة؛ نص توضيحي فقط | G16: فريق الباك اند | H16: مفتوح
... A23: Q-21 | B23: هل Booking/Submit يرجّع returnId = رقم الحجز الجديد؟ (للانتقال إلى /booking/{id} بعد الإرسال) | C23: تصميم S1-05 | D23: WP-S1 | E23: مهم | F23: نفترض نعم؛ وإلا ننتقل لـ/my-courses | G23: فريق الباك اند | H23: مفتوح

Sheet Assumptions_Risks
A1: الافتراضات والمخاطر
A4: ID | B4: النوع | C4: الوصف | D4: الأثر | E4: التخفيف / الإجراء
A5: R-01 | B5: خطر | C5: بيئة التنفيذ هنا بلا اتصال شبكة: لا npm install ولا تشغيل typecheck/lint/vitest/dev server | D5: لا يمكن إثبات سلامة الكود تلقائيًا بالجلسة | E5: كل جلسة كود تنتهي بأمر يشغّله المستخدم محليًا: npm run validate، وتُسجَّل نتيجته بـ SessionLog قبل اعتبار المهمة «مكتملة»
A6: R-02 | B6: خطر | C6: عدم وجود schema لردود كثيرة (D-15/Q-05) | D6: أنواع تخمينية قد تنكسر | E6: أنواع بحقول اختيارية + قراءة دفاعية + استبدالها فور استلام العينات
A7: R-03 | B7: خطر | C7: تعارض في routeTree.gen.ts عند الدمج المتوازي | D7: يعطّل البناء | E7: كل routes تُنشأ كـ stubs في WP-00 فيُولَّد مرة واحدة؛ عند التعارض: احذف وأعد التوليد
A8: R-04 | B8: خطر | C8: تعديل ملف تعاوني من جلستين | D8: تعارضات دمج | E8: FileOwnership + عمود ⚠ مكرر + طلبات التغيير
A9: R-05 | B9: خطر | C9: تعارض تحديث ملف الإكسل نفسه من جلسات متوازية | D9: فقدان تحديثات | E9: كاتب واحد للتتبع (المنسّق). الجلسات ترسل «تقريرًا» بصيغة SessionLog فقط
A10: R-06 | B10: افتراض | C10: ملفات docs/** و.claude/** المذكورة بـ CLAUDE.md/ATLAS غير موجودة بالـ zip، وهي قديمة بحسب المستخدم | D10: لا اعتماد عليها | E10: المصادر المعتمدة: Swagger + SRS + تقرير الجاهزية + هذا الملف
A11: R-07 | B11: افتراض | C11: «جاهز» بـ API_Map يعني وجود دالة بالكود وليس تجربتها فعليًا على الباك اند الحي | D11: قد تظهر فروقات وقت التشغيل | E11: تأكيد بالـ UAT
A12: R-08 | B12: خطر | C12: القائمة الجانبية تحدد الوحدة النشطة بـ startsWith على مسارات PAGES | D12: صفحات التفاصيل لا تفتح مجموعتها | E12: مهمة اختيارية 00-19
A13: R-09 | B13: خطر | C13: روابط الاجتماع قد تُحقن بـ javascript: | D13: ثغرة XSS | E13: isHttpUrl إلزامي بكل عرض/إدخال رابط (T4, S5) + مراجعة QA-09
A14: R-10 | B14: افتراض | C14: القاعدة الحاكمة بـ CLAUDE.md (Truth Rule): لا تُظهر الواجهة نشاطًا غير حقيقي | D14: يؤثر على W2/P1 | E14: حالات فراغ صادقة ولا أرقام مخترعة
A15: R-11 | B15: افتراض | C15: التطبيق يستخدم TanStack Start (file-based routing) ومكوّنات shadcn/radix بدون Tabs وبدون date-picker | D15: تصميم الواجهات | E15: SegmentedTabs جديد + input type=date/time الأصلي
... A21: R-17 | B21: خطر | C21: فحص Claude = tsc مع stubs للمكتبات الخارجية + تشغيل اختبارات النقي (102 فحصًا نجح): تقريبي لا يغني عن validate/lint/prettier | D21: أخطاء أنواع/تنسيق قد تظهر محليًا | E21: npm run format && npm run validate قبل اعتماد أي مهمة

Sheet ChangeRequests
A1: طلبات التغيير على الملفات/العقود المشتركة (CR)
A2: إذا احتاج WP تعديل ملف لا يملكه أو تغيير توقيع في Contracts: يضيف صفًا هنا ولا يعدّل الملف. المنسّق يقرر. الصف الأول مثال توضيحي (حالته «مثال» ولا يُحسب).
A4: CR | B4: التاريخ | C4: WP الطالب | D4: الملف / العقد | E4: التغيير المطلوب | F4: السبب | G4: الحالة | H4: قرار/تاريخ | I4: ملاحظات
A5: CR-000 | B5: 2026-10-01 | C5: WP-W2 (مثال) | D5: components/wallet/wallet-balance-panel.tsx | E5: إضافة prop اختيارية highlightTypes?: number[] | F5: لإبراز حركات الأرباح بلا تكرار الكود | G5: مثال | H5: — | I5: احذف هذا الصف عند أول CR حقيقي
A6: CR-001
A7: CR-002
A8: CR-003
A9: CR-004
A10: CR-005
A11: CR-006
A12: CR-007
A13: CR-008
A14: CR-009
A15: CR-010
A16: CR-011
A17: CR-012
... A40: CR-035

Sheet SessionLog
A1: سجل الجلسات (Append-only)
A2: لا تحذف صفوفًا قديمة. كل تقرير جلسة يُضاف كصف جديد بالصيغة الموحّدة (انظر README).
A4: # | B4: التاريخ | C4: الجلسة/Run | D4: WP | E4: المنفّذ | F4: الملخص | G4: المهام (ID: الحالة) | H4: الملفات المعدّلة | I4: نتيجة npm run validate | J4: افتراضات/أسئلة جديدة | K4: CRs | L4: الخطوة التالية | M4: نسخة التتبع بعدها
A5: 1 | B5: 2026-10-01 | C5: Session-0 (تخطيط) | D5: — | E5: Claude (المنسّق) | F5: قراءة SRS + تقرير الجاهزية + Swagger + zip الفرونت؛ بناء ملف التتبع هذا. لم تُكتب أي أسطر كود. | G5: — | H5: — | I5: غير منفَّذ (لا شبكة بالبيئة) | J5: R-01..R-12, Q-01..Q-19, D-01..D-17 | K5: — | L5: 1) المستخدم يجيب Q حاجبة ويلصق عينات JSON (Q-05). 2) تشغيل WP-00 (جلسة واحدة). 3) إطلاق Wave 1 بالتوازي. | M5: v1.0
A6: 2 | B6: 2026-10-01 | C6: Session-0b (تخطيط) | D6: WP-00 | E6: Claude (المنسّق) | F6: قرار: Claude ينفّذ WP-00 كاملًا بلا JSON؛ عزل المعتمد على JSON في WP-J؛ إضافة عمودي «يعتمد على JSON؟» و«بوابة البدء» وورقة Availability؛ ترشيح WP-P1 وWP-W2 للبدء الآن. | G6: — | H6: Tasks, WorkPackages, Contracts, Availability (لا كود) | I6: غير منفَّذ | J6: — | K6: — | L6: Claude يبدأ WP-00؛ المستخدم يبدأ WP-P1/WP-W2 | M6: v1.7
A7: 3 | B7: 2026-10-01 | C7: WP-00 (تنفيذ) | D7: WP-00 | E7: Claude | F7: تسليم WP-00: 17 مهمة منفّذة (طبقة API + enums/format/query-keys/booking-rules + UI مشتركة + 9 route stubs + مكونات stubs + my-courses لوحات + sidebar). لا يوجد JSON مخمَّن: كل رد غير موثّق = PendingResponse. | G7: 00-01..00-16, 00-19, 00-21: قيد المراجعة | 00-17: قيد التنفيذ (المستخدم) | 00-20: لم يبدأ | H7: wp-00-files.zip (49 ملفًا) | I7: غير منفَّذ (لا شبكة) — بانتظار 00-17 | J7: Q-15 افتراض: السبت أول الأسبوع | K7: — | L7: المستخدم: 00-17. ثم بدء مهام Wave 1 من الفئة A/B (انظر Availability). | M7: v1.7
A8: 4 | B8: 2026-10-01 | C8: A-user (P1+W2) | D8: WP-P1, WP-W2 | E8: المستخدم | F8: تسليم WP-P1 (7/7) وWP-W2 (4/4): تقرير ولي الأمر (إشعارات/403/حالة الحضور/قراءة فقط)، إعدادات ولي الأمر، أرباح المعلم (آخر 50 إيداعًا + نص العمولة + مراحل السحب). فحصتُ أنواع الملفات بـtsc مع stubs للمكتبات الخارجية: لا أخطاء حقيقية. | G8: P1-01..P1-07, W2-01..W2-04: قيد المراجعة | H8: parent.report.tsx, parent.settings.tsx, teacher.earnings.tsx, lib/parent-report.ts, lib/earnings.ts, lib/query-keys.ts (+qk.teacherEarningsCredits), test-units/* | I8: غير منفَّذ (لا شبكة) — بانتظار المستخدم | J8: — | K8: — | L8: المستخدم: 17 مهمة (T/W1/S9). Claude: 19 مهمة (S1..S8). | M8: v1.7
A9: 5 | B9: 2026-10-01 | C9: A-claude + A-user (Phase A) | D9: S1..S8, T1/T2/T4/T5, W1, S9 | E9: Claude + المستخدم | F9: تسليم Phase A: 36 مهمة (17 للمستخدم + 19 لـClaude). فحص نصف المستخدم بـtsc/اختبارات: لا أخطاء حقيقية (27 اختبارًا نجح). نصف Claude: 23 ملفًا (نوافذ إلغاء/إعادة جدولة/تقييم، لوحات كورساتي، الجدول بفلاتر وانضمام آمن، بطاقة الحضور، شاشة الحجز). | G9: 36 مهمة: قيد المراجعة (كل مهام Phase A) | H9: wave1-claude-half-files.zip + wave1-half-claude-files.zip | I9: غير منفَّذ (لا شبكة) — بانتظار المستخدم | J9: R-14..R-17 | K9: — | L9: المستخدم: npm run dev → format → validate ثم commit. بعدها J (عينات JSON) لفتح مهام C. | M9: v1.7
A10: 6 | B10: 2026-10-01 | C10: تخطيط (Phase B/C) | D10: — | E10: Claude (المنسّق) | F10: إعادة تصنيف 6 مهام من B إلى C (ما بقي فيها جوهر بلا JSON)؛ إضافة ورقة BackendChecklist (13 عنصرًا) وعمودي «ينتظر (NE)» و«حالة الاعتماد» بـTasks؛ إضافة Q-20 وQ-21. | G10: — | H10: هذا الملف فقط (لا كود) | I10: — | J10: Q-20, Q-21 | K10: — | L10: تعبئة BackendChecklist عند وصول العينات؛ بدء مهام B الـ11 (seam) إن رغبت. | M10: v1.7
A11: 7 | B11: 2026-10-01 | C11: تخطيط (Backend) | D11: — | E11: Claude (المنسّق) | F11: تصحيح عدد العينات المطلوبة من 17 إلى 15 (Booking/Submit له رد موثّق، وBooking/MyBookings لا تستخدمه أي مهمة)؛ إضافة NE-14 (تحقق اختياري من أنواع موجودة). | G11: — | H11: هذا الملف فقط | I11: — | J11: — | K11: — | L11: إرسال BackendChecklist لفريق الباك اند. | M11: v1.7
A12: 8
A13: 9
A14: 10
A15: 11
A16: 12
A17: 13
A18: 14
A19: 15
A20: 16
A21: 17
A22: 18
A23: 19
... A59: 55

Sheet Conventions
A1: قواعد العمل المتوازي (اقرأها قبل أي جلسة)
A3: القاعدة | B3: التفاصيل
A4: ملكية الملفات | B4: لا تعدّل أي ملف خارج ما يملكه WP الخاص بك (ورقة FileOwnership). الملفات المجمّدة ممنوعة. الحاجة لتعديل ملف غيرك → صف في ChangeRequests ثم انتظر الموافقة.
A5: ترتيب العمل | B5: Wave 0 (WP-00) يُدمج أولًا. ثم Wave 1 بالتوازي. ثم WP-QA. لا يبدأ أي WP من Wave 1 قبل إغلاق Wave 0.
A6: routeTree.gen.ts | B6: ملف تلقائي. لا تعدّله ولا تضعه في PR الخاص بك. إن ظهر فرق محلي بعد dev server فتجاهله (git checkout).
A7: الصلاحيات (Guard) | B7: لا تضف مفاتيح PAGES جديدة. أعد استخدام المفاتيح المذكورة في Contracts C-17.
A8: النصوص واللغات | B8: bi("عربي","English") داخل المكوّنات. لا تعدّل ملفات i18n JSON. الواجهة RTL: استخدم الخصائص المنطقية (ms-/me-/start-/end-).
A9: القاعدة الحاكمة (Truth Rule) | B9: لا بيانات وهمية ولا أرقام مخترعة. إن لم يوفّر الباك اند الحقل → حالة فراغ/«—» صادقة.
A10: نتائج العمليات | B10: كل POST/PUT يرجع OperationResult: استدعِ assertOk(result,…) وأظهر message القادمة من الباك اند عبر getErrorMessage.
A11: الأنواع الرقمية | B11: الحالات والأنواع أرقام (BookingStatus 1..6، DeliveryType 1|2، MeetingPlatform 1..4…). لا نصوص. استخدم lib/enums.ts.
A12: هيكل الصفحة | B12: AppPage + Panel + EmptyState/LoadingState/ErrorState (+RetryButton) + authPageHead(...) كما بالصفحات الحالية. كل صفحة: تحميل/خطأ/فراغ.
A13: react-query | B13: المفاتيح من lib/query-keys.ts فقط. بعد أي mutation للحجز: invalidateBookingQueries.
A14: الاعتماديات | B14: ممنوع إضافة npm packages أو تعديل package.json.
... A21: أسماء الملفات الجديدة | B21: أي ملف جديد يُسجَّل في FileOwnership قبل/عند التسليم. الأسماء المحجوزة لـClaude (A-claude) مذكورة بالورقة؛ لا تُنشئ ملفًا بنفس الاسم. المنطق النقي القابل للاختبار يوضع في src/lib/ واختباراته في src/test-units/.

Sheet Lists
A1: الحالة | B1: الأولوية | C1: الحجم | D1: نعم/لا | E1: حالة السؤال | F1: الخطورة | G1: نتيجة UAT | H1: حالة الفرق | I1: حالة CR | J1: WP | K1: الدمج
A2: لم يبدأ | B2: P0 | C2: S | D2: نعم | E2: مفتوح | F2: حاجب | G2: لم يُختبر | H2: مفتوح | I2: مفتوح | J2: WP-00 | K2: لا
A3: قيد التنفيذ | B3: P1 | C3: M | D3: لا | E3: تمت الإجابة | F3: مهم | G3: نجح | H3: قيد الإصلاح | I3: موافق عليه | J3: WP-J | K3: نعم
A4: قيد المراجعة | B4: P2 | C4: L | F4: عادي | G4: فشل | H4: مُصلَح | I4: مرفوض | J4: WP-T1
A5: متوقف | I5: منفّذ | J5: WP-T2
A6: مكتمل | J6: WP-T3
A7: مؤجل | J7: WP-T4
J8: WP-T5
J9: WP-S1
J10: WP-S2
J11: WP-S3
A12: هذه الورقة تغذّي القوائم المنسدلة. لا تحذف أعمدتها. | J12: WP-S4
J13: WP-S5
J14: WP-S6
J15: WP-S7
J16: WP-S8
J17: WP-S9
J18: WP-P1
J19: WP-W1
J20: WP-W2
J21: WP-QA

Sheet 00_Executive_Summary
A1: البند | B1: الإجابة
A2: مصدر التحليل | B2: Frontend_Completion_Tracker.xlsx + Acadimia-main.zip
A3: نطاق التحليل | B3: مطابقة كل FR وAPI والأسئلة المفتوحة والفروقات وقائمة BackendChecklist مع كود الـBackend الفعلي.
A4: النتيجة الأساسية | B4: الـBackend يغطي مسارات الحجز، الدفع، المحفظة، الكورسات والمجموعات والدروس، الطالب، ولي الأمر، المعلم، التقييم وإعادة الجدولة. معظم البنود غير الجاهزة في التقرير هي فجوات Frontend أو توثيق/عينات JSON.
A5: مهم جدًا | B5: وجود endpoint/DTO في الكود لا يعني أنه مجرّب Runtime أو موثّق في Swagger. لذلك تم فصل: Backend Implemented / Runtime or JSON Unverified / Frontend Gap.
A6: حالة FR | B6: تم الإبقاء على حالة Frontend كما هي في الـExcel، وإضافة حكم Backend مستقل حتى لا تختلط جاهزية الواجهة مع جاهزية الباك اند.
A7: أسئلة حاجبة حُسمت من الكود | B7: Q-01، Q-03 جزئيًا، Q-06، Q-07 جزئيًا، Q-08، Q-09، Q-10، Q-11، Q-12 جزئيًا، Q-14، Q-18، Q-19، Q-21.
A8: أسئلة لا يمكن حسمها من ملفات الكود وحدها | B8: Q-05 عينات JSON فعلية، Q-17 حسابات اختبار حية، Q-15 ترتيب العرض (قرار UX)، Q-20 بعض الحدود غير المعرّفة صراحةً.
A9: تناقض مهم في Excel | B9: FR-P11: الكود يوفر unreadNotificationsCount لولي الأمر لكنه لا يوفر endpoint لعرض قائمة إشعارات ولي الأمر؛ لذلك Backend = جزئي.
A10: تناقض مهم في Excel | B10: Q-19: توجد JoinRequestController/JoinRequestService فعليًا، مع خصم من محفظة الطالب وتحويل صافي للمعلم بعد العمولة عند القبول؛ لذا عبارة «لا توجد endpoints انضمام» أصبحت قديمة بالنسبة للكود المرفق.
A11: تناقض مهم في Excel | B11: API Map يصف عدة endpoints بأنها ناقصة لأن دوال Frontend غير موجودة، بينما الـController/Service/DTO موجودة في Backend. التقرير الجديد يوضح الفرق.
A12: التوصية | B12: استخدم ورقة 07_Frontend_Action_Plan كقائمة عمل لمطور الـFrontend، وورقة 03_OpenQuestions_Answers كقائمة ما يجب تأكيده/اختباره مع فريق الـBackend.

Sheet 01_FR_Backend_Analysis
A1: FR | B1: اسم FR | C1: حالة التقرير الأصلية | D1: حالة Frontend الحالية | E1: حكم Backend | F1: Endpoint/المسار | G1: دليل الكود | H1: التفسير | I1: WP | J1: ملاحظات Excel
A2: FR-I02 | B2: إعداد مجموعة طلاب حضورية | C2: غير جاهز | D2: قيد التنفيذ | E2: مدعوم بالكامل | F2: Course/ConfigureGroupSchedule | G2: CourseController.ConfigureGroupSchedule + GroupScheduleInputDto | H2: يدعم groupId, maxStudents, start/end dates, duration, scheduleDays. | I2: WP-T2
A3: FR-I03 | B3: عرض طلاب المجموعة | C3: غير جاهز | D3: لم يبدأ | E3: مدعوم بالكامل | F3: Course/GetGroupStudents | G3: CourseController.GetGroupStudents + CourseService.GetGroupStudentsAsync | H3: يطبق ownership على المجموعة ويعيد StudentGroupRosterDto. | I3: WP-T3
A4: FR-I04 | B4: إنشاء وجدولة دروس حضورية | C4: غير جاهز | D4: قيد التنفيذ | E4: مدعوم بالكامل | F4: Lesson/Create | G4: LessonController.Create + LessonInputDto | H4: يدعم التاريخ والوقت والمدة والعنوان والمجموعة/الكورس. | I4: WP-T4
A5: FR-I06 | B5: إعداد مجموعة كورس أونلاين | C5: غير جاهز | D5: لم يبدأ | E5: مدعوم بالكامل | F5: Course/ConfigureGroupSchedule | G5: GroupScheduleInputDto | H5: نفس مسار الجدولة، ويعمل للمجموعة بغض النظر عن نمط التسليم؛ DeliveryType موجود في الكورس. | I5: WP-T2
A6: FR-I08 | B6: إنشاء وجدولة دروس أونلاين | C6: غير جاهز | D6: قيد التنفيذ | E6: مدعوم بالكامل | F6: Lesson/Create + ConfigureMeeting | G6: LessonController.Create/ConfigureMeeting | H6: يدعم MeetingPlatform وMeetingUrl وInstructions. | I6: WP-T4
A7: FR-T06 | B7: معالجة دفع الحجز | C7: غير جاهز | D7: قيد التنفيذ | E7: مدعوم بالكامل | F7: Booking/Submit + Booking/Decide | G7: BookingService.DecideBookingAsync | H7: عند القبول: يتحقق من الرصيد، يخصم السعر، يحسب العمولة، ويضيف صافي المعلم ضمن transaction. | I7: WP-S1, WP-T5
A8: FR-T11 | B8: تقييم المعلم بعد الجلسة | C8: غير جاهز | D8: قيد التنفيذ | E8: مدعوم بالكامل | F8: Booking/Rate | G8: BookingService.RateTeacherAsync | H8: يشترط Completed ويمنع التقييم المكرر على نفس الحجز. | I8: WP-S4
A9: FR-W03a | B9: خصم رسوم التسجيل من محفظة الطالب | C9: جزئي | D9: قيد التنفيذ | E9: مدعوم بالكامل | F9: JoinRequest/Decide + Booking/Decide | G9: JoinRequestService.DecideAsync / BookingService.DecideBookingAsync | H9: مسار الانضمام أيضًا يخصم الرسوم عند القبول إذا كانت الرسوم > 0. | I9: WP-W1
A10: FR-W03b | B10: إيداع أرباح المعلم بعد العمولة | C10: جزئي | D10: قيد التنفيذ | E10: مدعوم بالكامل | F10: JoinRequest/Decide + Booking/Decide | G10: WalletTransaction InstructorCredit | H10: يحوّل صافي الرسوم للمعلم بعد العمولة. | I10: WP-W2
A11: FR-P04 | B11: عرض حضور الطالب (ولي أمر) | C11: جاهز | D11: جاهز (أصلي) | E11: مدعوم بالكامل | F11: Parent/ChildAttendance | G11: ParentService.GetChildAttendanceAsync | H11: يتحقق من ParentStudentLinks قبل الإرجاع. | I11: —
A12: FR-P05 | B12: عرض نتائج الامتحانات (ولي أمر) | C12: جاهز | D12: جاهز (أصلي) | E12: مدعوم بالكامل | F12: Parent/ChildExamResults | G12: ParentService.GetChildExamResultsAsync | H12: يتحقق من الرابط قبل إرجاع النتائج. | I12: —
A13: FR-P06 | B13: احتساب نسبة الحضور | C13: جاهز | D13: جاهز (أصلي) | E13: مدعوم بالكامل | F13: Parent/MyChildren | G13: ParentService.GetMyChildrenAsync | H13: يحسب AttendanceRatePercent من الحضور/الإجمالي. | I13: —
... A38: FR-T10 | B38: إدارة طلبات الحجز (معلم) | C38: غير مغطى بالتقرير | D38: قيد التنفيذ | E38: مدعوم بالكامل | F38: Booking/TeacherBookings + Decide | G38: BookingService.GetTeacherBookingsAsync / DecideBookingAsync | H38: فلترة بالحالة والتحقق من ملكية المعلم. | I38: WP-T5

Sheet 02_API_Backend_Verification
A1: # | B1: Controller | C1: Method | D1: Path | E1: Request/Body من Excel | F1: Swagger Response | G1: FE Function | H1: FE File | I1: Excel Link Status | J1: WP | K1: JSON Required? | L1: Sample Received? | M1: حكم Backend | N1: دليل الكود | O1: تفصيل/ملاحظة | P1: ملاحظات Excel
A2: 1 | B2: Booking | C2: POST | D2: /api/Booking/Submit | E2: body: teacherId, subjectId, gradeId, teachingMode, date, startTime, durationMinutes, studentNote | F2: OperationResult | G2: submitBooking | H2: bookings.ts | I2: needs correction in FE | J2: WP-S1 | K2: لا | L2: — | M2: موجود ومطابق | N2: BookingController.Submit + BookingInputDto | O2: OperationResult + ReturnId booking.Id | P2: الـFrontend القديم كان يستخدم courseId/BookingRow؛ الـBackend الحالي يستخدم subjectId/gradeId/teachingMode ويرجع ReturnId.
A3: 2 | B3: Booking | C3: POST | D3: /api/Booking/Decide | E3: body: bookingId, accept, rejectionReason | F3: OperationResult | G3: decideBooking | H3: bookings.ts | I3: يحتاج تصحيح | J3: WP-T5 | K3: لا | L3: — | M3: موجود ومطابق | N3: BookingController.Decide + BookingDecisionDto | O3: Accept وليس approve | P3: الكود يرسل approve بدل accept
A4: 3 | B4: Booking | C4: POST | D4: /api/Booking/Cancel | E4: query: bookingId, reason | F4: OperationResult | G4: cancelBooking | H4: bookings.ts | I4: يحتاج تصحيح | J4: (بديل) | K4: لا | L4: — | M4: موجود ومطابق | N4: BookingController.Cancel + CancelBookingAsync | O4: bookingId/reason، وStudent/CancelBooking أيضًا موجود | P4: الطالب يفضّل Student/CancelBooking
A5: 4 | B5: Booking | C5: POST | D5: /api/Booking/Complete | E5: query: bookingId | F5: OperationResult | G5: completeBooking | H5: bookings.ts | I5: يحتاج تصحيح | J5: WP-T5 | K5: لا | L5: — | M5: موجود ومطابق | N5: BookingController.Complete | O5: OperationResult
A6: 5 | B6: Booking | C6: POST | D6: /api/Booking/Rate | E6: body: bookingId, ratingValue, review | F6: OperationResult | G6: rateBooking | H6: bookings.ts | I6: يحتاج تصحيح | J6: WP-S4 | K6: لا | L6: — | M6: موجود ومطابق | N6: BookingController.Rate + RateTeacherDto | O6: RatingValue/Review | P6: الكود يرسل rating/comment
A7: 6 | B7: Booking | C7: GET | D7: /api/Booking/MyBookings | E7: — | F7: غير موثّق | G7: listMyBookings | H7: bookings.ts | I7: يحتاج تحقق | J7: — | K7: لا | L7: — | M7: موجود لكن schema معروف من DTO | N7: BookingController.MyBookings | O7: List<BookingDto> | P7: لا تستخدمه أي مهمة بالخطة (الطالب يستخدم Student/MyBookings)؛ لا عينة مطلوبة
A8: 7 | B8: Booking | C8: GET | D8: /api/Booking/TeacherBookings | E8: query: status(1..6) | F8: غير موثّق | G8: listTeacherBookings | H8: bookings.ts | I8: يحتاج تصحيح | J8: WP-T5 | K8: نعم | L8: لا | M8: موجود ومطابق | N8: BookingController.TeacherBookings | O8: BookingStatus? رقمي/enum | P8: الكود يرسل اسم الحالة نصًا؛ المطلوب رقم
A9: 8 | B9: Booking | C9: GET | D9: /api/Booking/TeacherRescheduleRequests | E9: query: status(1..4) | F9: غير موثّق | G9: — | H9: bookings.ts | I9: ناقص | J9: WP-T5 | K9: نعم | L9: لا | M9: موجود ومطابق | N9: BookingController.TeacherRescheduleRequests | O9: RescheduleRequestStatus? | P9: أسماء الحالات 1..4 غير موثّقة
A10: 9 | B10: Booking | C10: POST | D10: /api/Booking/DecideReschedule | E10: body: requestId, approve, rejectionReason | F10: OperationResult | G10: — | H10: bookings.ts | I10: ناقص | J10: WP-T5 | K10: لا | L10: — | M10: موجود ومطابق | N10: BookingController.DecideReschedule | O10: RequestId/Approve/RejectionReason
A11: 10 | B11: Course | C11: POST | D11: /api/Course/GetPublished | E11: body: DataTable (searchValue, sortColumn, sortColumnDirection, pageSize, skip) | F11: غير موثّق (مربوط سابقًا) | G11: listPublishedCoursesPage | H11: courses.ts | I11: جاهز | J11: (عام) | K11: لا | L11: — | M11: موجود ومطابق | N11: CourseController.GetPublished | O11: Paged wrapper recordsFiltered/TotalCount/Data
A12: 11 | B12: Course | C12: POST | D12: /api/Course/GetAll | E12: body: DataTable | F12: غير موثّق | G12: listAllCoursesForAdmin | H12: courses.ts | I12: يحتاج تحقق | J12: WP-T1 | K12: نعم | L12: لا | M12: موجود ومطابق | N12: CourseController.GetAll | O12: يفلتر للمعلم حسب Teacher.UserId | P12: هل يفلتر حسب المعلم؟ (Q-01)
A13: 12 | B13: Course | C13: GET | D13: /api/Course/GetById | E13: query: id | F13: غير موثّق | G13: getPublishedCourse | H13: courses.ts | I13: جاهز | J13: (عام) | K13: لا | L13: — | M13: موجود ومطابق | N13: CourseController.GetById | O13: publishedOnly=true
A14: 13 | B14: Course | C14: GET | D14: /api/Course/GetMineById | E14: query: id | F14: غير موثّق | G14: — | H14: courses.ts | I14: ناقص | J14: WP-T1, T2, T3, T4 | K14: نعم | L14: لا | M14: موجود لكن لا يعيد groupId في CourseListItemDto | N14: CourseController.GetMineById + CourseService.Project | O14: يحتاج frontend إلى مصدر groupId آخر؛ Q-02 | P14: هل يرجع المجموعات/groupId؟ (Q-02)
A15: 14 | B15: Course | C15: GET | D15: /api/Course/GetGroupStudents | E15: query: groupId, keyword | F15: غير موثّق | G15: — | H15: courses.ts | I15: ناقص | J15: WP-T3 | K15: نعم | L15: لا | M15: موجود ومطابق | N15: CourseController.GetGroupStudents | O15: يتحقق من ownership | P15: الحقول المرجعة (اسم/هاتف/موقع؟)
A16: 15 | B16: Course | C16: POST | D16: /api/Course/CreateEdit | E16: body: id, teacherId, subjectId, categoryId, title, description, price, deliveryType(1|2), maxStudents, groupName, gradeId, saveAsDraft | F16: OperationResult | G16: — | H16: courses.ts | I16: ناقص | J16: WP-T1 | K16: لا | L16: — | M16: موجود ومطابق | N16: CourseController.CreateEdit + CourseInputDto | O16: teacherId/categoryId/gradeId/groupName... | P16: teacherId مطلوب بالـ DTO (Q-03)
A17: 16 | B17: Course | C17: POST | D17: /api/Course/ConfigureGroupSchedule | E17: body: groupId, maxStudents, courseStartDate, courseEndDate, defaultLessonDurationMinutes, scheduleDays[{dayOfWeek,startTime}] | F17: OperationResult | G17: — | H17: courses.ts | I17: ناقص | J17: WP-T2 | K17: لا | L17: — | M17: موجود ومطابق | N17: CourseController.ConfigureGroupSchedule + GroupScheduleInputDto | O17: جدول أيام متكرر
A18: 17 | B18: Lesson | C18: POST | D18: /api/Lesson/Create | E18: body: id, groupId, courseId, title, scheduledDate, startTime, durationMinutes, orderIndex, meetingPlatform, meetingUrl, meetingInstructions, room | F18: OperationResult | G18: createLesson | H18: lessons.ts | I18: يحتاج تصحيح | J18: WP-T4 | K18: لا | L18: — | M18: موجود ومطابق | N18: LessonController.Create + LessonInputDto | O18: OperationResult | P18: الكود يتوقع LessonRow
A19: 18 | B19: Lesson | C19: PUT | D19: /api/Lesson/Update | E19: نفس Create | F19: OperationResult | G19: updateLesson | H19: lessons.ts | I19: يحتاج تصحيح | J19: WP-T4 | K19: لا | L19: — | M19: موجود ومطابق | N19: LessonController.Update | O19: OperationResult
A20: 19 | B20: Lesson | C20: PUT | D20: /api/Lesson/ConfigureMeeting | E20: body: lessonId, meetingPlatform, meetingUrl, meetingInstructions | F20: OperationResult | G20: configureLessonMeeting | H20: lessons.ts | I20: يحتاج تصحيح | J20: WP-T4 | K20: لا | L20: — | M20: موجود ومطابق | N20: LessonController.ConfigureMeeting | O20: MeetingPlatform/URL
A21: 20 | B21: Lesson | C21: PUT | D21: /api/Lesson/Cancel | E21: body: lessonId, reason | F21: OperationResult | G21: cancelLesson | H21: lessons.ts | I21: يحتاج تصحيح | J21: WP-T4 | K21: لا | L21: — | M21: موجود ومطابق | N21: LessonController.Cancel | O21: LessonCancelDto
A22: 21 | B22: Lesson | C22: GET | D22: /api/Lesson/GetSchedule | E22: query: courseId, groupId | F22: غير موثّق | G22: getLessonSchedule | H22: lessons.ts | I22: يحتاج تحقق | J22: WP-T4 | K22: نعم | L22: لا | M22: موجود لكن يحتاج عينة JSON فقط للتأكد من الشكل النهائي | N22: LessonController.GetSchedule | O22: List/DTO غير موثق في Swagger
A23: 22 | B23: Parent | C23: GET | D23: /api/Parent/MyChildren | E23: — | F23: غير موثّق (النوع بالكود) | G23: getMyChildren | H23: parent.ts | I23: جاهز | J23: WP-P1 | K23: لا | L23: — | M23: موجود ومطابق | N23: ParentController.MyChildren | O23: ChildOverviewDto | P23: unreadNotificationsCount موجود بالنوع
A24: 23 | B24: Parent | C24: GET | D24: /api/Parent/ChildAttendance | E24: query: studentId, from, to | F24: غير موثّق | G24: getChildAttendance | H24: parent.ts | I24: جاهز | J24: WP-P1 | K24: لا | L24: — | M24: موجود ومطابق | N24: ParentController.ChildAttendance | O24: يتحقق من ParentStudentLinks
A25: 24 | B25: Parent | C25: GET | D25: /api/Parent/ChildExamResults | E25: query: studentId | F25: غير موثّق | G25: getChildExamResults | H25: parent.ts | I25: جاهز | J25: WP-P1 | K25: لا | L25: — | M25: موجود ومطابق | N25: ParentController.ChildExamResults | O25: يتحقق من ParentStudentLinks
A26: 25 | B26: Student | C26: GET | D26: /api/Student/Dashboard | E26: — | F26: غير موثّق (النوع بالكود) | G26: getStudentDashboard | H26: student.ts | I26: جاهز | J26: WP-S6 | K26: لا | L26: — | M26: موجود ومطابق | N26: StudentController.Dashboard | O26: StudentDashboardDto | P26: activeCourses لـ WP-S6
A27: 26 | B27: Student | C27: GET | D27: /api/Student/MyRequests | E27: query: status(1..6) | F27: غير موثّق | G27: getStudentMyRequests | H27: student.ts | I27: جاهز | J27: WP-S2 | K27: لا | L27: — | M27: موجود ومطابق | N27: StudentController.MyRequests | O27: BookingStatus?
A28: 27 | B28: Student | C28: GET | D28: /api/Student/GetBooking | E28: query: id | F28: غير موثّق | G28: — | H28: student.ts | I28: ناقص | J28: WP-S2, S3, S4 | K28: نعم | L28: لا | M28: موجود ومطابق | N28: StudentController.GetBooking | O28: Booking detail | P28: هل يتضمن isRated/تفاصيل الدفع؟
A29: 28 | B29: Student | C29: GET | D29: /api/Student/MyBookings | E29: — | F29: غير موثّق | G29: getStudentMyBookings | H29: student.ts | I29: جاهز | J29: WP-S2 | K29: لا | L29: — | M29: موجود ومطابق | N29: StudentController.MyBookings | O29: confirmed bookings
A30: 29 | B30: Student | C30: GET | D30: /api/Student/BookingPayment | E30: query: bookingId | F30: غير موثّق | G30: — | H30: student.ts | I30: ناقص | J30: WP-W1 | K30: نعم | L30: لا | M30: موجود ومطابق | N30: StudentController.BookingPayment | O30: BookingPaymentDto
A31: 30 | B31: Student | C31: POST | D31: /api/Student/CancelBooking | E31: body: bookingId, reason | F31: OperationResult | G31: — | H31: student.ts | I31: ناقص | J31: WP-S2 | K31: لا | L31: — | M31: موجود ومطابق | N31: StudentController.CancelBooking | O31: CancelBookingDto
A32: 31 | B32: Student | C32: POST | D32: /api/Student/RequestReschedule | E32: body: bookingId, proposedDate, proposedStartTime, note | F32: OperationResult | G32: — | H32: student.ts | I32: ناقص | J32: WP-S3 | K32: لا | L32: — | M32: موجود ومطابق | N32: StudentController.RequestReschedule | O32: RescheduleRequestInputDto
A33: 32 | B33: Student | C33: GET | D33: /api/Student/MyRescheduleRequests | E33: — | F33: غير موثّق | G33: — | H33: student.ts | I33: ناقص | J33: WP-S3 | K33: نعم | L33: لا | M33: موجود ومطابق | N33: StudentController.MyRescheduleRequests | O33: List<RescheduleRequestDto> | P33: أسماء حالات الطلب
A34: 33 | B34: Student | C34: GET | D34: /api/Student/Schedule | E34: query: From, To, CourseId, TeacherId, Mode(1|2) | F34: غير موثّق (النوع بالكود) | G34: getStudentSchedule | H34: student.ts | I34: جاهز | J34: WP-S5 | K34: لا | L34: — | M34: موجود ومطابق | N34: StudentController.Schedule | O34: StudentScheduleFilterDto
A35: 34 | B35: Student | C35: GET | D35: /api/Student/GetLesson | E35: query: id | F35: غير موثّق | G35: — | H35: student.ts | I35: ناقص | J35: WP-S5 | K35: نعم | L35: لا | M35: موجود ومطابق | N35: StudentController.GetLesson | O35: StudentLessonDetailDto
A36: 35 | B36: Student | C36: GET | D36: /api/Student/GetCourse | E36: query: id | F36: غير موثّق | G36: — | H36: student.ts | I36: ناقص | J36: WP-S6 | K36: نعم | L36: لا | M36: موجود ومطابق | N36: StudentController.GetCourse | O36: StudentCourseDetailDto
A37: 36 | B37: Student | C37: GET | D37: /api/Student/Attendance | E37: query: from, to, courseId | F37: غير موثّق | G37: — | H37: student.ts | I37: ناقص | J37: WP-S7 | K37: نعم | L37: لا | M37: موجود ومطابق | N37: StudentController.Attendance | O37: StudentAttendanceDto
A38: 37 | B38: Student | C38: GET | D38: /api/Student/ExamResults | E38: query: courseId | F38: غير موثّق | G38: — | H38: student.ts | I38: ناقص | J38: WP-S8 | K38: نعم | L38: لا | M38: موجود ومطابق | N38: StudentController.ExamResults | O38: StudentExamResultDto
A39: 38 | B39: Student | C39: GET | D39: /api/Student/Progress | E39: — | F39: غير موثّق (StudentProgressDto بالكود) | G39: — | H39: student.ts | I39: ناقص | J39: WP-S9, S7 | K39: لا | L39: — | M39: موجود ومطابق | N39: StudentController.Progress | O39: StudentProgressDto | P39: النوع موجود بالكود فقط
A40: 39 | B40: Student | C40: GET | D40: /api/Student/Notifications | E40: query: unreadOnly, skip, pageSize | F40: غير موثّق | G40: getStudentNotifications | H40: student.ts | I40: جاهز | J40: (FR-S12) | K40: لا | L40: — | M40: موجود ومطابق | N40: StudentController.Notifications | O40: StudentNotificationDto
A41: 40 | B41: Student | C41: POST | D41: /api/Student/MarkNotificationRead | E41: query: id | F41: OperationResult | G41: markStudentNotificationRead | H41: student.ts | I41: جاهز | J41: (FR-S12) | K41: لا | L41: — | M41: موجود ومطابق | N41: StudentController.MarkNotificationRead | O41: OperationResult
A42: 41 | B42: Teacher | C42: POST | D42: /api/Teacher/Search | E42: body: TeacherSearchFilterDto | F42: غير موثّق | G42: searchTeachers | H42: teachers.ts | I42: جاهز | J42: (عام) | K42: لا | L42: — | M42: موجود ومطابق | N42: TeacherController.Search | O42: TeacherSearchFilterDto
A43: 42 | B43: Teacher | C43: GET | D43: /api/Teacher/PublicProfile | E43: query: id | F43: غير موثّق | G43: getTeacherPublicProfile | H43: teachers.ts | I43: جاهز | J43: WP-S1 | K43: لا | L43: — | M43: موجود ومطابق | N43: TeacherController.PublicProfile | O43: Public profile | P43: الأسماء فقط للمواد/الصفوف (بدون IDs)
A44: 43 | B44: Teacher | C44: GET | D44: /api/Teacher/Availability | E44: query: teacherId, mode, date | F44: غير موثّق | G44: getTeacherAvailability | H44: teachers.ts | I44: جاهز | J44: WP-S1 | K44: لا | L44: — | M44: موجود ومطابق | N44: TeacherController.Availability | O44: TeacherAvailability
A45: 44 | B45: Teacher | C45: POST | D45: /api/Teacher/SetAvailability | E45: body: slots[...] | F45: OperationResult | G45: setMyTeacherAvailability | H45: teachers.ts | I45: جاهز | J45: (FR-T09) | K45: لا | L45: — | M45: موجود ومطابق | N45: TeacherController.SetAvailability | O45: OperationResult
A46: 45 | B46: Teacher | C46: POST | D46: /api/Teacher/UpdateProfile | E46: body: TeacherProfileInputDto | F46: OperationResult | G46: updateMyTeacherProfile | H46: teachers.ts | I46: جاهز | J46: (FR-T08) | K46: لا | L46: — | M46: موجود ومطابق | N46: TeacherController.UpdateProfile | O46: TeacherProfileInputDto
A47: 46 | B47: Teacher | C47: GET | D47: /api/Teacher/CreateEditModal | E47: query: id | F47: غير موثّق | G47: getGradesList | H47: teachers.ts | I47: يحتاج تحقق | J47: WP-T1, S1 | K47: نعم | L47: لا | M47: موجود؛ محتوى الـModal يحدد Teacher + Grades فقط | N47: TeacherController.CreateEditModal | O47: لا يعيد Subject list مباشرة | P47: مصدر محتمل للصفوف والمواد (Q-04)
A48: 47 | B48: Constant | C48: POST | D48: /api/Constant/GetAll | E48: body: DataTable | F48: غير موثّق | G48: (admin-constants.ts) | H48: admin-constants.ts | I48: يحتاج تحقق | J48: WP-T1, S1 | K48: نعم | L48: لا | M48: موجود | N48: ConstantController.GetAll | O48: يدعم DataTableRequestDto | P48: مصدر محتمل لـ subjectId/categoryId (Q-04)
A49: 48 | B49: Wallet | C49: GET | D49: /api/Wallet/MyWallet | E49: — | F49: غير موثّق (النوع بالكود) | G49: getMyWallet | H49: wallet.ts | I49: جاهز | J49: WP-S1 | K49: لا | L49: — | M49: موجود ومطابق | N49: WalletController.MyWallet | O49: Wallet DTO
